Workbook
Name DADOS: #REF!
Name DATA1: #REF!
Name DATA1_1: #REF!
Name DATA10: #REF!
Name DATA10_1: #REF!
Name DATA100: #REF!
Name DATA100_1: #REF!
Name DATA101: #REF!
Name DATA101_1: #REF!
Name DATA102: #REF!
Name DATA102_1: #REF!
Name DATA103: #REF!
Name DATA103_1: #REF!
Name DATA104: #REF!
Name DATA104_1: #REF!
Name DATA105: #REF!
Name DATA105_1: #REF!
Name DATA106: #REF!
Name DATA106_1: #REF!
Name DATA107: #REF!
Name DATA107_1: #REF!
Name DATA108: #REF!
Name DATA108_1: #REF!
Name DATA109: #REF!
Name DATA109_1: #REF!
Name DATA11: #REF!
Name DATA11_1: #REF!
Name DATA110: #REF!
Name DATA110_1: #REF!
Name DATA111: #REF!
Name DATA111_1: #REF!
Name DATA112: #REF!
Name DATA112_1: #REF!
Name DATA113: #REF!
Name DATA113_1: #REF!
Name DATA114: #REF!
Name DATA114_1: #REF!
Name DATA115: #REF!
Name DATA115_1: #REF!
Name DATA116: #REF!
Name DATA116_1: #REF!
Name DATA117: #REF!
Name DATA117_1: #REF!
Name DATA118: #REF!
Name DATA118_1: #REF!
Name DATA119: #REF!
Name DATA119_1: #REF!
Name DATA12: #REF!
Name DATA12_1: #REF!
Name DATA120: #REF!
Name DATA120_1: #REF!
Name DATA121: #REF!
Name DATA121_1: #REF!
Name DATA122: #REF!
Name DATA122_1: #REF!
Name DATA123: #REF!
Name DATA123_1: #REF!
Name DATA124: #REF!
Name DATA124_1: #REF!
Name DATA125: #REF!

Sheet NOTAS
A1: PRIORIDADE LESTE | B1: LEVANTADOR | C1: DATA DESPACHO | D1: ID SISCO | E1: PROTOCOLO | F1: TIPO NOTA | G1: DATA ABERTURA | H1: PRIORIDADE | I1: STATUS SAP | J1: STATUS SISCO | K1: STATUS LIST | L1: FASE | M1: PAT | N1: REGIONAL | O1: MUNICIPIO | P1: DISTANCIA BT | Q1: DISTANCIA MT | R1: DISTANCIA TRAFO | S1: POSTE PREVISTO BT | T1: POSTE PREVISTO MT | U1: NOME | V1: CONTA CONTRATO | W1: INSTALAÇÃO | X1: ENDEREÇO | Y1: LOCALIDADE | Z1: LATITUDE | AA1: LONGITUDE | AB1: INFORMAÇÕES | AC1: TEXTO | AD1: TEXTO_GERAL | CJ1: INFORMAÇÕES EXTRAS
B2: 0 | D2: 660688 | E2: 1106211252 | F2: UNI | G2: 45939 | H2: 0 | I2: CANC | J2: 0 | K2: 0 | L2: MO | M2: PAT1 | N2: CENTRO | O2: PERITORÓ | P2: 35.63 | Q2: 80.77 | R2: 107.66 | S2: 0.89075 | T2: 0.89744444 | U2: ANTONIO MARCOS FERREIRA DA SILVA | V2: 3024429341 | W2: 2001090081 | X2: BR 135 10 / CENTRO | Y2: URBANO | Z2: -4.3844089 | AA2: -44.339222 | AB2: PRÓXIMO A PROFESSORA ROSÂNGELA | CJ2: 09.10.2025 16:58:28 U5511235 20251007008283101 CIENTE DO PRAZO DE 05 DIAS ÚTEIS PARA VISTORIA E EXECUÇÃO DO SERVIÇO. CLIENTE AFIRMA QUE JÁ POSSUI O PADRÃO INSTALADO DENTRO DO LIMITE DA VIA DISJUNTOR: 25A Descrição problema FASE: medidor_monofasico PADRÃO INSTALADO: SIM PONTO DE REFERÊNCIA: PRÓXIMO A PROFESSORA ROSÂNGELA PÚBLICA E CIENTE QUE CASO A INEXISTÊNCIA SEU PEDIDO SERÁ REJEITADO. Rede de BT MAIS APROXIMADA A 100 METROS,CLIENTE JÁ POSSUI PADRÃO MONTADO SOLICITAÇÃO VIA BACKOFFICE (MARANHAO) Nº DO PROTOCOLO DO SITE TELEFONE: (99) 99220-7756
B3: 0 | D3: 662478 | E3: 1108555059 | F3: UNI | G3: 46010 | H3: 0 | I3: REJE | J3: Pré Análise | K3: Notas para expurgos | L3: 0 | M3: PAT1 | N3: LESTE | O3: TIMBIRAS | P3: 9.7 | Q3: 48.54 | R3: 87.61 | S3: 0.2425 | T3: 0.53933333 | U3: WILLYAM DEYVID LIMA CALDAS | V3: 3025006444 | W3: 2001113154 | X3: MARIA CILENE S/N / SANTAREM | Y3: URBANO | Z3: -4.24833 | AA3: -43.933932 | CJ3: 19.12.2025 09:47:12 U5516018 20251203008335532PADRÃO INSTALADO: SIM FASE: MONOFASICO DISJUNTOR: 25 APONTO DE REFERÊNCIA:TELEFONE: (99) 98267-5079CLIENTE AFIRMA QUE JÁ CIENTE QUE CASO A INEXISTÊNCIA SEU PEDIDO SERÁ REJEITADO. CIENTE DO Descrição problema Maior que 100mts POSSUI O PADRÃO INSTALADO DENTRO DO LIMITE DA VIA PÚBLICA E PRAZO DE 05 DIAS ÚTEIS PARA VISTORIA E EXECUÇÃO DO SERVIÇO. SOLICITAÇÃO VIA BACKOFFICE MANº DO PROTOCOLO DO SITE
B4: 0 | D4: 560365 | E4: 1109597721 | F4: UNR | G4: 46043 | H4: 0 | I4: CANC | J4: Liberado para Levantamento | K4: Em levantamento | L4: MO | M4: PAT1 | N4: CENTRO | O4: LIMA CAMPOS | P4: 17.46 | Q4: 10.23 | R4: 70.31 | S4: 0.4365 | T4: 0.11366667 | U4: CELIA PEREIRA DA CRUZ | V4: 3025220667 | W4: 2001121574 | X4: ANTONIO LUCAS CRUZ S/N / CENTRO | Y4: RURAL | Z4: -4.5136508 | AA4: -44.471581 | CJ4: 20260106000198923PADRÃO INSTALADO: SIM FASE: MONOFASICO DISJUNTOR: 21.01.2026 11:49:28 U5514981 25APONTO DE REFERÊNCIA:TELEFONE: (99) 98467-4671CLIENTE AFIRMA QUE JÁ CIENTE QUE CASO A INEXISTÊNCIA SEU PEDIDO SERÁ REJEITADO. CIENTE DO Descrição problema POSSUI O PADRÃO INSTALADO DENTRO DO LIMITE DA VIA PÚBLICA E PRAZO DE 05 DIAS ÚTEIS PARA VISTORIA E EXECUÇÃO DO SERVIÇO. SOLICITAÇÃO VIA BACKOFFICE MANº DO PROTOCOLO DO SITE Sem rede BT para ligar o cliente, rede mas próxima a uns 55 metros, PG do último poste 13036124
B5: 0 | D5: 1894111 | E5: 1109878435 | F5: UNI | G5: 46051 | H5: 0 | I5: CANC | J5: Pré Análise | K5: 0 | L5: MO | M5: PAT1 | N5: CENTRO | O5: PRESIDENTE DUTRA | P5: 44.56 | Q5: 59.95 | R5: 143.21 | S5: 1.114 | T5: 0.66611111 | U5: DANGYLA TASSILA RODRIGUES ALVES CARNIB | V5: 3025294458 | W5: 2001099046 | X5: PRINCIPAL S/N / SAO BENEDITO | Y5: URBANO | Z5: -5.27892 | AA5: -44.479525 | AB5: JDA COMERCIO | CJ5: 29.01.2026 16:34:18 T34411 ATENDIMENTO PRESENCIAL. CEL: 99984626523 CPF REGULAR NA RECEITA: SIM Descrição problema END: RUA PRINCIPAL, S/N, SAO BENEDITO IN: 2001099046 O cliente já é mono mais o cliente que agora rede trifásico mais não tem rede trifásico PADRAO MONO MONTADO NA PAREDE. REF:ESTRADA DA CANAFISTULA SRA DANGYLA TASSILA RODRIGUES ALVES CARNIB SOLICITA REATIVAÇAO NO necessário 90 metros de rede de BT trifásico multiplequisada
B6: 0 | D6: 1894557 | E6: 1109993254 | F6: UNR | G6: 46055 | H6: 0 | I6: CANC | J6: Liberado para Levantamento | K6: Em levantamento | L6: MO | M6: PAT1 | N6: CENTRO | O6: LIMA CAMPOS | P6: 290.93 | Q6: 115.64 | R6: 142.61 | S6: 7.27325 | T6: 1.2848889 | U6: MARIA LUCIA DA CONCEICAO GASPAR | V6: 3025319183 | W6: 2001125364 | X6: SITIO NOVO S/N / CENTRO | Y6: RURAL | Z6: -4.496165 | AA6: -44.571795 | CJ6: ANÁLISE DUP CADASTRO? NÃO 02.02.2026 17:03:53 T12482 ANEXO DOC. DO SOLICITANTE E FORMULÁRIO DE CONEXÃO ASSINADO. CIDADE : LIMA CAMPOS CLIENTE VEIO AO ATENDIMENTO E SOLICITOU CONEXÃO. CIENTE DO PRAZO DE COORD. GEOGRÁFICAS: NÃO APRESENTOU Descrição problema E-MAIL VÁLIDO: NÃO POSSUI ENDEREÇO CORRESPONDÊNCIA: POV SANTO ANTONIO DOS NINAS LIMA CAMPOS ENDEREÇO DA CONEXÃO É O MESMO ENDEREÇO DE CORRESPONDÊNCIA? SIM LOCAL DEMARCADO: NÃO MILHO CONHECIDA COMO DOUTOR PARCELADO: 12 x R$ 36,05 PONTO DE REFERÊNCIA: ENFRENTE A SUA CASA TEM UM PLANTIO DE ARROZ E POSSUI REDE ELÉTRICA PROX. AO IMÓVEL? SIM Rede de BT a 300 metros referência 68056794 SERÁ REJEITADO. TELEFONE: 99981084499 VISTORIA E QUE, EM CASO DE PADRÃO INCOMPLETO/INEXISTENTE, SEU PEDIDO WHATSAPP:99981084499
B7: 0 | D7: 1894891 | E7: 1110247929 | F7: UNI | G7: 46063 | H7: 0 | I7: CANC | J7: Liberado para Levantamento | K7: Em levantamento | L7: MO | M7: PAT1 | N7: CENTRO | O7: VITORINO FREIRE | P7: 26.8 | Q7: 6.47 | R7: 141.87 | S7: 0.67 | T7: 0.071888889 | U7: RENATA BRITO SILVA | V7: 3025388096 | W7: 2001127948 | X7: RUA NAO CADASTRADA S/N / CENTRO | Y7: URBANO | Z7: -4.2786883 | AA7: -45.242538 | AB7: PROX AO MAX BEN GAS. PENULTIMA RUA DO BAIRRO | CJ7: - VITORINO FREIRE MA 10.02.2026 10:16:19 T12653 ANEXO DOC. DO SOLICITANTE, FORMULÁRIO DE CONEXÃO E FORMULÁRIO DE PADRAO ANÁLISE DUP CADASTRO? NÃO AUTORIZAÇÃO BLITZ URBANA? NÃO CLIENTE RENATA BRITO SILVA SOLICITOU CONEXAO NOVA COM COMPADRAO JÁ CLIENTE VEIO AO ATENDIMENTO E SOLICITOU CONEXÃO COM O PADRÃO JÁ COORD. GEOGRÁFICAS: NAO APRESENTOU Cliente fica a 61 metros da rede de baixa tensão, não sendo possível realizar o serviço porque a DEVIDAMENTE MONTADO. CIENTE DO PRAZO DE VISTORIA. Descrição problema E-MAIL VÁLIDO: RENATABRITTO103@GMAIL.COM ENDEREÇO CORRESPONDÊNCIA: AV DOS TUCANOS BAIRRO LUANA LOTE 05 - QD 02 B ENDEREÇO DA CONEXÃO É O MESMO ENDEREÇO DE CORRESPONDÊNCIA? SIM INSTALACAO VIZINHO: 2000906104 LIG. EM PRAÇA PÚBLICA? NAO LOCAL DEMARCADO: SIM MONTADO EM CAMPO MONTADO. NAO
B8: 0 | D8: 1894989 | E8: 1110275419 | F8: UNI | G8: 46064 | H8: 0 | I8: CANC | J8: Pré Análise | K8: 0 | L8: MO | M8: PAT1 | N8: CENTRO | O8: PAULO RAMOS | P8: 75.91 | Q8: 180.62 | R8: 192.78 | S8: 1.89775 | T8: 2.0068889 | U8: JEANNE ARAUJO COSTA | V8: 3025396579 | W8: 2001128522 | X8: I JOAO DA MATA S/N / RES BOA ESPERANCA | Y8: URBANO | Z8: -4.4398283 | AA8: -45.243283 | CJ8: 11.02.2026 09:29:29 U5515375 CIENTE DO PRAZO DE 05 DIAS CLIENTE AFIRMA QUE JÁ POSSUI O PADRÃO INSTALADO DENTRO DO LIMITE DA VIA DISJUNTOR: 25A Descrição problema FASE: Monofásica Não tem rede da equatorial proxima PADRÃO INSTALADO: SIM PONTO DE REFERÊNCIA:NÃO INFORMADO PÚBLICA E CIENTE QUE CASO A INEXISTÊNCIA SEU PEDIDO SERÁ REJEITADO. SOLICITAÇÃO VIA BACKOFFICE MA Nº DO PROTOCOLO DO SITE 20260204000247493 TELEFONE: (98) 98240-3358 ÚTEIS PARA VISTORIA E EXECUÇÃO DO SERVIÇO.
B9: 0 | D9: 1895194 | E9: 1110422398 | F9: UNI | G9: 46069 | H9: 0 | I9: CANC | J9: Pré Análise | K9: 0 | L9: MO | M9: PAT1 | N9: CENTRO | O9: POCAO DE PEDRAS | P9: 133.6 | Q9: 307.41 | R9: 343 | S9: 3.34 | T9: 3.4156667 | U9: PAULO MELO MARTINS | V9: 3025437909 | W9: 2001130190 | X9: MARTINS S/N / NOVA JERUSALEM | Y9: URBANO | Z9: -4.7661183 | AA9: -44.941198 | AB9: FEITO EM 072006 99 9179 5571 PROX A CASA DO SR JOSE | CJ9: 16.02.2026 15:34:43 U5511235 20260212000257469 CIENTE DO PRAZO DE 05 DIAS ÚTEIS PARA VISTORIA E EXECUÇÃO DO SERVIÇO. CLIENTE AFIRMA QUE JÁ POSSUI O PADRÃO INSTALADO DENTRO DO LIMITE DA VIA DISJUNTOR: 25A Descrição problema FASE: medidor_Monofásica Não possui rede BT próxima do local. Sem PG no local PADRÃO INSTALADO: SIM PONTO DE REFERÊNCIA: FEITO EM 072006 99 9179 5571 PROX A CASA DO SR JOSE PÚBLICA E CIENTE QUE CASO A INEXISTÊNCIA SEU PEDIDO SERÁ REJEITADO. SOLICITAÇÃO VIA BACKOFFICE (MARANHAO) Nº DO PROTOCOLO DO SITE TELEFONE: (99) 98527-6572
B10: 0 | D10: 1896486 | E10: 1111146794 | F10: UNR | G10: 46094 | H10: 0 | I10: REJE | J10: Expurgo Concluído | K10: Improdutivo | L10: 0 | M10: PAT3 | N10: LESTE | O10: COLINAS | P10: 1121.26 | Q10: 1235.5 | R10: 1425.26 | S10: 28.0315 | T10: 13.727778 | U10: JOSE OLIVIO DE SA CARDOSO ROSA | V10: 3025639870 | W10: 2001137616 | X10: FAZENDA MANDIOCAL S/N / PORTO ALEGRE | Y10: RURAL | Z10: -5.9224861 | AA10: -44.417462 | AB10: FINAL DO PV CENTRO DO FELIANO, PROX AO CARISVALDO, TRATA-SE DA FAZENDA MANDIOCAL DO ZE OLIVIO, A 4KM | CJ10: 98 8115-5438 ASSINOU FORMULÁRIO DE FINANC. DE PADRÃO? SIM *CLIENTE VEIO AO 13.03.2026 15:22:10 T12500 ANÁLISE DUP CADASTRO? NÃO ATENDIMENTO E SOLICITOU CONEXÃO COM FINANCIAMENTO DE PADRÃO. CIENTE DO AUTORIZAÇÃO BLITZ URBANA? NÃO CC / MD VIZINHO 8686289 /11521903599 COORD. GEOGRÁFICAS: 5.910067600000- 44.417774400000- ; Descrição problema E-MAIL VÁLIDO: VICTORPCROSA@GMAILCOM ENDEREÇO CORRESPONDÊNCIA: FAZENDA MANDIOCAL, PORTO ALEGRE, COLINAS-MA ENDEREÇO DA CONEXÃO É O MESMO ENDEREÇO De CORRESPONDÊNCIA? SIM FELICIANO, PROX AO HAIRAM, PROX AO RENATO FORMULÁRIO DE FINACIAMENTO DE PADRÃO ASSINADOS. LIG. EM PRAÇA PÚBLICA? NÃO LIGAÇÃO NOVA COM FINANCIAMENTO DE PADRAO LOCAL DEMARCADO:NÃO NÃO POSSUI REDE PROX. AO IMÓVEL? NÃO OBS: ENTRAR EM CONTATO COM CLIENTE, DEVIDO AO ACESSO VICTOR ROSA FONE: PADRÃO FINANCIADO: PFC7
B11: 0 | D11: 1907572 | E11: 1111250867 | F11: UNI | G11: 46098 | H11: GIRO NO PRAZO | I11: CANC | J11: Pré Análise | K11: Em levantamento | L11: MO | M11: PAT1 | N11: CENTRO | O11: TRIZIDELA DO VALE | P11: 30.18 | Q11: 19.89 | R11: 107.09 | S11: 0.7545 | T11: 0.221 | U11: MARIA VILANIR DOS SANTOS PIMENTEL | V11: 3025668609 | W11: 2001138628 | X11: STO ANTONIO 12 / STO ANTONIO | Y11: URBANO | Z11: -4.5615467 | AA11: -44.61974 | CJ11: 17.03.2026 17:11:02 T12482 ANEXO DOC. DO SOLICITANTE, FORMULÁRIO DE CONEXÃO E FORMULÁRIO DE PADRAO ANÁLISE DUP CADASTRO? NÃO AUTORIZAÇÃO BLITZ URBANA? NÃO CLIENTE SOLICITOU CONEXAO NOVA COM COMPADRAO JÁ MONTADO EM CAMPO CLIENTE VEIO AO ATENDIMENTO E SOLICITOU CONEXÃO COM O PADRÃO JÁ COORD. GEOGRÁFICAS: XXXXXXXXXX DEVIDAMENTE MONTADO. CIENTE DO PRAZO DE VISTORIA. Descrição problema E-MAIL VÁLIDO: NÃO APRESENTOU ENDEREÇO CORRESPONDÊNCIA: ENDEREÇO DA CONEXÃO É O MESMO ENDEREÇO DE CORRESPONDÊNCIA? SIM Falta construir rede de BT pra atender o cliente a mais do limite permitido pela equatorial INSTALACAO VIZINHO: XXXXXXXXXX LIG. EM PRAÇA PÚBLICA? LOCAL DEMARCADO: SIM MONTADO. NAO PONTO DE REFERÊNCIA: ENFRENTE A CASA DO SIM CONSTRURORA . RUA SEM SAIDA POSSUI REDE PROX. AO IMÓVEL? SIM
B12: 0 | D12: 1907612 | E12: 1111279625 | F12: UNI | G12: 46099 | H12: 0 | I12: REJE | J12: Pré Análise | K12: 0 | L12: 0 | M12: PAT2 | N12: CENTRO | O12: VARGEM GRANDE | P12: 413.66 | Q12: 156.5 | R12: 226.52 | S12: 10.3415 | T12: 1.7388889 | U12: JECIARA SANTOS DE ANDRADE | V12: 3025679660 | W12: 2001139018 | X12: PROJETADA 1 S/N / TRIZIDELA | Y12: URBANO | Z12: -3.5612347 | AA12: -43.919498 | AB12: LT 06 QD 12 PROJETADA 23 | CJ12: "CLIENTE JECIARA SANTOS DE ANDRADE SOLICITOU CONEXAO NOVA COM 06 QUADRA 12 ZONA URBANA DE VARGEM GRANDE MA 18.03.2026 15:56:28 T35429 ANEXO DOC. DO SOLICITANTE, FORMULÁRIO DE CONEXÃO E FORMULÁRIO DE ANÁLISE DUP CADASTRO? NÃO ASSINOU FORMULÁRIO DE FINANC. DE PADRÃO? SIM AUTORIZAÇÃO BLITZ URBANA? NÃO CLIENTE VEIO AO ATENDIMENTO E SOLICITOU CONEXÃO COM FINANCIAMENTO DE COORD. GEOGRÁFICAS: NAO INFORMADO Descrição problema E-MAIL VÁLIDO: NÃO APRESENTOU ENDEREÇO CORRESPONDÊNCIA:LOTEAMENTO NOVA ALIANCA RUA PROJETDA III LOTE ENDEREÇO DA CONEXÃO É O MESMO ENDEREÇO DE CORRESPONDÊNCIA? NAO FINACIAMENTO DE PADRÃO ASSINADOS." FINANCIAMENTO DE PADRAO FPC7 INSTALACAO VIZINHO: NAO INFORMADO LIG. EM PRAÇA PÚBLICA?NAO LOCAL DEMARCADO: SIM NAO PADRÃO FINANCIADO: SIM
B13: 0 | D13: 1912223 | E13: 1111929860 | F13: UNI | G13: 46121 | H13: 0 | I13: CANC | J13: Liberado para Levantamento | K13: Em levantamento | L13: TR | M13: PAT1 | N13: CENTRO | O13: ESPERANTINÓPOLIS | P13: 23.95 | Q13: 19 | R13: 52.9 | S13: 0.59875 | T13: 0.21111111 | U13: MUNICIPIO DE ESPERANTINOPOLIS | V13: 3025856561 | W13: 2001145198 | X13: GENESIO CARVALHO S/N / CENTRO | Y13: URBANO | Z13: -4.88372 | AA13: -44.880895 | AB13: MEDIDOR REFERÊNCIA – 3703-019415-3 | CJ13: (99) 98849-9579 Oi (99) 99141-0688 Claro -------------- Mensagem original -------------- 09.04.2026 21:36:53 U5510610 30 AVISO: Este e-mail foi originado de fora do Grupo Equatorial Energia. Assunto: De: Kleber Carneiro [klebercarneiro10@gmail.com] Descrição problema Enviado: 09/04/2026 13:56 Grato, Kléber Carneiro Não clique em links ou abra anexos, a menos que reconheça o remetente e Para: laise.rabelo@equatorialenergia.com.br; artemilton.torres@equatorialenergia.com.br; grandesclientes.maranhao@equatorialenergia.com.br saiba que o conteúdo é seguro.
B14: 0 | D14: 1974648 | E14: 1112194457 | F14: UNI | G14: 46132 | H14: 0 | I14: REJE | J14: Pré Análise | K14: Em levantamento | L14: 0 | M14: PAT1 | N14: NORTE | O14: SANTA RITA | P14: 88.58 | Q14: 86.62 | R14: 73.82 | S14: 2.2145 | T14: 0.96244444 | U14: ELENILTON BARDOSA | V14: 3025931687 | W14: 2001147773 | X14: PRINCIPAL S/N / POVOADO CASCAVEL | Y14: URBANO | Z14: -3.1887667 | AA14: -44.25205 | CJ14: ,20)* 20.04.2026 11:44:58 T40239 ANEXO DOC. DO SOLICITANTE E FORMULÁRIO DE CONEXÃO ASSINADO. ANÁLISE DUP CADASTRO? SIM / NÃO ATO DA REALIZAÇÃO SERVIÇO. VALOR DE R$ 57,20 (PARC DE 1 VEZES DE R$57 CHECKLIST PADRÃO MONTADO ASSINADO PELO CLIENTE? SIM / CLIENTE VEIO AO ATENDIMENTO E SOLICITOU CONEXÃO. CIENTE DO PRAZO DE COORD. GEOGRÁFICAS: NAO MAPEADO Descrição problema E-MAIL VÁLIDO: ELENILTON BARDOSA ENDEREÇO CORRESPONDÊNCIA: RU APRINCIPAL, POVOADO CASCAVEL CIDADE SANTA ENDEREÇO DA CONEXÃO É O MESMO ENDEREÇO DE CORRESPONDÊNCIA? SIM FINANCIAMENTO PARCIAL DE PADRÃO DO DISJUNTOR, CASO ESTEJA PENDENTE NO PADRÃO INSTALADO EXTERNAMENTE? SIM / NÃO PONTO DE REFERÊNCIA: PROXIMO AO SITIO SAO JOSE POSSUI REDE ELÉTRICA PROX. AO IMÓVEL? SIM / RITA-MA SERÁ REJEITADO. Sem rede falta de padrão cliente ainda não se pradronizou
B15: 0 | D15: 1978181 | E15: 1112533746 | F15: UNR | G15: 46146 | H15: 0 | I15: REJE | J15: Pré Análise | K15: 0 | L15: 0 | M15: PAT2 | N15: CENTRO | O15: GONÇALVES DIAS | P15: 826.64 | Q15: 123.61 | R15: 1238.78 | S15: 20.666 | T15: 1.3734444 | U15: ANGRA CRISTINA DAMACENA FIGUEIREDO | V15: 3026069016 | W15: 2001152035 | X15: PRINCIPAL S/N / CENTRO | Y15: RURAL | Z15: -5.0797569 | AA15: -44.149557 | AB15: NO COMECO DO POVOADO, LUZIA | CJ15: 04.05.2026 11:38:37 T16550 A INSTALAÇÃO POSSUI OU CONTARÁ COM CARREGADORES PARA VEÍCULOS ELÉTRICOS? AMPERAGEM DO DISJUNTOR: 25A ANEXO DOC. DO SOLICITANTE E FORMULÁRIO DE CONEXÃO ASSINADO. ANÁLISE DUP CADASTRO? SIM CASO SIM, INFORMAR DADOS DO CARREGADOR : (Potência e modelo da estação CHECKLIST PADRÃO MONTADO ASSINADO PELO CLIENTE? SIM CLIENTE VEIO AO ATENDIMENTO E SOLICITOU CONEXÃO. CIENTE DO PRAZO DE COORD. GEOGRÁFICAS: 5.073342700000, 44.158955400000 SEM REDE PROXIMA Cliente sem rede de Mt a rede de MT passar em frente a casa do cliente fica só 5 metros da casa Descrição problema E-MAIL VÁLIDO: XXXXXXXXXXXXXXXXXXXXXXXXXXXXXXXXXXXXX ENDEREÇO CORRESPONDÊNCIA: PV LARGES ZONA RURAL ENDEREÇO DA CONEXÃO É O MESMO ENDEREÇO DE CORRESPONDÊNCIA? SIM Expansão rural, não possui rede de bt para atender o cliente,cliente ja possui o padrão montado. FICA UNS 1000M DE DISTANCIA DA REDE INSTALAÇÃO DO VIZINHO: 37977969 Necessidade de obra, no endereço da ligação não possui rede de BT, passa a rede de MT monofasico a PADRÃO INSTALADO EXTERNAMENTE? SIM PONTO DE REFERÊNCIA: LUIZA MARIA, NO COMECO DO POVOADO,
B16: 0 | D16: 1978188 | E16: 1112535950 | F16: UNR | G16: 46146 | H16: 0 | I16: REJE | J16: Pré Análise | K16: 0 | L16: 0 | M16: PAT3 | N16: LESTE | O16: SUCUPIRA DO RIACHÃO | P16: 3494.76 | Q16: 2688.79 | R16: 2636.68 | S16: 87.369 | T16: 29.875444 | U16: RITA MARIA DOS SANTOS SOUSA | V16: 3026068656 | W16: 2001152144 | X16: MATA S/N / RURAL | Y16: RURAL | Z16: -6.4013033 | AA16: -43.548266 | CJ16: TELEFONE: (99) 98487-4227 04.05.2026 14:06:41 U5512834 20260428000398591 8 km do poste 1004231 CLASSE DE CONSUMO: RESIDENCIAL Descrição problema Endereço não localizado NOME DO CLIENTE: RITA MARIA DOS SANTOS SOUSA SOLICITA FINANCIAMENTO DE PADRÃO PARCELADO EM: 024 PONTO DE REFERÊNCIA: NÃO TEM APELIDO: NÃO INFORMADO SOLICITAÇÃO VIA BACKOFFICE (MA) Nº DO PROTOCOLO DO SITE TIPO DE FASE: MONOFÁSICO:
B17: 0 | D17: 1980140 | E17: 1112567806 | F17: UNR | G17: 46147 | H17: 0 | I17: REJE | J17: Pré Análise | K17: 0 | L17: 0 | M17: PAT2 | N17: SUL | O17: GRAJAÚ | P17: 338.06 | Q17: 264.43 | R17: 266.07 | S17: 8.4515 | T17: 2.9381111 | U17: ISAEL DO ESPIRITO SANTO DOS SANTOS | V17: 3026078465 | W17: 2001152422 | X17: CHACARA SANTA LUZIA S/N / ZONA RURAL | Y17: RURAL | Z17: -5.7393717 | AA17: -46.267075 | AB17: PROXIMO A INSTALAÇÃO 41908939 , DEPOIS DA BELA ESTRELA. | CJ17: 05.05.2026 10:00:56 T53617 ? NAO A INSTALAÇÃO POSSUI OU CONTARÁ COM CARREGADORES PARA VEÍCULOS ELÉTRICOS AMPERAGEM DO DISJUNTOR : 25A ANEXO DOC. DO SOLICITANTE, FORMULÁRIO DE CONEXÃO E FORMULÁRIO DE ANÁLISE DUP CADASTRO? NÃO ASSINOU FORMULÁRIO DE FINANC. DE PADRÃO? SIM CARREGADOR : XXXXXXXXXXXXXX CHECKLIST PADRÃO MONTADO ASSINADO PELO CLIENTE? NÃO CIENTE DO PRAZO DE VISTORIA. CLIENTE: ISAEL DO ESPIRITO SANTO DOS SANTOS COORD. GEOGRÁFICAS: NAO LOCALIZADAS Cliente fica a 150 metros dessa instalação 41908939 Descrição problema E-MAIL VÁLIDO: ISAEL2533@GMAIL.COM ENDEREÇO CORRESPONDÊNCIA: CHACARA SANTA LUZIA, S/N, ZONA RURAL. ENDEREÇO DA CONEXÃO É O MESMO ENDEREÇO DE CORRESPONDÊNCIA? SIM ESTRELA. FINACIADO EM 24X DE 18,03 FINACIAMENTO DE PADRÃO ASSINADOS.
B18: 0 | D18: 1980788 | E18: 1112633274 | F18: UNI | G18: 46149 | H18: GIRO NO PRAZO | I18: CANC | J18: Pré Análise | K18: 0 | L18: MO | M18: PAT1 | N18: CENTRO | O18: PRESIDENTE DUTRA | P18: 20.07 | Q18: 21.53 | R18: 65.09 | S18: 0.50175 | T18: 0.23922222 | U18: LUIS ANTONIO LINDOLFO DA SILVA | V18: 3026103494 | W18: 2001153294 | X18: PRINCIPAL S/N / PARQUE DOS IPES | Y18: URBANO | Z18: -5.2934356 | AA18: -44.478846 | AB18: MEDIDOR VIZINHO 37030079427 | CJ18: 07.05.2026 10:20:12 T34411 ANEXO DOC. DO SOLICITANTE E FORMULÁRIO DE CONEXÃO ASSINADO CHECKLIST PADRÃO MONTADO ASSINADO PELO CLIENTE? SIM CLIENTE VEIO AO ATENDIMENTO E SOLICITOU CONEXÃO. CIENTE DO PRAZO DE COORD. GEOGRÁFICAS: 5.292562620000- 44.478204560000- Descrição problema ENDEREÇO CORRESPONDÊNCIA: RD BR 226, PARQUE DOS IPES, S/N, CENTRO NOVA. Necessário construção de rede BT e MT para atender o cliente, rede MT mais próxima fica a 600m PADRÃO INSTALADO EXTERNAMENTE? SIM PONTO DE REFERÊNCIA: MEDIDOR VIZINHO 37030079427 POSSUI REDE ELÉTRICA PROX. AO IMÓVEL? SIM SERÁ REJEITADO. Sr. LUIS ANTONIO LINDOLFO DA SILVA VEIO AO ATENDIMENTO SOLICITAR LIGAÇÃO TELEFONE: 99991276318 VISTORIA E QUE, EM CASO DE PADRÃO INCOMPLETO/INEXISTENTE, SEU PEDIDO WHATSAPP: 99991276318
B19: 0 | D19: 1983481 | E19: 1112769193 | F19: UNR | G19: 46154 | H19: 0 | I19: REJE | J19: Pré Análise | K19: 0 | L19: 0 | M19: PAT3 | N19: LESTE | O19: SUCUPIRA DO RIACHÃO | P19: 1887.87 | Q19: 1912.57 | R19: 1889.72 | S19: 47.19675 | T19: 21.250778 | U19: JOSE FRANCISCO SILVA DOS SANTOS | V19: 3026146738 | W19: 2001154830 | X19: MATA S/N / RURAL | Y19: RURAL | Z19: -6.3681814 | AA19: -43.573366 | CJ19: 12.05.2026 16:32:06 U5514207 20260507000416598 CIENTE QUE CASO A INEXISTÊNCIA SEU PEDIDO SERÁ REJEITADO. CIENTE DO CLIENTE AFIRMA QUE JÁ POSSUI O PADRÃO INSTALADO DENTRO DO LIMITE DA VIA Descrição problema FASE: MONOFASICO DISJUNTOR: SIM PADRÃOINSTALADO: NÃO FINANCIAMENTO 24X PONTO DE REFERÊNCIA: PROX POCO ARTESIANO DA MATA PRAZO DE 05 DIAS PÚBLICA E SOLICITAÇÃO VIA BACKOFFICE (EQUATORIAL MARANHÂO) Nº DO PROTOCOLO DO SITE Sem rede e cliente aceita financiamento 1004231 PG fica a 9km TELEFONE: (99) 98425-1166 ÚTEIS PARA VISTORIA E EXECUÇÃO DO SERVIÇO.
B20: 0 | D20: 1987035 | E20: 1112956037 | F20: UNI | G20: 46162 | H20: 0 | I20: REJE | J20: Pré Análise | K20: 0 | L20: 0 | M20: PAT1 | N20: NOROESTE | O20: CENTRO DO GUILHERME | P20: 18.86 | Q20: 134.4 | R20: 154.1 | S20: 0.4715 | T20: 1.4933333 | U20: KELTON DOUGLAS DUTRA | V20: 3026214148 | W20: 2001157176 | X20: VILA DO VAL S/N / VILA DO VAL | Y20: URBANO | Z20: -2.45833 | AA20: -46.04876 | CJ20: 20.05.2026 09:22:18 U5512834 CIENTE DO PRAZO DE 05 DIAS ÚTEIS PARA VISTORIA E EXECUÇÃO DO SERVIÇO. CLIENTE AFIRMA QUE JÁ POSSUI O PADRÃO INSTALADO DENTRO DO LIMITE DA VIA Cliente nao montou seu pradao e nao tem rede pra ligar o cliente Cliente sem pontalete sem disjuntor sem aterramento sem eletroduto sem estalacao Cliente orientado Descrição problema ENDEREÇO: RUA 03, lotes 16 e 17 do lado esquerdo - vila do val. centro Nº DO PROTOCOLO DO SITE 20260519000439489 PADRÃO INSTALADO: SIM FASE: MONOFÁSICO DISJUNTOR: 25A PONTO DE REFERÊNCIA: lotes 16 e 17 do lado esquerdo PÚBLICA E CIENTE QUE CASO A INEXISTÊNCIA SEU PEDIDO SERÁ REJEITADO. SOLICITAÇÃO VIA BACKOFFICE MA TELEFONE: (98) 98204-6902 a se padronizar do guilherme CEP 65288000
B21: 0 | D21: 1987700 | E21: 1113020981 | F21: UNR | G21: 46164 | H21: 0 | I21: REJE | J21: Pré Análise | K21: 0 | L21: 0 | M21: PAT3 | N21: NORTE | O21: MORROS | P21: 3440.23 | Q21: 3462.87 | R21: 3457.18 | S21: 86.00575 | T21: 38.476333 | U21: EDILSON MARQUES DOS SANTOS | V21: 3026237326 | W21: 2001157933 | X21: PV BARRO BRANCO S/N / PV BARRO BRANCO | Y21: RURAL | Z21: -2.98846 | AA21: -43.757403 | CJ21: Cliente a 3km a frente ,sem acesso ao local. 22.05.2026 08:47:31 U5513369 CLASSE DE CONSUMO: RESIDENCIAL Descrição problema NOME DO CLIENTE: EDILSON MARQUES DOS SANTOS Nº DO PROTOCOLO DO SITE 20260521000444621 PARCELADO EM: 24 VEZES NO VALOR DE R$18,03. PONTO DE REFERÊNCIA: NÃO INFORMADO SOLICITAÇÃO DE LIGAÇÃO COM FINANCIAMENTO DE PADRÃO VIA SITE (MA) Sem rede TELEFONE: (98) 9929-1559 TIPO DE FASE: monofásico
B22: 0 | D22: 1986240 | E22: 1113027419 | F22: UNI | G22: 46164 | H22: 0 | I22: CANC | J22: Pré Análise | K22: 0 | L22: MO | M22: PAT1 | N22: CENTRO | O22: VARGEM GRANDE | P22: 46.58 | Q22: 38.79 | R22: 60.42 | S22: 1.1645 | T22: 0.431 | U22: ITAYANARA MARTINS DIAS | V22: 3026245230 | W22: 2001158235 | X22: PROJETADA S/N / SAO FRANCISCO | Y22: URBANO | Z22: -3.544805 | AA22: -43.927422 | AB22: INSTALAÇÃO : 45073173 VILA DA DODO | CJ22: COORD. GEOGRÁFICAS: LAT 3.545078000000- ; LONG 43.927388790000- 22.05.2026 15:55:32 T41311 ? NÃO A INSTALAÇÃO POSSUI OU CONTARÁ COM CARREGADORES PARA VEÍCULOS ELÉTRICOS AMPERAGEM DO DISJUNTOR : 25 A ANEXO DOC. DO SOLICITANTE E FORMULÁRIO DE CONEXÃO ASSINADO. ANÁLISE DUP CADASTRO?NÃO CHECKLIST PADRÃO MONTADO ASSINADO PELO CLIENTE? SIM DO PRAZO DE VISTORIA E QUE, EM CASO DE PADRÃO INCOMPLETO/INEXISTENTE, Descrição problema E-MAIL VÁLIDO: XXXXXXXXXXXXXXXXXXXXXXXXXXXXXXXXXXXXX ENDEREÇO CORRESPONDÊNCIA: RUA PROJETADA I S/N SAO FRANCISCO VARGEM ENDEREÇO DA CONEXÃO É O MESMO ENDEREÇO DE CORRESPONDÊNCIA? SIM GRANDE MA INSTALAÇÃO : 45073173 ITAYANARA MARTINS DIAS VEIO AO ATENDIMENTO E SOLICITOU CONEXÃO. CIENTE PADRÃO INSTALADO EXTERNAMENTE? SIM PONTO DE REFERÊNCIA: VILA DA DODO POSSUI REDE ELÉTRICA PROX. AO IMÓVEL? SIM SEU PEDIDO SERÁ REJEITADO.
B23: 0 | D23: 1988781 | E23: 1113028488 | F23: UNI | G23: 46164 | H23: GIRO NO PRAZO | I23: CANC | J23: Pré Análise | K23: 0 | L23: MO | M23: PAT1 | N23: CENTRO | O23: VARGEM GRANDE | P23: 40.07 | Q23: 33.33 | R23: 61.06 | S23: 1.00175 | T23: 0.37033333 | U23: ITAYANARA MARTINS DIAS | V23: 3026245531 | W23: 2001158300 | X23: PROJETADA S/N / SAO FRANCISCO | Y23: URBANO | Z23: -3.5447667 | AA23: -43.927436 | AB23: INSTALAÇÃO : 45073173 VILA DA DODO | CJ23: COORD. GEOGRÁFICAS: LAT 3.545078000000- ; LONG 43.927388790000- 22.05.2026 16:57:41 T41311 ? NÃO A INSTALAÇÃO POSSUI OU CONTARÁ COM CARREGADORES PARA VEÍCULOS ELÉTRICOS AMPERAGEM DO DISJUNTOR : 25 A ANEXO DOC. DO SOLICITANTE E FORMULÁRIO DE CONEXÃO ASSINADO. ANÁLISE DUP CADASTRO?NÃO CHECKLIST PADRÃO MONTADO ASSINADO PELO CLIENTE? SIM DO PRAZO DE VISTORIA E QUE, EM CASO DE PADRÃO INCOMPLETO/INEXISTENTE, Descrição problema E-MAIL VÁLIDO: XXXXXXXXXXXXXXXXXXXXXXXXXXXXXXXXXXXXX ENDEREÇO CORRESPONDÊNCIA: RUA PROJETADA I S/N SAO FRANCISCO VARGEM ENDEREÇO DA CONEXÃO É O MESMO ENDEREÇO DE CORRESPONDÊNCIA? SIM GRANDE MA INSTALAÇÃO : 45073173 ITAYANARA MARTINS DIAS VEIO AO ATENDIMENTO E SOLICITOU CONEXÃO. CIENTE PADRÃO INSTALADO EXTERNAMENTE? SIM PONTO DE REFERÊNCIA: VILA DA DODO POSSUI REDE ELÉTRICA PROX. AO IMÓVEL? SIM SEU PEDIDO SERÁ REJEITADO.
B24: 0 | D24: 1987729 | E24: 1113050143 | F24: UNI | G24: 46165 | H24: 0 | I24: REJE | J24: Pré Análise | K24: 0 | L24: 0 | M24: PAT1 | N24: NOROESTE | O24: MIRINZAL | P24: 253.21 | Q24: 67.62 | R24: 349.48 | S24: 6.33025 | T24: 0.75133333 | U24: ANTONIO JOSE ARAUJO CRUZ | V24: 3026248034 | W24: 2001158360 | X24: MACHIXE S/N / MAXIXE | Y24: URBANO | Z24: -2.184715 | AA24: -44.917492 | CJ24: 23.05.2026 08:25:52 U5515486 CLASSE DE CONSUMO: RESIDENCIAL Descrição problema FINANCIAMENTO NOME DO CLIENTE: ANTONIO JOSE ARAUJO CRUZ SOLICITA FINANCIAMENTO DE Nº DO PROTOCOLO DO SITE 20260520000443882 PADRÃO PARCELADO EM: 024 VEZES PONTO DE REFERÊNCIA: XXXXXXXX SOLICITAÇÃO VIA BACKOFFICE MARANHÃO TELEFONE: (98) 98545-7279 TIPO DE FASE: MONOFÁSICO sem rede cliente aceita financiamento
B25: 0 | D25: 651006 | E25: 1089090493 | F25: UNI | G25: 45411 | H25: 0 | I25: ATIV | J25: Pré Análise | K25: 0 | L25: BT | M25: PAT3 | N25: NOROESTE | O25: BOA VISTA DO GURUPI | P25: 0 | Q25: 0 | R25: 0 | S25: 0 | T25: 0 | U25: RAIMUNDO NONATO FERREIRA LOPES | V25: 3020627122 | W25: 2000931988 | X25: RUA NAO CADASTRADA S/N / RURAL | Y25: RURAL | Z25: 0 | AA25: 0 | AB25: A DIREITA SO SR. SERROTE | CJ25: Descrição problema PADRÃO INSTALADO: SIM FASE: monofasico DISJUNTOR: 50A A distância da MT para casa do cliente é de 1.200 mts TELEFONE:98985421755 SOLICITAÇÃO VIA BACKOFFICE MA Nº DO PROTOCOLO DO SITE 20240429006275096 PÚBLICA E CIENTE QUE CASO A INEXISTÊNCIA SEU PEDIDO SERÁ REJEITADO. PONTO DE REFERÊNCIA: A DIREITA SO SR. SERROTE 29.04.2024 14:45:51 U5513960 CIENTE DO PRAZO DE 05 DIAS ÚTEIS PARA VISTORIA E EXECUÇÃO DO SERVIÇO. ENDEREÇO:POVOADO VILA JAPARIQUARA CLIENTE AFIRMA QUE JÁ POSSUI O PADRÃO INSTALADO DENTRO DO LIMITE DA VIA
B26: 0 | D26: 1988835 | E26: 1113120631 | F26: UNR | G26: 46169 | H26: 0 | I26: REJE | J26: Pré Análise | K26: Em levantamento | L26: 0 | M26: PAT1 | N26: NOROESTE | O26: MIRINZAL | P26: 75.44 | Q26: 83.33 | R26: 85.6 | S26: 1.886 | T26: 0.92588889 | U26: JOINA BASTOS TRINDADE | V26: 3026274582 | W26: 2001159471 | X26: RUA NAO CADASTRADA S/N / RURAL | Y26: RURAL | Z26: -2.1282917 | AA26: -44.782217 | CJ26: 20260526000453726 27.05.2026 09:17:30 U5513370 APELIDO: NÃO INFORMADO CLASSE DE CONSUMO: RESIDENCIAL Descrição problema NOME DO CLIENTE: JOINA BASTOS TRINDADE FINANCIAMENTO DE PADRÃO PARCELADO EM: 024 PONTO DE REFERÊNCIA: NÃO INFORMADO SEM rede MT e bt no local SOLICITAÇÃO VIA BACKOFFICE (MA) Nº DO PROTOCOLO DO SITE TELEFONE: (98) 98501-5374 TIPO DE FASE: MONOFÁSICO: medidor_monofasico cliente aceita financiamento
B27: FABIO ALTINO DE SOUZA JUNIOR | C27: 46265 | D27: 2305462 | E27: 1113154784 | F27: UNI | G27: 46170 | H27: 0 | I27: REJE | J27: Liberado para Levantamento | K27: Em levantamento | L27: 0 | M27: PAT2 | N27: SUL | O27: JOAO LISBOA | P27: 593.52 | Q27: 36.1 | R27: 71.13 | S27: 14.838 | T27: 0.40111111 | U27: MARIA DE JESUS SANTOS DE ARAUJO | V27: 3026292564 | W27: 2001160151 | X27: MURAJUBA S/N / LOTEAMENTO MURAJUBA | Y27: URBANO | Z27: -5.3341089 | AA27: -47.405755 | AB27: PRÓXIMO A FAZENDA CHAPARRAL | CJ27: 28.05.2026 14:25:50 T27855 ?NAO A INSTALAÇÃO POSSUI OU CONTARÁ COM CARREGADORES PARA VEÍCULOS ELÉTRICOS AMPERAGEM DO DISJUNTOR : ANEXO DOC. DO SOLICITANTE, FORMULÁRIO DE CONEXÃO E FORMULÁRIO DE ANÁLISE DUP CADASTRO? SIM / ASSINOU FORMULÁRIO DE FINANC. DE PADRÃO? SIM / CHECKLIST PADRÃO MONTADO ASSINADO PELO CLIENTE? SIM / CLIENTE Sra. MARIA DE JESUS SANTOS DE ARAUJO VEIO AO ATENDIMENTO E COORD. GEOGRÁFICAS: NAO LOCALIZADA ; Descrição problema E-MAIL VÁLIDO: NAO INFORMADO ENDEREÇO CORRESPONDÊNCIA: XXXXXXXXXXXXXXXXXXXXXXXXXXXXXXXXXXXXX ENDEREÇO DA CONEXÃO É O MESMO ENDEREÇO DE CORRESPONDÊNCIA? SIM / FINACIAMENTO DE PADRÃO ASSINADOS. IMOVEL LOCALIZADO NA AREA URBANA LIGAÇÃO NOVA – COM FINANCIAMENTO DE PADRÃO PADRAO FINANCIADO: ( X ) SIM FPC7 PADRÃO INSTALADO EXTERNAMENTE? SIM / PONTO DE REFERÊNCIA: Próximo a fazenda chaparral
B28: 0 | D28: 2305485 | E28: 1113194562 | F28: UNR | G28: 46171 | H28: GIRO NO PRAZO | I28: CANC | J28: Pré Análise | K28: 0 | L28: MO | M28: PAT2 | N28: CENTRO | O28: NINA RODRIGUES | P28: 948.15 | Q28: 28.78 | R28: 111.64 | S28: 23.70375 | T28: 0.31977778 | U28: RAIMUNDA DO LAGO CASTRO | V28: 3026308533 | W28: 2001160805 | X28: RUA NAO CADASTRADA S/N / RURAL | Y28: RURAL | Z28: -3.4491242 | AA28: -43.930637 | AB28: CHACARA DO TENENTE | CJ28: 20260528008400704 29.05.2026 17:41:05 U5513370 APELIDO: NÃO INFORMADO CLASSE DE CONSUMO: RESIDENCIAL Descrição problema NOME DO CLIENTE: RAIMUNDA DO LAGO CASTRO FINANCIAMENTO DE PADRÃO PARCELADO EM: 24_-_R$_18,03 PONTO DE REFERÊNCIA: CHACARA DO TENENTE Rede de MT há 130 metros da residência poste 22151919 para referência SOLICITAÇÃO VIA BACKOFFICE (MA) Nº DO PROTOCOLO DO SITE TELEFONE: (98) 99146-6385 TIPO DE FASE: MONOFÁSICO: medidor_monofasico
B29: 0 | D29: 2306469 | E29: 1113244872 | F29: UNR | G29: 46174 | H29: 0 | I29: CANC | J29: Pré Análise | K29: 0 | L29: MO | M29: PAT2 | N29: CENTRO | O29: TUNTUM | P29: 936.83 | Q29: 251.34 | R29: 261.48 | S29: 23.42075 | T29: 2.7926667 | U29: DIOGO TAVARES DA SILVA | V29: 3026325098 | W29: 2001161410 | X29: PA PACAS S/N / PACAS | Y29: RURAL | Z29: -5.2789508 | AA29: -44.775437 | AB29: ENTRE OS POVOADOS PA PACA E SERRA GRANDE HA 200 METROS DA CASA DO JOSE JEFERSON FILHO DO | CJ29: 200 METROS DA CASA DO JOSE JEFERSON FILHO DO COXINHA POPRIEDADE DO CIDADE TUNTUM DIOGO TAVARES DA SILVA CLIENTE SOLICITOU CONEXAO NOVA COM 01.06.2026 15:58:44 T12490 ? CASO SIM, INFORMAR DADOS DO CARREGADOR : (Potência e modelo da A INSTALAÇÃO POSSUI OU CONTARÁ COM CARREGADORES PARA VEÍCULOS ELÉTRICOS AMPERAGEM DO DISJUNTOR : 25 ANEXO DOC. DO SOLICITANTE, FORMULÁRIO DE CONEXÃO E FORMULÁRIO DE ANÁLISE DUP CADASTRO? SIM ASSINOU FORMULÁRIO DE FINANC. DE PADRÃO? SIM AUTORIZAÇÃO BLITZ URBANA? NÃO CASA EM CONSTRUCAO CLIENTE VEIO AO ATENDIMENTO E SOLICITOU CONEXÃO COM FINANCIAMENTO DE COORD. GEOGRÁFICAS: -5.2783018302665115, -44.775652326919335 DIOGO DA AGROFORT. CC VIZINHA 3019560545 HA 2 KM DA SERRA GRANDE Descrição problema E-MAIL VÁLIDO: ZOOTDIOO@GMAIL.COM ENDEREÇO CORRESPONDÊNCIA: ESTRADA DO PV PACA , PACA - ZONA RURAL, ENDEREÇO DA CONEXÃO É O MESMO ENDEREÇO DE CORRESPONDÊNCIA? SIM FINACIAMENTO DE PADRÃO ASSINADOS.
B30: 0 | D30: 2309309 | E30: 1113410522 | F30: UNI | G30: 46182 | H30: GIRO NO PRAZO | I30: CANC | J30: Pré Análise | K30: 0 | L30: MO | M30: PAT1 | N30: CENTRO | O30: PAULO RAMOS | P30: 60.46 | Q30: 230.54 | R30: 248.91 | S30: 1.5115 | T30: 2.5615556 | U30: FRANCISCO ARAUJO OLIVEIRA | V30: 3026378248 | W30: 2001163426 | X30: COLIBRIS 54 / XEXEU | Y30: URBANO | Z30: -4.4417683 | AA30: -45.245603 | CJ30: 09.06.2026 09:15:02 U5511622 CIENTE DO PRAZO DE 05 DIAS ÚTEIS PARA VISTORIA E EXECUÇÃO DO SERVIÇO. CLIENTE AFIRMA QUE JÁ POSSUI O PADRÃO INSTALADO DENTRO DO LIMITE DA VIA Descrição problema PADRÃO INSTALADO: SIM FASE: monofásico DISJUNTOR: 25a PONTO DE REFERÊNCIA: não informado TELEFONE: (98) 98196-9471 PÚBLICA E CIENTE QUE CASO A INEXISTÊNCIA SEU PEDIDO SERÁ REJEITADO. Rede de BT a mais de 90mts SOLICITAÇÃO VIA BACKOFFICE Nº DO PROTOCOLO DO SITE 20260608000475801
B31: 0 | D31: 2309327 | E31: 1113413457 | F31: UNR | G31: 46182 | H31: 0 | I31: REJE | J31: Concluído | K31: Concluído | L31: 0 | M31: PAT1 | N31: LESTE | O31: PARAIBANO | P31: 87.36 | Q31: 88.85 | R31: 256.27 | S31: 2.184 | T31: 0.98722222 | U31: ROSILENE ALENCAR DA SILVA NOLETO | V31: 3026381575 | W31: 2001163576 | X31: PONTA DA SERRA S/N / MARAJA | Y31: RURAL | Z31: -6.4173617 | AA31: -43.974753 | AB31: PROXIMO A CASA DA ANA PAULA NOLETO E PROXIMO A PLACA ARENA ALEXANDRO | CJ31: 09.06.2026 11:47:06 U5511865 CIENTE DO PRAZO DE 05 DIAS ÚTEIS PARA VISTORIA E EXECUÇÃO DO SERVIÇO. CLIENTE AFIRMA QUE JÁ POSSUI O PADRÃO INSTALADO DENTRO DO LIMITE DA VIA DISJUNTOR:25 A Descrição problema FASE: MONOFASICO NOME: ROSILENE ALENCAR DA SILVA NOLETO Nº DO PROTOCOLO DO SITE 20260608008403043 PADRÃO INSTALADO: SIM PLACA ARENA ALEXANDRO PONTO DE REFERÊNCIA: PROXIMO A CASA DA ANA PAULA NOLETO E PROXIMO A Poste mais próximo 100 metros PÚBLICA E CIENTE QUE CASO A INEXISTÊNCIA SEU PEDIDO SERÁ REJEITADO. SOLICITAÇÃO VIA BACKOFFICE (EQUATORIAL MA) TELEFONE: (99) 98491-2916
B32: 0 | D32: 2310168 | E32: 1113442679 | F32: UNR | G32: 46183 | H32: 0 | I32: REJE | J32: Concluído | K32: Concluído | L32: 0 | M32: PAT1 | N32: LESTE | O32: BURITI | P32: 106.35 | Q32: 29.49 | R32: 122.21 | S32: 2.65875 | T32: 0.32766667 | U32: ANATALIA COSTA DE FRANCA | V32: 3026395070 | W32: 2001163990 | X32: BOM JESUS S/N / LAGOA | Y32: RURAL | Z32: -3.945415 | AA32: -42.967588 | AB32: DEPOIS DA FAZENDA BOM ESPERANCA, VIZINHO DA LENIA | CJ32: 10.06.2026 11:51:37 F39989912 150 metros longe da rede ANATALIA COSTA DE FRANCA VEIO AO ATENDIMENTO E SOLICITOU CONEXÃO. ANEXO DOC. DO SOLICITANTE E FORMULÁRIO DE CONEXÃO ASSINADO.TERMOS ANÁLISE DUP CADASTRO? NÃO CHECKLIST PADRÃO MONTADO ASSINADO PELO CLIENTE? SIM CIENTE DO PRAZO DE VISTORIA E QUE EM CASO DE PADRÃO INCOMPLETO/ COORD. GEOGRÁFICAS: NÃO INFORMADO Cliente não se encontra pra fazer o financiamento casa fechada DEVIDAMENTE ANEXADOS NO CRM E CSS Descrição problema E-MAIL VÁLIDO: NÃO INFORMADO ENDEREÇO CORRESPONDÊNCIA: PV BOM JESUS S/N BURITI ZONA RURAL ENDEREÇO DA CONEXÃO É O MESMO ENDEREÇO DE CORRESPONDÊNCIA? SIM INEXISTENTE SEU PEDIDO SERÁ REJEITADO. LIGAÇÃO NOVA COM PADRÃO INSTALADO PADRÃO INSTALADO EXTERNAMENTE? SIM PONTO DE REFERÊNCIA: DEPOIS DA FAZENDA BOM ESPERANCA VIZINHO DA LENIA POSSUI REDE ELÉTRICA PROX. AO IMÓVEL? SIM TELEFONE: 98984387618
B33: 0 | D33: 2309377 | E33: 1113465542 | F33: UNR | G33: 46183 | H33: 0 | I33: REJE | J33: Pré Análise | K33: 0 | L33: 0 | M33: PAT1 | N33: LESTE | O33: BREJO | P33: 183.68 | Q33: 178.42 | R33: 185.48 | S33: 4.592 | T33: 1.9824444 | U33: FLAVIO JOSE MORAES DE SOUSA | V33: 3026402408 | W33: 2001164283 | X33: ESCALVADO S/N / ZONA RURAL | Y33: RURAL | Z33: -3.7514922 | AA33: -42.716524 | CJ33: 10.06.2026 22:27:13 U5514856 BAIRRO: ZONA RURAL CIDADE: BREJO CIENTE DO PRAZO DE 05 DIAS ÚTEIS PARA VISTORIA E EXECUÇÃO DO SERVIÇO CLIENTE A QUE JÁ POSSUI O PADRÃO INSTALADO DENTRO DO LIMITE DA VIA COMPLEMENTO:xxxxxxxxx Cliente Fora de padrão, Sem padrão, e não ta no local para financiar kit poste Cliente fica mais de 300mt da Rede BT e MT a casa fica no fundo da casa que tem um orelhão na porta Descrição problema FASE: Monofásica DISJUNTOR: 50A NOME DO TITULAR: FLAVIO JOSE MORAES DE SOUSA PADRÃO INSTALADO: não PONTO DE REFERÊNCIA:xxxxxxxxx PROTOCOLO DO SITE 20260609000479566 PÚBLICA E CIENTE QUE CASO A INEXISTÊNCIA SEU PEDIDO SERÁ REJEITADO. RUA: ESCALVADO s/n SOLICITAÇÃO BACKOFFICE Telefone: (99) 99167-8647
B34: 0 | D34: 2328156 | E34: 1113680488 | F34: UNR | G34: 46193 | H34: 0 | I34: REJE | J34: Pré Análise | K34: Análise de levantamento | L34: 0 | M34: PAT2 | N34: LESTE | O34: PARAIBANO | P34: 414.43 | Q34: 464.25 | R34: 467.01 | S34: 10.36075 | T34: 5.1583333 | U34: MARDENS ROCHA DE SOUSA | V34: 3026480255 | W34: 2001167443 | X34: RIACHUELO S/N / CENTRO | Y34: RURAL | Z34: -6.4306733 | AA34: -44.016265 | AB34: PROXIMO A PONTE DA CHAPADINA | CJ34: 20.06.2026 07:54:19 U5512599 APELIDO: XXXXXXXXXXX CLASSE DE CONSUMO: RESIDENCIAL Cliente fica a uns 200 metros da BT mais próximo, componente mais próximo 3554465. Descrição problema FINANCIAMENTO DE PADRÃO NOME DO CLIENTE: MARDENS ROCHA DE SOUSA SOLICITA FINANCIAMENTO DE PADRÃO PARCELADO EM:24_-_R$_18 03 X VEZES PONTO DE REFERÊNCIA: PROXIMO A PONTE DA CHAPADINA SOLICITAÇÃO VIA BACKOFFICE MA Nº DO PROTOCOLO DO SITE 20260618008405686 TELEFONE: (99) 98446-1748 TIPO DE FASE: MONOFÁSICO: 25A
B35: 0 | D35: 2331990 | E35: 1113806648 | F35: UNR | G35: 46199 | H35: 0 | I35: REJE | J35: Pré Análise | K35: 0 | L35: 0 | M35: PAT2 | N35: CENTRO | O35: BOM JARDIM | P35: 833.26 | Q35: 302.55 | R35: 653.24 | S35: 20.8315 | T35: 3.3616667 | U35: CLAUDENICE GUAJAJARA BARROS | V35: 3026532271 | W35: 2001169532 | X35: PRINCIPAL 07 / RURAL | Y35: RURAL | Z35: -3.6144964 | AA35: -45.517798 | AB35: TERRA INDIGENA RIO PINDARÉ | CJ35: (SEGUE EM ANEXO) 26.06.2026 11:21:28 L90862636 ANEXO DOC. DO SOLICITANTE FORMULÁRIO DE CONEXÃO E FORMULÁRIO DE PADRAO CLAUDENICE GUAJAJARA BARROS SOLICITA LIGACAO NOVA FAVOR FINANCIAR CLIENTE CIENTE DO PRAZO DE VISTORIA. Descrição problema E-MAIL VÁLIDO: HELIVANDO.SOUSA@FUNAI.GOV.BR ENDERECO ALDEIA GUARIMA TERRA INDIGENA DO RIO PINDARE SEM NUMERO ZONA ENDEREÇO CORRESPONDÊNCIA: ENDERECO ALDEIA GUARIMA TERRA INDIGENA DO RIO ENDEREÇO DA CONEXÃO É O MESMO ENDEREÇO DE CORRESPONDÊNCIA? SIM Levantob. PG mais próximo 13160959 MONTADO. NAO Necessário obra, sem rede e cliente aceita financiamento e sem padrão , código para a nota PADRAO EM CAMPO PINDARE SEM NUMERO ZONA RURAL MUNICIPIO DE BOM JARIM Pg mais próximo 368517 RURAL MUNICIPIO DE BOM JARIM SITUAÇÃO DO CPF DO CLIENTE REGULAR NA RECEITA FEDERAL? ( X ) SIM ( ) SOLICITACAO COM AUTORIZACAO DA GERENTE LAISE AZEVEDO
B36: 0 | D36: 2343646 | E36: 1114167469 | F36: UNR | G36: 46216 | H36: 0 | I36: ATIV | J36: Pré Análise | K36: 0 | L36: 0 | M36: PAT2 | N36: CENTRO | O36: ARARI | P36: 560.67 | Q36: 569.74 | R36: 574.37 | S36: 14.01675 | T36: 6.3304444 | U36: FRANCIMARIO CARVALHO FERNANDES | V36: 3026666936 | W36: 2001174549 | X36: DA ILHOTA S/N, LOTE 04, Q / LOTEAMENTO NATUREZA | Y36: RURAL | Z36: -3.4382883 | AA36: -44.757318 | CJ36: 13.07.2026 17:07:05 RFCUSER CPF: 60185129390 Descrição problema E-mail para recebimento de conta: Mecessita de obra pra atender esse cliente, mais de 900 metros do poste mais próximo várias casas Medidor: 0 Nome civil: FRANCIMARIO CARVALHO FERNANDES Nome: FRANCIMARIO CARVALHO FERNANDES Novo titular: Padrão de instalação: Parcelas: 000 Poste: 0 Representante: Não em construção
B37: 0 | D37: 1981470 | E37: 1109910091 | F37: MGD | G37: 46160 | H37: GIRO FORA PRAZO | I37: RECE | J37: Pré Análise | K37: 0 | L37: 0 | M37: PAT1 | N37: SUL | O37: BALSAS | P37: 42.44 | Q37: 48.2 | R37: 88.48 | S37: 1.061 | T37: 0.53555556 | U37: EDENILTON PINHEIRO SILVA | V37: 3012153650 | W37: 2000095768 | X37: 02 S/N / RURAL | Y37: RURAL | Z37: -7.4594005 | AA37: -46.04267 | AB37: POVOADO, 99 99171-5657 | CJ37: 20260129000236919 Aberto Anexos BackOffice Equatorial Energia Busca de solicitações CPF do responsável técnico 904.217.281-91 CPF ou CNPJ 021.224.843-06 CPF/CNPJ do formulário 021.224.843-06 Celular com DDD (98) 99107-6922 Celular do responsável técnico (63) 98426-7870 Conta Contrato 3012153650 Dados da solicitação Dados gerais Data de abertura 29/01/2026 13:38 Data de criação 29/01/2026 Detalhes da Solicitação Disjuntor de entrada 40 E-mail do responsável técnico davilucasrodriguesjorge@gmail.com Empresa do responsável técnico SE LIGA SOLUCOES Endereço de e-mail para acompanhamento davilucasrodriguesjorge@gmail.com
B38: 0 | D38: 2342107 | E38: 1111114107 | F38: MGD | G38: 46219 | H38: GIRO FORA PRAZO | I38: FINL | J38: Pré Análise | K38: Em levantamento | L38: 0 | M38: PAT2 | N38: CENTRO | O38: FERNANDO FALCAO | P38: 1422.17 | Q38: 58.05 | R38: 60.49 | S38: 35.55425 | T38: 0.645 | U38: HILO DE ALMEIDA SOUSA | V38: 35106936 | W38: 35106936 | X38: MARAVILHA 1 / PV MARAVILHA | Y38: RURAL | Z38: -6.1259482 | AA38: -44.812644 | AB38: TEM QUE IR ACESSO POR FERNANDO FALCAO APOS 20 KM DEPOIS DA PONTE DO RIO PERCATA FICA DO LADO MUNICIP | CJ38: 20260312000302705 Aberto Anexos BackOffice Equatorial Energia Busca de solicitações CPF do responsável técnico 956.170.943-00 CPF ou CNPJ 151.391.404-97 CPF/CNPJ do formulário 151.391.404-97 Celular com DDD (86) 98893-7435 Celular do responsável técnico (86) 98893-7435 Conta Contrato 35106936 Dados da solicitação Dados gerais Data de abertura 12/03/2026 09:09 Data de criação 12/03/2026 Detalhes da Solicitação Disjuntor de entrada 63 E-mail do responsável técnico projetos@madseng.com.br Empresa do responsável técnico MADS ENGENHARIA LTDA Endereço de e-mail para acompanhamento projetos@madseng.com.br
B39: 0 | D39: 1987136 | E39: 1112789893 | F39: MGD | G39: 46170 | H39: GIRO FORA PRAZO | I39: FINL | J39: Pré Análise | K39: 0 | L39: 0 | M39: PAT1 | N39: LESTE | O39: SANTA QUITERIA DO MARANHAO | P39: 69.87 | Q39: 59.75 | R39: 68.13 | S39: 1.74675 | T39: 0.66388889 | U39: ESTADO DO MARANHAO DEFENSORIA | V39: 3025114964 | W39: 2001117569 | X39: PARDAIS S/N / CENTRO | Y39: URBANO | Z39: -3.4919572 | AA39: -42.56392 | AB39: RESIDENCIAL PALMEIRAS, SETOR B. | CJ39: 20260512000425842 Aberto Anexos BackOffice Equatorial Energia Busca de solicitações CPF do responsável técnico 088.776.454-15 CPF ou CNPJ 00.820.295/0001-42 CPF/CNPJ do formulário 00.820.295/0001-42 Celular com DDD (98) 98348-7323 Celular do responsável técnico (84) 99637-6086 Conta Contrato 400318501605 Dados da solicitação Dados gerais Data de abertura 12/05/2026 10:25 Data de criação 12/05/2026 Detalhes da Solicitação Disjuntor de entrada 63 E-mail do responsável técnico financeiro@worldtelecom.com.br Empresa do responsável técnico WORLD TELECOM LTDA Endereço de e-mail para acompanhamento financeiro@worldtelecom.com.br
B40: 0 | D40: 2342096 | E40: 1112857404 | F40: MGD | G40: 46219 | H40: GIRO FORA PRAZO | I40: FINL | J40: Pré Análise | K40: Em levantamento | L40: 0 | M40: PAT1 | N40: CENTRO | O40: BACABAL | P40: 8.84 | Q40: 10.29 | R40: 11.52 | S40: 0.221 | T40: 0.11433333 | U40: ANA VALERIA DA SILVA NOGUEIRA | V40: 3025879758 | W40: 2000916316 | X40: ROMA 24 / RESIDENCIAL VILLAGIO | Y40: URBANO | Z40: -4.244055 | AA40: -44.803165 | AB40: AO LADO DO ARENA CLUB | CJ40: 20260513000427460 Aberto Anexos BackOffice Equatorial Energia Busca de solicitações CPF do responsável técnico 035.298.283-78 CPF ou CNPJ CPF/CNPJ do formulário Celular com DDD (86) 98135-0536 Celular do responsável técnico (99) 99144-9411 Conta Contrato 0 Dados da solicitação Dados gerais Data de abertura 12/05/2026 22:09 Data de criação 13/05/2026 Detalhes da Solicitação Disjuntor de entrada 63 E-mail do responsável técnico eduardofacundejr@gmail.com Empresa do responsável técnico EVOLUCAO SOLAR E ELETRICA LTDA Endereço de e-mail para acompanhamento eduardofacundejr@gmail.com
B41: 0 | D41: 1986185 | E41: 1112928647 | F41: UNI | G41: 46161 | H41: 0 | I41: RECE | J41: Pré Análise | K41: 0 | L41: 0 | M41: PAT1 | N41: SUL | O41: SAMBAÍBA | P41: 33.83 | Q41: 83.41 | R41: 160.68 | S41: 0.84575 | T41: 0.92677778 | U41: EVALDO BARBOSA DA SILVA | V41: 3026201330 | W41: 2001156728 | X41: PRINCIPAL S/N / CENTRO | Y41: URBANO | Z41: -7.1290636 | AA41: -45.350225 | AB41: ZONA RURAL | CJ41: TELEFONE: (99) 8808-2918 19.05.2026 08:50:37 U5512834 20260515000433054 CLASSE DE CONSUMO: RESIDENCIAL Descrição problema ENDEREÇO: FAZENDO RIACHUELO - GLEBA 3, S/N, BAIRRO: ZONA RURAL, Essa uc está a mais de 500 metros do última pg NOME DO CLIENTE: EVALDO BARBOSA DA SILVA SOLICITA FINANCIAMENTO DE PADRÃO PARCELADO EM: 024 PONTO DE REFERÊNCIA: NÃO TEM APELIDO: NÃO INFORMADO SAMBAÍBA/MA SOLICITAÇÃO VIA BACKOFFICE (MA) Nº DO PROTOCOLO DO SITE TIPO DE FASE: MONOFÁSICO:
B42: 0 | D42: 1986193 | E42: 1112930550 | F42: UNR | G42: 46161 | H42: 0 | I42: CANC | J42: Pré Análise | K42: 0 | L42: 0 | M42: PAT1 | N42: SUL | O42: BALSAS | P42: 270.83 | Q42: 102.6 | R42: 286.83 | S42: 6.77075 | T42: 1.14 | U42: ANTONIO PEREIRA DOS SANTOS | V42: 3026204045 | W42: 2001156828 | X42: POVOADO ANGELIM S/N / RURAL | Y42: RURAL | Z42: -7.4609808 | AA42: -46.125011 | AB42: 15 KM DE BALSAS | CJ42: 19.05.2026 10:38:34 T37123 ? NAO A INSTALAÇÃO POSSUI OU CONTARÁ COM CARREGADORES PARA VEÍCULOS ELÉTRICOS AMPERAGEM DO DISJUNTOR : 25A ANEXO DOC. DO SOLICITANTE E FORMULÁRIO DE CONEXÃO ASSINADO. ANÁLISE DUP CADASTRO? / NÃO CHECKLIST PADRÃO MONTADO ASSINADO PELO CLIENTE? SIM / CLIENTE VEIO AO ATENDIMENTO E SOLICITOU CONEXÃO. CIENTE DO PRAZO DE COORD. GEOGRÁFICAS:; NÃO LOCALIZADAS Descrição problema E-MAIL VÁLIDO: NÃO POSSUI ENDEREÇO CORRESPONDÊNCIA: POVOADO ANGELIM, RURAL ENDEREÇO DA CONEXÃO É O MESMO ENDEREÇO DE CORRESPONDÊNCIA? SIM IMOVEL LOCALIZADO NA AREA URBANA OU RURAL? RURAL LIGAÇÃO NOVA – COM PADRÃO INSTALADO PADRÃO INSTALADO EXTERNAMENTE? SIM / PONTO DE REFERÊNCIA: 15 KM DE BALSAS POSSUI REDE ELÉTRICA PROX. AO IMÓVEL? SIM / Poste mais próximo 22157758 SERÁ REJEITADO.
B43: 0 | D43: 1986221 | E43: 1112955817 | F43: UNR | G43: 46162 | H43: 0 | I43: RECE | J43: Pré Análise | K43: 0 | L43: 0 | M43: PAT2 | N43: SUL | O43: RIACHAO | P43: 1270.37 | Q43: 89.86 | R43: 463.92 | S43: 31.75925 | T43: 0.99844444 | U43: FELIPE DE LISBOA RODRIGUES LOPES | V43: 3026211971 | W43: 2001157180 | X43: DATA FAZENDA GRANDE S/N / ZONA RURAL | Y43: RURAL | Z43: -7.6321431 | AA43: -46.998938 | AB43: PROXIMO A CASA DO SEU LUIS BOA | CJ43: 20.05.2026 09:10:38 T27855 ? NAO A INSTALAÇÃO POSSUI OU CONTARÁ COM CARREGADORES PARA VEÍCULOS ELÉTRICOS AMPERAGEM DO DISJUNTOR : 25AP ANEXO DOC. DO SOLICITANTE E FORMULÁRIO DE CONEXÃO ASSINADO. ANÁLISE DUP CADASTRO? SIM / CHECKLIST PADRÃO MONTADO ASSINADO PELO CLIENTE? SIM / CLIENTE FELIPE DE LISBOA RODRIGUES LOPES VEIO AO ATENDIMENTO E COORD. GEOGRÁFICAS: XXXXXXXXXXXXXXXXXX; XXXXXXXXXXXXXXXXXX Descrição problema E-MAIL VÁLIDO: NAO POSSUI ENDEREÇO CORRESPONDÊNCIA: XXXXXXXXXXXXXXXXXXXXXXXXXXXXXXXXXXXXX ENDEREÇO DA CONEXÃO É O MESMO ENDEREÇO DE CORRESPONDÊNCIA? SIM / IMOVEL LOCALIZADO NA AREA RURAL INCOMPLETO/INEXISTENTE, SEU PEDIDO SERÁ REJEITADO. LIGAÇÃO NOVA – COM PADRÃO INSTALADO PADRÃO INSTALADO EXTERNAMENTE? SIM / PONTO DE REFERÊNCIA: PROXIMO A CASA DO SEU LUIS BOA POSSUI REDE ELÉTRICA PROX. AO IMÓVEL? SIM / SOLICITOU CONEXÃO. CIENTE DO PRAZO DE VISTORIA E QUE, EM CASO DE PADRÃO
B44: 0 | D44: 1987048 | E44: 1112960025 | F44: UNR | G44: 46162 | H44: 0 | I44: RECE | J44: Pré Análise | K44: 0 | L44: 0 | M44: PAT3 | N44: SUL | O44: RIACHAO | P44: 2092.29 | Q44: 1478.67 | R44: 1438.98 | S44: 52.30725 | T44: 16.429667 | U44: ANA LUCIA NOLETO BASTOS | V44: 3026218496 | W44: 2001157391 | X44: DATA RIACHO SECO S/N / ZONA RURAL | Y44: RURAL | Z44: -7.7780928 | AA44: -46.658031 | AB44: PROXIMO AFAZENDA BARREIRO RASO, DO SR DESDETE, | CJ44: 20.05.2026 14:41:04 T37123 ? NAO A INSTALAÇÃO POSSUI OU CONTARÁ COM CARREGADORES PARA VEÍCULOS ELÉTRICOS AMPERAGEM DO DISJUNTOR : 25A ANEXO DOC. DO SOLICITANTE E FORMULÁRIO DE CONEXÃO ASSINADO. ANÁLISE DUP CADASTRO? / NÃO CHECKLIST PADRÃO MONTADO ASSINADO PELO CLIENTE? SIM / CLIENTE VEIO AO ATENDIMENTO E SOLICITOU CONEXÃO. CIENTE DO PRAZO DE COORD. GEOGRÁFICAS:; NÃO LOCALIZADAS Descrição problema E-MAIL VÁLIDO: NÃO POSSUI ENDEREÇO CORRESPONDÊNCIA: FAZENDA RIACHO DO MEIO ( IPOEIRA) , DATA ENDEREÇO DA CONEXÃO É O MESMO ENDEREÇO DE CORRESPONDÊNCIA? SIM IMOVEL LOCALIZADO NA AREA URBANA OU RURAL? RURAL LIGAÇÃO NOVA – COM PADRÃO INSTALADO PADRÃO INSTALADO EXTERNAMENTE? SIM / PONTO DE REFERÊNCIA: PROXIMO AFAZENDA BARREIRO RASO, DO SR DESDETE, POSSUI REDE ELÉTRICA PROX. AO IMÓVEL? SIM / RIACHO SECO SERÁ REJEITADO.
B45: 0 | D45: 2328056 | E45: 1113246072 | F45: MGD | G45: 46195 | H45: GIRO FORA PRAZO | I45: FINL | J45: Avaliação de Expurgo | K45: Improdutivo | L45: 0 | M45: PAT1 | N45: NORTE | O45: HUMBERTO DE CAMPOS | P45: 33.68 | Q45: 64.39 | R45: 65.49 | S45: 0.842 | T45: 0.71544444 | U45: LUIS FERNANDO SILVA DOS SANTOS | V45: 3023373083 | W45: 2001047624 | X45: PERIA S/N / PERIA | Y45: URBANO | Z45: -2.6492023 | AA45: -43.486405 | AB45: PRÓXIMO A BR É UMA MA SITIO DO LUIZINHO / CONTATO: 98984539092 | CJ45: 2026053099227034 Anexos BackOffice Equatorial Energia MA BackOffice Equatorial Energia v 2.1.2 - GMZ Solutions CPF ou CNPJ validado pelo formulário Conta Contrato Conta Contrato validada pelo formulário Conta ativa no momento da solicitação Dados Orçamento de Conexão – 1780102227 Dados da Solicitação Dados do Usuário Logado Data 30/05/2026 01:09:02 Nome do usuário logado POTÊNCIA INVERSOR: 25,00 KW POTÊNCIA MÓDULO: 35,96 KW Painel de Agendamentos Preferência de retorno de contato Protocolos de Solicitação 20260529008401208 Relatórios Situação Em Aberto
B46: 0 | D46: 2332966 | E46: 1113415125 | F46: MGD | G46: 46209 | H46: 0 | I46: ATIV | J46: Expurgo Concluído | K46: Improdutivo | L46: 0 | M46: PAT1 | N46: NORTE | O46: ROSÁRIO | P46: 39.97 | Q46: 41.93 | R46: 51.41 | S46: 0.99925 | T46: 0.46588889 | U46: ALAIM ROGERIO CARVALHO TAVARES | V46: 5320992 | W46: 5320992 | X46: 2 5 / CENTRO | Y46: 0 | Z46: -2.9393802 | AA46: -44.254636 | AB46: NA MESMA RUA DELEGACIA | CJ46: 2026060899228582 Anexos BackOffice Equatorial Energia MA BackOffice Equatorial Energia v 2.1.2 - GMZ Solutions CPF ou CNPJ validado pelo formulário Conta Contrato Conta Contrato validada pelo formulário Conta ativa no momento da solicitação Dados Orçamento de Conexão – 1780918132 Dados da Solicitação Dados do Usuário Logado Data 08/06/2026 11:47:57 Nome do usuário logado POTÊNCIA INVERSOR: 10,00 KW POTÊNCIA MÓDULO: 8,93 KW Painel de Agendamentos Preferência de retorno de contato Protocolos de Solicitação 20260608008402756 Relatórios Situação Em Aberto
B47: 0 | D47: 2332959 | E47: 1113577993 | F47: MGD | G47: 46209 | H47: GIRO FORA PRAZO | I47: FINL | J47: Avaliação de Expurgo | K47: Improdutivo | L47: 0 | M47: PAT1 | N47: NORTE | O47: PAÇO DO LUMIAR | P47: 13.9 | Q47: 13.76 | R47: 1.32 | S47: 0.3475 | T47: 0.15288889 | U47: ARTHIMISIA DE FATIMA PEREIRA | V47: 3022236562 | W47: 2001000641 | X47: RUA NAO CADASTRADA 17 / LT DR AMARAL DE MATOS | Y47: URBANO | Z47: -2.5475124 | AA47: -44.189957 | AB47: -2.5476983,-44.1903637 NO LOTEAMENTO EM FRENTE AO KIOLA FERRAGEM | CJ47: 2026061599230451 Anexos BackOffice Equatorial Energia MA BackOffice Equatorial Energia v 2.1.2 - GMZ Solutions CPF ou CNPJ validado pelo formulário Conta Contrato Conta Contrato validada pelo formulário Conta ativa no momento da solicitação Dados Orçamento de Conexão 1781528926 Dados da Solicitação Dados do Usuário Logado Data 15/06/2026 13:28:05 Nome do usuário logado POTÊNCIA MÓDULOS: 4,88 KW POTÊNCIA INVERSOR: 5,00 KW Painel de Agendamentos Preferência de retorno de contato Protocolos de Solicitação 20260615008404625 Relatórios Situação Em Aberto Solicitação - Orçamento de Conexão 1781528926
B48: ISRAEL GARRAS VERAS | C48: 46265 | D48: 2328160 | E48: 1113695590 | F48: UNR | G48: 46195 | H48: 0 | I48: DEVO | J48: Pré Análise | K48: Em levantamento | L48: MO | M48: PAT1 | N48: NORTE | O48: SAO JOSE DE RIBAMAR | P48: 27.89 | Q48: 26.43 | R48: 100.18 | S48: 0.69725 | T48: 0.29366667 | U48: DENNISSON MARTINS DE SOUSA | V48: 3026487586 | W48: 2001167734 | X48: MARLENE MONROE S/N / SAO JOSE DOS INDIOS | Y48: RURAL | Z48: -2.5483431 | AA48: -44.101611 | CJ48: 22.06.2026 11:45:58 U10263 420038771 Descrição problema
B49: 0 | D49: 2341457 | E49: 1113804917 | F49: MGD | G49: 46218 | H49: GIRO FORA PRAZO | I49: FINL | J49: Concluído | K49: Concluído | L49: 0 | M49: PAT1 | N49: NORTE | O49: SANTO AMARO DO MARANHAO | P49: 13.41 | Q49: 11.91 | R49: 203.16 | S49: 0.33525 | T49: 0.13233333 | U49: KELIANE GARCIA DE OLIVEIRA | V49: 3015019750 | W49: 2000711518 | X49: BOA ESPERANCA S/N / OLHO DAGUA | Y49: URBANO | Z49: -2.5155161 | AA49: -43.256599 | AB49: 98984267051 AO LADO DA PISTA DE CAVALO | CJ49: 20260625000509059 Aberto Anexos BackOffice Equatorial Energia Busca de solicitações CPF do responsável técnico 038.671.383-97 CPF ou CNPJ CPF/CNPJ do formulário Celular com DDD (98) 98497-4300 Celular do responsável técnico (98) 98838-2213 Conta Contrato 361096201658 Dados da solicitação Dados gerais Data de abertura 25/06/2026 19:46 Data de criação 25/06/2026 Detalhes da Solicitação Disjuntor de entrada 50 E-mail do responsável técnico ELETROKSAPROJETOS@GMAIL.COM Empresa do responsável técnico ELETROKSA ENGENHARIA LTDA Endereço de e-mail para acompanhamento ELETROKSAPROJETOS@GMAIL.COM
A50: SIM | B50: EDELSON SOUSA GUIMARÃES | C50: 46265 | D50: 2306412 | E50: 1113189649 | F50: UNI | G50: 46171 | H50: GIRO NO PRAZO | I50: ATIV | J50: Liberado para Levantamento | K50: Correção de levantamento | L50: MO | M50: PAT1 | N50: LESTE | O50: AFONSO CUNHA | P50: 24.93 | Q50: 25.36 | R50: 23.24 | S50: 0.62325 | T50: 0.28177778 | U50: RAIMUNDO NONATO SANTOS DA SILVA | V50: 3026301679 | W50: 2001160526 | X50: CHAPADA NOVA S/N, ao povoado / RURAL | Y50: URBANO | Z50: -4.1571733 | AA50: -43.343348 | CJ50: 29.05.2026 11:38:15 RFCUSER CPF: 05055702389 Cliente fica a 80m da rede de bt,com medidor mais próximo 12032189367 e componente 354642x Descrição problema E-mail para recebimento de conta: Medidor: 1 Nome civil: RAIMUNDO NONATO SANTOS DA SILVA Nome: RAIMUNDO NONATO SANTOS DA SILVA Novo titular: Padrão de instalação: Parcelas: 024 Poste: 1 Representante: Não
B51: 0 | D51: 1907979 | E51: 1111617751 | F51: UNR | G51: 46111 | H51: 0 | I51: DEVO | J51: Pré Análise | K51: 0 | L51: 0 | M51: PAT1 | N51: SUL | O51: GRAJAÚ | P51: 28.97 | Q51: 30.31 | R51: 325.19 | S51: 0.72425 | T51: 0.33677778 | U51: ROBSON GOMES DA SILVA | V51: 3025778315 | W51: 2001142667 | X51: FAZENDA SANTO ANTONIO S/N / POV GAVIAO | Y51: RURAL | Z51: -5.29218 | AA51: -45.815725 | AB51: PROXIMO A INSTALAÇÃO: 40356649,POVOADO GAVIAO ITAIPAVA DE GRAJAU | CJ51: 1212/660 1212/660 30.03.2026 16:15:38 T53617 30.03.2026 16:15:38 T53617 ANEXO DOC. DO SOLICITANTE, FORMULÁRIO DE CONEXÃO E FORMULÁRIO DE ANEXO DOC. DO SOLICITANTE, FORMULÁRIO DE CONEXÃO E FORMULÁRIO DE ANÁLISE DUP CADASTRO? NÃO ANÁLISE DUP CADASTRO? NÃO CIENTE DO PRAZO DE VISTORIA. CIENTE DO PRAZO DE VISTORIA. CLIENTE: ROBSON GOMES DA SILVA CLIENTE: ROBSON GOMES DA SILVA COORD. GEOGRÁFICAS:NAO LOCALIZADAS COORD. GEOGRÁFICAS:NAO LOCALIZADAS Descrição problema Descrição problema E-MAIL VÁLIDO: MARILENEPERREIRASILVA09@GMAIL.COM E-MAIL VÁLIDO: MARILENEPERREIRASILVA09@GMAIL.COM ENDEREÇO CORRESPONDÊNCIA: LOCALIZADO NA FAZENDA SANTO ANTONIO, POVOADO ENDEREÇO CORRESPONDÊNCIA: LOCALIZADO NA FAZENDA SANTO ANTONIO, POVOADO
B52: 0 | D52: 1983439 | E52: 1112731434 | F52: 0 | G52: 46153 | H52: 0 | I52: DEVO | J52: Pré Análise | K52: Análise de levantamento | L52: 0 | M52: PAT1 | N52: SUL | O52: ARAME | P52: 285.65 | Q52: 58.22 | R52: 140.4 | S52: 7.14125 | T52: 0.64688889 | U52: ARGEMIRO PAULINO GUAJAJARA | V52: 3026131811 | W52: 2001154323 | X52: PRINCIPAL S/N / ZUTIUA | Y52: 0 | Z52: -5.18581 | AA52: -46.282133 | CJ52: 11.05.2026 14:22:44 T27638 11.05.2026 14:22:44 T27638 APOIO : EZEQUIEL REIS E EDUARDO ACACIO - GERC APOIO : EZEQUIEL REIS E EDUARDO ACACIO - GERC BACURI) BACURI) Descrição problema Descrição problema E-MAIL FORMALIZADO E ANEXADO NO PEDIDO E-MAIL FORMALIZADO E ANEXADO NO PEDIDO Esse cliente fica a 200 mts do pg 1014176 Esse cliente fica a 200 mts do pg 1014176 Esse cliente fica a 500 MTS do PG 1046616 Esse cliente fica a 500 MTS do PG 1046616 PADRÃO SERÁ DOADO CONFORME ORIENTAÇÃO DA AREA POR UNIVERSALIZAÇÃO PADRÃO SERÁ DOADO CONFORME ORIENTAÇÃO DA AREA POR UNIVERSALIZAÇÃO PROX A INSTALACAO 31665604 PROX A INSTALACAO 31665604 SOLICITACAO PARA ATENDER AS ALDEIAS ( VILA MARTINS, VILA MEL,PORTGUAL E SOLICITACAO PARA ATENDER AS ALDEIAS ( VILA MARTINS, VILA MEL,PORTGUAL E
B53: ISRAEL GARRAS VERAS | C53: 46265 | D53: 2328192 | E53: 1113700142 | F53: UNR | G53: 46195 | H53: 0 | I53: DEVO | J53: Pré Análise | K53: Em levantamento | L53: MO | M53: PAT1 | N53: NORTE | O53: SAO JOSE DE RIBAMAR | P53: 27.89 | Q53: 26.43 | R53: 100.18 | S53: 0.69725 | T53: 0.29366667 | U53: HALERSON LEMOS NUNES | V53: 3026494434 | W53: 2001168022 | X53: MARLENE MONROE S/N / SAO JOSE DOS INDIOS | Y53: RURAL | Z53: -2.5483431 | AA53: -44.101611 | CJ53: 22.06.2026 17:32:19 U10263 420038771 Descrição problema
B54: DIEGO LOPES DOS SANTOS | C54: 46262 | D54: 1981514 | E54: 1037979614 | F54: UNI | G54: 46160 | H54: 0 | I54: ATIV | J54: Liberado para Levantamento | K54: Em levantamento | L54: MO | M54: PAT1 | N54: NORTE | O54: SAO LUIS | P54: 1006.61 | Q54: 1182.92 | R54: 1193.37 | S54: 25.16525 | T54: 13.143556 | U54: ELIAS ALMEIDA FERNANDES | V54: 3009880657 | W54: 2000494190 | X54: TAUAMIRIM 18 / TAUAMIRIM | Y54: URBANO | Z54: -2.7246559 | AA54: -44.383385 | CJ54: CSS DE PRAZO E PROCEDIMENTO E AFIRMA QUE VAI FINANCIAR O SEU PADRÃO EM 24X VEIO AO ATENDIMENTO PORTANDO CPF E RG SOLICITAR LIGAÇÃO NOVA ESTA CIENTE ____________________ LIGAÇÃO NOVA ESTA CIENTE DE PRAZO E PROCEDIMENTO E AFIRMA QUE VAI Descrição problema FINANCIAR O SEU PADRÃO EM 24X PELA CEMAR. VERIFICAR TERMOS ANEXO CRM E PELA CEMAR. VERIFICAR TERMOS ANEXO CRM E CSS 08.01.2020 14:40:34 TATE5508377 Descrição da solução ELIAS ALMEIDA FERNANDES VEIO AO ATENDIMENTO PORTANDO CPF E RG SOLICITAR
B55: 0 | D55: 2331176 | E55: 1113718777 | F55: 0 | G55: 46196 | H55: 0 | I55: DEVO | J55: Pré Análise | K55: 0 | L55: 0 | N55: NOROESTE | O55: APICUM-ACU | P55: 0 | Q55: 0 | R55: 0 | S55: 0 | T55: 0 | U55: ANTONIO AZEVEDO MARTINS | V55: 3026495856 | W55: 2001168079 | X55: PRAIA DE BALEIA S/N / ZONA PRAIANA | Y55: 0 | Z55: 0 | AA55: 0 | CJ55: 23.06.2026 09:07:46 U5511865 CIENTE DO PRAZO DE 05 DIAS ÚTEIS PARA VISTORIA E EXECUÇÃO DO SERVIÇO. CLIENTE AFIRMA QUE JÁ POSSUI O PADRÃO INSTALADO DENTRO DO LIMITE DA VIA DISJUNTOR:25 A Descrição problema FASE: MONOFASICO NOME:ANTONIO AZEVEDO MARTINS Nº DO PROTOCOLO DO SITE 20260622000500703 PADRÃO INSTALADO: SIM PONTO DE REFERÊNCIA: NÃO INFORMADO PÚBLICA E CIENTE QUE CASO A INEXISTÊNCIA SEU PEDIDO SERÁ REJEITADO. SOLICITAÇÃO VIA BACKOFFICE (EQUATORIAL MA) TELEFONE: (98) 97005-8407
B56: DIEGO LOPES DOS SANTOS | C56: 46262 | D56: 1982078 | E56: 1045219038 | F56: UNI | G56: 46160 | H56: 0 | I56: ATIV | J56: Liberado para Levantamento | K56: Em levantamento | L56: MO | M56: PAT1 | N56: NORTE | O56: SAO LUIS | P56: 137.69 | Q56: 136.4 | R56: 168.39 | S56: 3.44225 | T56: 1.5155556 | U56: MARIA DA CONCEICAO MACEDO CUNHA | V56: 3011533174 | W56: 2000571559 | X56: HORTAS 03 / IGARAU | Y56: URBANO | Z56: -2.7543891 | AA56: -44.316012 | AB56: RUA DAS PALMEIRAS FICA DE ESQUINA COM A RUA DAS PALMEIRAS 98 98717-0586/9898227-1394 | CJ56: 30.10.2020 16:47:28 TATE5507104 FINS DE SOLICITAR LIGAÇÃO NOVA , A MESMA JA FINANCIOU O SEU PADRAO EM Sra. MARIA DA CONCEICAO MACEDO CUNHA CLIENTE VEIO AO ATT COM RG E CPF A 24X DE 14,07 Descrição problema
B57: DIEGO LOPES DOS SANTOS | C57: 46262 | D57: 1981610 | E57: 1045618848 | F57: UNR | G57: 46160 | H57: 0 | I57: ATIV | J57: Liberado para Levantamento | K57: Correção de levantamento | L57: MO | M57: PAT2 | N57: NORTE | O57: SAO LUIS | P57: 40.07 | Q57: 49.12 | R57: 128.63 | S57: 1.00175 | T57: 0.54577778 | U57: FRANCISCO COSTA FERREIRA | V57: 3011612015 | W57: 2000575134 | X57: RUA NAO CADASTRADA 04 / IGARAU | Y57: RURAL | Z57: -2.7459579 | AA57: -44.332511 | AB57: ESCOLA ANTONINHO BALDEZ 98984324753 | CJ57: 98984324753 ACORDO COM OS PADRÃO DE ACORDO COM O PADRÃO DA COMPANHIA SUA NOTA DE LIGAÇÃO SERÁ CANCELADA E O VALOR DA FISCALIZAÇÃO SERÁ DE SUA SEU PADRÃO ESTA DEVIDAMENTE EXTERNAMENTE DENTRO DOS PADRÕES CEMAR. ESCOLA ANTONINHO BALDEZ SOLICITAR LIGAÇÃO NOVA ESTA CIENTE DE PRAZO E PROCEDIMENTO E AFIRMA QUE Sem rede, cliente sem padrão e sem financiamento de padrão. CLIENTE ASSINOU TERMO E ESTA CIENTE QUE SE NÃO ESTIVER COM O PADRÃO DE Descrição problema VERIFICAR TERMOS ANEXO CRM E CSS . FRANCISCO COSTA FERREIRA VEIO AO ATENDIMENTO PORTANDO CPF E RG 11.11.2020 10:20:52 TATE5507908 RESPONSABILIDADE
B58: 0 | D58: 1982092 | E58: 1000582304 | F58: UNR | G58: 46160 | H58: 0 | I58: ATIV | J58: Liberado para Levantamento | K58: Em levantamento | L58: MO | M58: PAT1 | N58: NOROESTE | O58: TURILÂNDIA | P58: 21.16 | Q58: 47.52 | R58: 52.56 | S58: 0.529 | T58: 0.528 | U58: MARIA DAS DORES SILVA | V58: 3000247684 | W58: 2000013561 | X58: PRINCIPAL 1 / SAO DOMINGOS | Y58: RURAL | Z58: -2.3257455 | AA58: -45.51385 | AB58: AO LADO DA CASA DE LUCIA E DA CASA DE ANTONIO SE TRATA DO POVOADO CORO DEPOIS DO SAO DOMINGOS | CJ58: Descrição problema cliente solicita ligacao nova 01.03.2016 16:51:01 TATE50377
B59: 0 | D59: 1981638 | E59: 1001045406 | F59: UNR | G59: 46160 | H59: 0 | I59: ATIV | J59: Pré Análise | K59: Em levantamento | L59: MO | M59: PAT1 | N59: CENTRO | O59: BERNARDO DO MEARIM | P59: 191.41 | Q59: 351.59 | R59: 325.13 | S59: 4.78525 | T59: 3.9065556 | U59: FRANCISCO RONE SILVA NEVES | V59: 3000406952 | W59: 2000022077 | X59: PRINCIPAL S/N / RURAL | Y59: RURAL | Z59: -4.6381828 | AA59: -44.761832 | AB59: DEPOIS DA FAZENDA SAO PEDRO | CJ59: COMO RONE, NÃO TEM TELEFONE 28.03.2016 12:03:13 TCGB12368 CLIENTE SOLICITA LIGAÇAO NOVA E INFORMA QUE O PADRAO JA ESTA MONTADO, A PAULO, CASA DE PROJETO É A PIRMEIRA ANTES DA FAZENDA CLIENTE CONHECIDO Descrição problema Comp. 100326 7. Poste. 469042 CASA FICA NO POV CANELEIRO DEPOIS DO ENCANTADO, FICA PX A FAZENDA SAO
B60: 0 | D60: 1981192 | E60: 1001177430 | F60: UNR | G60: 46160 | H60: 0 | I60: ATIV | J60: Pré Análise | K60: 0 | L60: MO | M60: PAT1 | N60: NOROESTE | O60: TURIAÇU | P60: 64.84 | Q60: 46.79 | R60: 241.89 | S60: 1.621 | T60: 0.51988889 | U60: ALAIDE JINKINGS ROXO | V60: 3000458057 | W60: 2000025237 | X60: CAMPINA DOS ROCHOS S/N / CAMPINA DOS ROCHOS | Y60: RURAL | Z60: -1.8541225 | AA60: -45.285684 | AB60: APOS A ENTRADA DA CAMPINA DOS ROCHOS | CJ60: SRA JEANE ATT TURIACU 09833971496 EM NOME DA SRA ALAIDE JINKINGS ROXO 7M 04.04.2016 09:33:31 TATE70304 337,67 EM 24X FINANCIAMENTO DE PADRAO TATE0304 FERNANDO Descrição problema
B61: 0 | D61: 1981268 | E61: 1001177520 | F61: UNR | G61: 46160 | H61: 0 | I61: ATIV | J61: Pré Análise | K61: 0 | L61: 0 | M61: PAT1 | N61: NOROESTE | O61: TURIAÇU | P61: 0 | Q61: 0 | R61: 0 | S61: 0 | T61: 0 | U61: ANTONIA RIBEIRO COSTA | V61: 3000459002 | W61: 2000025249 | X61: CAMPINA DOS ROCHO 01 / BARRACA | Y61: 0 | Z61: 0 | AA61: 0 | AB61: APOS A ENTRADA DA CAMPINAS DOS ROCHOS | CJ61: DA LIGAÇÃO NOVA INF QUE O CLIENTE DESEJA SOLICITAR UM FPC;7 357.67 24 X14.07 TATE6730TAIS Descrição problema SR(A )JEANE (ATENDENTE) TUARIACU 09833971496 SOLICITA O PEDIDO 04.04.2016 09:43:37 TATE67305
B62: 0 | D62: 1982457 | E62: 1001177684 | F62: UNR | G62: 46160 | H62: 0 | I62: ATIV | J62: Pré Análise | K62: 0 | L62: MO | M62: PAT1 | N62: NOROESTE | O62: TURIAÇU | P62: 64.84 | Q62: 46.79 | R62: 241.89 | S62: 1.621 | T62: 0.51988889 | U62: TEREZINHA ROXO | V62: 3000459231 | W62: 2000025278 | X62: CAMPINA DOS ROCHOS S/N / CAMPINA DOS ROCHOS | Y62: RURAL | Z62: -1.8541225 | AA62: -45.285684 | AB62: APOS A ENTRADA CAMPINA DOS ROXOS | CJ62: JEANE ATT TURIACU Descrição problema SOLICITA FPC 5 MT VALOR 337.67 EM 24X 14.07 TATE 5341 ANDREIA 04.04.2016 10:00:44 TATE35341 EM NOME DA SRA TEREZINHA ROXO
B63: 0 | D63: 1981899 | E63: 1001178070 | F63: UNI | G63: 46160 | H63: 0 | I63: ATIV | J63: Pré Análise | K63: 0 | L63: MO | M63: PAT1 | N63: NOROESTE | O63: TURIAÇU | P63: 54.46 | Q63: 31.15 | R63: 44 | S63: 1.3615 | T63: 0.34611111 | U63: JOSE PAULINO FERREIRA NETO | V63: 3000458545 | W63: 2000025341 | X63: CAMPINAS S/N / CAMPINAS | Y63: URBANO | Z63: -1.7446409 | AA63: -45.468631 | AB63: OBS: POVOADO CASTELO , APOS CAPOEIRA DE GATO | CJ63: Descrição problema 04.04.2016 10:48:53 TATE54359 ATT; GEANE AG: TURIACUL, SOLICITA LIGACAO NOVA PARA CLIENTE JOSE PADRAO NA CEMAR VALOR 337,67 / 24 DE 14,07. TATE 54359 - LEUCIVAN PAULINO FERREIRA NETO, COM FINANCIMENTO DE PADRAO FINANCIAMENTO DE
B64: 0 | D64: 1982118 | E64: 1001178152 | F64: UNR | G64: 46160 | H64: 0 | I64: ATIV | J64: Pré Análise | K64: 0 | L64: MO | M64: PAT1 | N64: NOROESTE | O64: TURIAÇU | P64: 64.84 | Q64: 46.79 | R64: 241.89 | S64: 1.621 | T64: 0.51988889 | U64: MARIA DO SOCORRO ROXO | V64: 3000459886 | W64: 2000025357 | X64: CAMPINA DOS ROCHOS S/N / CAMPINA DOS ROCHOS | Y64: RURAL | Z64: -1.8541225 | AA64: -45.285684 | AB64: APOS O POV CAPOEIRA DO GADO | CJ64: 04.04.2016 11:03:26 TATE70304 TATE0304 FERNANDO 7M SRA JEANE ATT TURIACU 09833971496 EM NOME DA SRA MARIA DO SOCORRO ROXO 337,67 EM 24X Descrição problema FINANCIAMENTO DE PADRAO
B65: 0 | D65: 1981971 | E65: 1017687308 | F65: UNR | G65: 46160 | H65: 0 | I65: ATIV | J65: Pré Análise | K65: Em levantamento | L65: B | M65: PAT3 | N65: NORTE | O65: AGUA DOCE DO MARANHAO | P65: 748.59 | Q65: 742.66 | R65: 773.46 | S65: 18.71475 | T65: 8.2517778 | U65: LADJANE DA SILVA SOUZA | V65: 3005314924 | W65: 2000284740 | X65: JOSE SILVA S/N / CENTRO | Y65: RURAL | Z65: -2.8517202 | AA65: -42.183423 | CJ65: A uc ficar 56 metros da Bt pg legível vizinha 1252329373-5 tráfico 049856-4 TEL:09834851301 Descrição problema rg: 241374120037 TATE47319WALDANHA CPF: 01839800348 07.03.2018 10:06:51 TATE47319 ATENDENTE RESPONSAVEL PARA ANEXAR A DOCUMENTACAO AT: LETICIA AG: AGUA DOCE SOLICITA LIGACAO NOVA COM FCP DE 7M EM 12X
B66: 0 | D66: 1982170 | E66: 1001180985 | F66: UNR | G66: 46160 | H66: 0 | I66: ATIV | J66: Pré Análise | K66: 0 | L66: MO | M66: PAT1 | N66: NOROESTE | O66: TURIAÇU | P66: 64.84 | Q66: 46.79 | R66: 241.89 | S66: 1.621 | T66: 0.51988889 | U66: MARILENE PAIVA DE LIMA | V66: 3000464308 | W66: 2000025576 | X66: CAMPINA DOS ROCHOS S/N / CAMPINA DOS ROCHOS | Y66: RURAL | Z66: -1.8541225 | AA66: -45.285684 | AB66: APOS A ENTRADA DO CAMPINA DOS ROCHOS | CJ66: Descrição problema 04.04.2016 15:52:28 TATE44370 RAYSUANE ATD: GEANE AG: TURIAÇU SOLICITA LIGAÇÃO NOVA MONOFASICA TATE 44370
B67: 0 | D67: 1981172 | E67: 1001181113 | F67: UNR | G67: 46160 | H67: 0 | I67: ATIV | J67: Pré Análise | K67: 0 | L67: MO | M67: PAT1 | N67: NOROESTE | O67: TURIAÇU | P67: 64.84 | Q67: 46.79 | R67: 241.89 | S67: 1.621 | T67: 0.51988889 | U67: ADAILTON GONCALVES | V67: 3000463360 | W67: 2000025569 | X67: CAMPINA DOS ROCHOS 1 / CAMPINA DOS ROCHOS | Y67: RURAL | Z67: -1.8541225 | AA67: -45.285684 | AB67: APOS O POVOADO CAMPINA DOS ROCHOS | CJ67: 04.04.2016 16:10:53 TATE73320 Descrição problema ATT GEANE AG:TURIACU SOLICITA PEDIDO DE LIGACAO NOVA COM FINANCIAMENTO DE PADRAO DE 5 METROS DIVIDIDO EM 24 VEZES TATE73320JUCILENE
B68: 0 | D68: 1981381 | E68: 1001221687 | F68: UNR | G68: 46160 | H68: 0 | I68: ATIV | J68: Pré Análise | K68: 0 | L68: MO | M68: PAT1 | N68: NOROESTE | O68: TURIAÇU | P68: 64.84 | Q68: 46.79 | R68: 241.89 | S68: 1.621 | T68: 0.51988889 | U68: CESARIO GARCIA | V68: 3000478813 | W68: 2000026538 | X68: CAMPINA DOS ROCHOS S/N / CAMPINA DOS ROCHOS | Y68: RURAL | Z68: -1.8541225 | AA68: -45.285684 | AB68: APOS A ENTRADA DA CAMPINA | CJ68: Descrição problema 06.04.2016 14:19:13 TATE09323 ATD: GEANE AG: TURIAÇU Sr. CESARIO GARCIA SOLICITA O FINANCIAMENTO DE PADRÃO COMPLETO EM 24X DE 5 METROS TATE09323 LILIANE
B69: 0 | D69: 1981185 | E69: 1001221907 | F69: UNR | G69: 46160 | H69: 0 | I69: ATIV | J69: Pré Análise | K69: 0 | L69: MO | M69: PAT1 | N69: NOROESTE | O69: TURIAÇU | P69: 64.84 | Q69: 46.79 | R69: 241.89 | S69: 1.621 | T69: 0.51988889 | U69: AGAPTO ASSUNCAO MELO | V69: 3000478961 | W69: 2000026561 | X69: CAMPINA DOS ROCHOS 14888 / CAMPINA DOS ROCHOS | Y69: RURAL | Z69: -1.8541225 | AA69: -45.285684 | AB69: APOS A ENTRADA DA CAMPINA | CJ69: Descrição problema 06.04.2016 14:39:53 TATE06392 ATT:GEANE AG TURIACU SOLICITA PEDIDO DE LIGACAO NOVA EM NOME SR AGAPTO ASSUNCAO MELO O MESMO DESEJA FINANCIAR PADRAO DE 7 METROS 24 VEZES TATE06392 KALINE
B70: 0 | D70: 1981557 | E70: 1001222011 | F70: UNR | G70: 46160 | H70: 0 | I70: ATIV | J70: Pré Análise | K70: 0 | L70: MO | M70: PAT1 | N70: NOROESTE | O70: TURIAÇU | P70: 64.84 | Q70: 46.79 | R70: 241.89 | S70: 1.621 | T70: 0.51988889 | U70: EVANGELINA FERREIRA OLIVEIRA | V70: 3000479089 | W70: 2000026558 | X70: CAMPINA DOS ROCHOS 14888 / CAMPINA DOS ROCHOS | Y70: RURAL | Z70: -1.8541225 | AA70: -45.285684 | AB70: APOS A ENTRADA DA CAMPINA | CJ70: Descrição problema 06.04.2016 14:50:22 TATE73320 ATT GEANE AG:TURIACU 9956 SOLICITA PARA SRA EVANGELINA FERREIRA OLIVEIRA LPEDIDO DE LIGACAO NOVA CLIENTE DESEJA FINANCIAR PADRAO DE 5 METROS 24 VEZES TATE73320JUCILENE
B71: 0 | D71: 1982405 | E71: 1001222410 | F71: UNR | G71: 46160 | H71: 0 | I71: ATIV | J71: Pré Análise | K71: 0 | L71: MO | M71: PAT1 | N71: NOROESTE | O71: TURIAÇU | P71: 64.84 | Q71: 46.79 | R71: 241.89 | S71: 1.621 | T71: 0.51988889 | U71: ROSILENE OLIVEIRA MELO | V71: 3000479259 | W71: 2000026611 | X71: CAMPINA DOS ROCHOS S/N / CAMPINA DOS ROCHOS | Y71: RURAL | Z71: -1.8541225 | AA71: -45.285684 | AB71: APOS A CAMPINA | CJ71: Descrição problema 06.04.2016 15:24:41 TATE09323 ATD: GEANE AG: TURIAÇU INF QUE CLIENTE ROSILENE OLIVEIRA MELO DESEJA O FINANCIAMENTO DE PADRÃO COMPLETO DE 24X DE 5 METROS TATE09323 LILIANE
B72: 0 | D72: 1981932 | E72: 1001284460 | F72: UNR | G72: 46160 | H72: 0 | I72: ATIV | J72: Pré Análise | K72: 0 | L72: MO | M72: PAT2 | N72: SUL | O72: ALTO PARNAÍBA | P72: 1929.03 | Q72: 802.69 | R72: 1536.04 | S72: 48.22575 | T72: 8.9187778 | U72: JOSIAS LUSTOSA DE PAULA | V72: 3000506639 | W72: 2000028147 | X72: ALTO DO PARNAIBA A LIZARDA 38 / LAVRAS | Y72: RURAL | Z72: -9.4246966 | AA72: -46.24776 | AB72: PADRAO CONSTRUIDO LOCALIZADO NA TORRE REAL- DEPOIS 24KM DOS MORRINHOS- NAO POSSUI TELEFONE DE CONTAT | CJ72: PARA ZONA RURAL, JÁ POSSUI PADRAO MONTADO. REF: LOCALIZADO NA TORRE REAL- DEPOIS 24KM DOS MORRINHOS- NAO POSSUI TELEFONE DE CONTATO- Sr. JOSIAS LUSTOSA DE PAULA VEIO ATENDIMENTO SOLICITAR LIGAÇÃO NOVA MONO 11.04.2016 15:19:20 TATE35395 TATE35395SAMYA Descrição problema
B73: 0 | D73: 1982390 | E73: 1001306342 | F73: UNR | G73: 46160 | H73: 0 | I73: ATIV | J73: Liberado para Levantamento | K73: Em levantamento | L73: MO | M73: PAT2 | N73: CENTRO | O73: ARAGUANA | P73: 91.16 | Q73: 101.49 | R73: 199.3 | S73: 2.279 | T73: 1.1276667 | U73: RONILDO DA CONCEICAO SILVA | V73: 3000511497 | W73: 2000028525 | X73: NUCLEO AD S/N / NUCLEO AB | Y73: RURAL | Z73: -3.1021262 | AA73: -45.709657 | AB73: PADRAO FINANCIADO FICA ANTES DA SEGUNDA PONTE UNS 300 METROS A DIREITA CLIENTE FILHO DO SR DIZIDERO | CJ73: direita casa do senhor dizidera A UC fica mas o menos uns 3 km da rede de MT último coponetev0482269 Descrição problema 12.04.2016 09:51:37 TCGB86377 parceiro solicita uma ligacao nova fica antes da segunda ponte do ad a
B74: 0 | D74: 1981723 | E74: 1001306700 | F74: UNR | G74: 46160 | H74: 0 | I74: FINL | J74: 0 | K74: 0 | L74: B | M74: PAT1 | N74: CENTRO | O74: BARRA DO CORDA | P74: 134.77 | Q74: 52.41 | R74: 170.73 | S74: 3.36925 | T74: 0.58233333 | U74: IRONILDA RODRIGUES MATIAS | V74: 3000513163 | W74: 2000028570 | X74: SAPUCAIA 14908 / CACHOEIRA COMPRIDA | Y74: RURAL | Z74: -5.6811168 | AA74: -45.530417 | AB74: ALDEIA SAPUCAIA DO MEARIM, PROCURAR CASA DA IRONILDA | CJ74: CPF E RG, SOLICITA LIGACAO NOVA 12.04.2016 10:19:57 TCGB08347 Sr. IRONILDA RODRIGUES MATIAS, VEIO AO ATENDIMENTO COM DOCS ORIGINAIS JOABE Para expansão Descrição problema
B75: 0 | D75: 1981452 | E75: 1001313378 | F75: UNR | G75: 46160 | H75: 0 | I75: ATIV | J75: Pré Análise | K75: 0 | L75: MO | M75: PAT1 | N75: NOROESTE | O75: TURIAÇU | P75: 64.84 | Q75: 46.79 | R75: 241.89 | S75: 1.621 | T75: 0.51988889 | U75: DINAILDE PINHEIRO OLIVEIRA | V75: 3000517061 | W75: 2000028717 | X75: CAMPINA DOS ROCHOS 1 / CAMPINA DOS ROCHOS | Y75: RURAL | Z75: -1.8541225 | AA75: -45.285684 | AB75: TRATA-SE DO PV SÃO SALVADOR | CJ75: Descrição problema 12.04.2016 14:08:00 TATE84314 ATT: JEANE AG: TURIACU 09833971496 9956 SOLICITA LIGACAO NOVA A MESMA INFORMA QUE CLIENTE DESJA FINANCIAR O PADRAO DE 5 METROS EM 24X DE 14 R$ TATE84314 FERNANDA
B76: 0 | D76: 1982148 | E76: 1001426883 | F76: UNR | G76: 46160 | H76: 0 | I76: FINL | J76: 0 | K76: 0 | L76: B | M76: PAT1 | N76: CENTRO | O76: BARRA DO CORDA | P76: 134.77 | Q76: 52.41 | R76: 170.73 | S76: 3.36925 | T76: 0.58233333 | U76: MARIA JULIA RODRIGUES GUAJAJARA | V76: 3000552959 | W76: 2000031383 | X76: SAPUCAIA S/N / CACHOEIRA COMPRIDA | Y76: RURAL | Z76: -5.6811168 | AA76: -45.530417 | AB76: PADRAO FINANCIADO DE 7 METROS FICA NA ALDEIA SAPUCAIA DO MEARIM DEPOIS DA COLONIA CC VZ 36662409 POS | CJ76: ATD PALOMA MARIA JULIA RODRIGUES GUAJAJARA SOLICITOU LIGAÇÃO NOVA COM FINANCIAMENTO Descrição problema Para expansão 18.04.2016 10:29:31 TCGB61302 DE PADRÃO SOLICITU PARCELAR EM 24 PARCELAS DE 14,07
B77: 0 | D77: 1981555 | E77: 1001448872 | F77: UNI | G77: 46160 | H77: 0 | I77: ATIV | J77: Liberado para Levantamento | K77: Em levantamento | L77: MO | M77: PAT1 | N77: SUL | O77: SÍTIO NOVO | P77: 5.78 | Q77: 4.44 | R77: 19.6 | S77: 0.1445 | T77: 0.049333333 | U77: EVALDO BARBOSA DA SILVA | V77: 3000562105 | W77: 2000031829 | X77: PACIENCIA S, N / CARVALHADA | Y77: URBANO | Z77: -5.8249343 | AA77: -46.16254 | CJ77: EVALDO BARBOSA DA SILVA, veio ao atendimento solicitar uma LIGAÇÃO NOVA Poste 1511363 Descrição problema 19.04.2016 08:58:56 TDPL59326 O mesmo possui dois debitos 03/2014 e 02/2016 em outra CC mais foram Referencia: Proximo a Vila Grupo Novo e ao Sr. Domingo de Assis. o mesmo ciente do valor deseja parcelar em 24 vezes de 14,07. Ponto de pagos dia 04.04.2016 na casa loterica. COM FINANCIAMENTO DE PADRÃO DE 7 METROS
B78: 0 | D78: 1981968 | E78: 1023765373 | F78: UNR | G78: 46160 | H78: 0 | I78: ATIV | J78: Pré Análise | K78: 0 | L78: B | M78: PAT3 | N78: NORTE | O78: AGUA DOCE DO MARANHAO | P78: 312.83 | Q78: 364.99 | R78: 555.63 | S78: 7.82075 | T78: 4.0554444 | U78: KENILSON SILVA VERAS | V78: 3006826309 | W78: 2000356528 | X78: MANOEL PEREIRA S/N / CANA BRAVA | Y78: RURAL | Z78: -3.0668437 | AA78: -42.218529 | AB78: FPC7 DEPOIS DO POSTO DE GASOLINA DO OSVALDO ULTIMA CASA SENTIDO TUTOIA POR TRAS DO CANTEIRO DE OBRAS | CJ78: Descrição problema 16.10.2018 11:12:14 TATE50359 Casa a 210m da rede de baixa tensão poste 4045567 medidor visinho 10143204703 componente 2066412. 14,07 CLIENTE COM DEBITO NEGOCIADO LIGAÇÃO NOVA COM FINANCIAMENTO DE PADRAO COMPLETO TOTAL 337,67 EM 24X
B79: 0 | D79: 1981519 | E79: 1001662721 | F79: UNR | G79: 46160 | H79: PASSIVO | I79: CANC | J79: Liberado para Levantamento | K79: Correção de levantamento | L79: MO | M79: PAT1 | N79: CENTRO | O79: COROATÁ | P79: 57.11 | Q79: 31.12 | R79: 109.74 | S79: 1.42775 | T79: 0.34577778 | U79: ELIETE CARDOSO BEZERRA | V79: 3000621969 | W79: 2000036049 | X79: BOM JARDIM S/N / BOM JARDIM | Y79: RURAL | Z79: -4.1274992 | AA79: -44.160229 | AB79: FPC7; POV BOM JARDIM/ CAPITÃO DO MATO PROX: CASA DO SEU ANTONIO, E AO LADO DA CASA DO SEU DEMILSON. | CJ79: PROX: CASA DO SEU ANTONIO, E AO LADO DA CASA DO SEU DEMILSON. sra ELIETE CARDOSO BEZERRA VEIO AO ATENDIMENTO SOLICITAR LIGAÇÃO NOVA EM SUA RESIDENCIA. A MESMA DESEJA FINANCIAMENTO COMPLETO DO PADRAO. 60 mts da bt poste 1972803 padrão financiado completo no atendimento 29.04.2016 08:27:53 TCGB27394 TITULAR: ELIETE CARDOSO BEZERRA. Descrição problema POV BOM JARDIM/ CAPITÃO DO MATO
B80: 0 | D80: 1981748 | E80: 1001826710 | F80: UNR | G80: 46160 | H80: 0 | I80: ATIV | J80: Liberado para Levantamento | K80: Em levantamento | L80: MO | M80: PAT1 | N80: SUL | O80: SÍTIO NOVO | P80: 1137.56 | Q80: 103.21 | R80: 63.35 | S80: 28.439 | T80: 1.1467778 | U80: JACKSON DE SOUSA MIRANDA | V80: 3000667969 | W80: 2000038887 | X80: TIUBA S/N / TIUBA | Y80: RURAL | Z80: -6.5047562 | AA80: -46.49099 | AB80: PROX A FAZ DO JOAO AZEVEDO | CJ80: TATE54359 - LEUCIVAN ATT:DAMASIO AG: SITIO NOVO , SOLICITA LIGACAO NOVA PARA CLIENTE JACKSON DE SOUSA MIRANDA, COM FINANCIAMENTO DE PADRAO DE CINCO METROS :FINANCIAMENTO DE PADRAO NA CEMAR VALOR 337,67 / 24 DE 14,07 Descrição problema Poste1999634 06.05.2016 11:35:53 TATE54359
B81: 0 | D81: 1981764 | E81: 1001926344 | F81: UNR | G81: 46160 | H81: 0 | I81: FINL | J81: 0 | K81: 0 | L81: B | M81: PAT2 | N81: CENTRO | O81: BARRA DO CORDA | P81: 134.77 | Q81: 52.41 | R81: 170.73 | S81: 3.36925 | T81: 0.58233333 | U81: JARCIO RODRIGUES GAUAJAJARA | V81: 3000691517 | W81: 2000040253 | X81: SAPUCAIA S/N / CACHOEIRA COMPRIDA | Y81: RURAL | Z81: -5.6811168 | AA81: -45.530417 | AB81: EXPANSAO FINANCIAR PADRAO EM CAMPO CC VZ 36723220 FICA DEPOIS DA ALDEIA REMANSO VZ A OLINDA | CJ81: DEPOIS DA ALDEIA REMANSO VZ A OLINDA TRATA SE DA ALDEIA SAPUCAIA NOVA REFERENCIA, EXPANSAO FINANCIAR PADRAO EM CAMPO CC VZ 36723220 FICA TCGB61302PALOMA 11.05.2016 10:12:07 TCGB61302 Descrição problema Expansão SR. JARCIO RODRIGUES GAUAJAJARAVEIO AO ATENDIMENT E SOLICIOU LIGAÇAO
B82: 0 | D82: 1982500 | E82: 1002329299 | F82: UNR | G82: 46160 | H82: 0 | I82: ATIV | J82: Pré Análise | K82: 0 | L82: MO | M82: PAT1 | N82: CENTRO | O82: JENIPAPO DOS VIEIRAS | P82: 151.84 | Q82: 76.4 | R82: 711.7 | S82: 3.796 | T82: 0.84888889 | U82: VICENTE QUIRINO DA SILVA | V82: 3000838542 | W82: 2000049975 | X82: SABONETE S/N / CENTRO | Y82: RURAL | Z82: -5.1483702 | AA82: -45.501934 | AB82: ACEITA FINANCIAR PADRAO, EXPANSÃO CC VZ 7496680VZ A 3 KM FAZENDA SAO FRANCISCO TEL 99 3423 6006 ETAP | CJ82: DE 54,23 PAGA DIA 01/06/2016 AS 12:065 NO BANCO DO BRASIL, REFERENCIA Descrição problema DOCUMENTOS ORIGINAIS RG,CPF, APRESENTOU FAT PAGA DE CMP 05/2016 NO VALOR Sr. VICENTE QUIRINO DA SILVA VEIO AO ATENDIMENTO APRESENTOU OS FRANCISCO VZ AO TONHÃO TCGB61302PALOMA Para expansão 01.06.2016 12:27:00 TCGB61302 ACEITA FINANCIAR PADRÃO, EXPANSÃO CC VZ 7496680 vz a 3 km TEL 99 3423 6006 Etapa,Livro,Seq 30,006535,87TEL 34236006 TRATA SE DA FZ SAO
B83: 0 | D83: 1981821 | E83: 1002353451 | F83: UNR | G83: 46160 | H83: 0 | I83: ATIV | J83: Pré Análise | K83: Em levantamento | L83: MO | M83: PAT2 | N83: NOROESTE | O83: TURIAÇU | P83: 11.95 | Q83: 11.73 | R83: 70.53 | S83: 0.29875 | T83: 0.13033333 | U83: JOINA DE JESUS FERREIRA SILVA | V83: 3000845611 | W83: 2000050432 | X83: CAMPO GRANDE S/N / CAMPO GRANDE | Y83: RURAL | Z83: -1.8853765 | AA83: -45.232436 | AB83: EM FRENTE AO CAMPO DE BOLA | CJ83: FINANCIAMENTO DE PADRAO NA CEMAR VALOR 337,67 / 24 DE 14,07. TATE54359 - ATT:GEANE AG: TURIACU, SOLICITA LIGACAO NOVA PRA CLIENTE JOINA DE JESUS Descrição problema FERREIRA SILVA, COM FINANCIAMENTO DE PADRAO COM POSTE DE SETE METROS. 02.06.2016 10:23:42 TATE54359 Cliente mora atrás de outros terreno e fica a 55 m da rede de baixa tensão LEUCIVAN
B84: 0 | D84: 1982183 | E84: 1002379573 | F84: UNR | G84: 46160 | H84: 0 | I84: ATIV | J84: Liberado para Levantamento | K84: Em levantamento | L84: MO | M84: PAT1 | N84: NOROESTE | O84: GOVERNADOR NUNES FREIRE | P84: 95.87 | Q84: 65.66 | R84: 85.09 | S84: 2.39675 | T84: 0.72955556 | U84: MASCIMIANO ANICETO DE SOUSA | V84: 3000854670 | W84: 2000050915 | X84: QDA 10 CIDELANCIA 1 / QD 10 CIDELANCIA | Y84: RURAL | Z84: -2.1676137 | AA84: -45.968124 | AB84: PROX. A RESIDENCIA DA SENHORA JOSEFA E AO LADO DA RESIDENCIA DO SENHOR ANTONIO JOSE. | CJ84: 03.06.2016 10:04:43 TMON60300 TMON60300 PARCEIRO DE NEGOCIO SOLICITA UMA LIGAÇÃO NOVA COM FINANCIAMENTO DE Descrição problema PADRAO COM POSTE DE 7 METROS. NEIDYANE
B85: 0 | D85: 1982520 | E85: 1002379944 | F85: UNR | G85: 46160 | H85: 0 | I85: ATIV | J85: Pré Análise | K85: 0 | L85: MO | M85: PAT3 | N85: SUL | O85: FORMOSA DA SERRA NEGRA | P85: 755.25 | Q85: 62.19 | R85: 68.17 | S85: 18.88125 | T85: 0.691 | U85: WEDILLA NASCIMENTO DOS SANTOS | V85: 3000853843 | W85: 2000050948 | X85: CABECEIRA S/N / CABECEIRA VERDE | Y85: RURAL | Z85: -6.6219467 | AA85: -46.160306 | AB85: EM FRENTE A CASA NO NATAL JORGE | CJ85: POSTE DE SETE METROS - FINANCIAMENTO DE PADRAO NA CEMAR VALOR 337,67 / Descrição problema 61850516308 03.06.2016 10:32:05 TATE54359 24 DE 14,07. TATE54359 - LEUCIVAN CLIENTE WEDILLA NASCIMENTO DOS SANTOS, COM FINANCIAMENTO DE PADRAO COM ATT:MATEUS AG: FARMOSA DA SERRA NEGRA, SOLICITA LIGACAO NOVA PARA
B86: 0 | D86: 1981810 | E86: 1002564149 | F86: UNR | G86: 46160 | H86: 0 | I86: ATIV | J86: Pré Análise | K86: 0 | L86: MO | M86: PAT1 | N86: NOROESTE | O86: SANTA LUZIA DO PARUA | P86: 955.19 | Q86: 84.34 | R86: 347.04 | S86: 23.87975 | T86: 0.93711111 | U86: JOAO SOUSA DA SILVA | V86: 3000922233 | W86: 2000055179 | X86: PITU S/N / PITU | Y86: RURAL | Z86: -2.6024554 | AA86: -45.868414 | AB86: DEPOIS DO CAJUEIRO, ESTRADA DA PITU, ENTRADA PROXIMO A CASA DE PROJETO. CENTRO DO ZEZICO, CASA DO MI | CJ86: Descrição problema Poste At 1977500 mais próximo fica a 20 metros da casa, fica na frente da UC LIGAÇÃO NOVA, PADRÃO FINANCIADO 13.06.2016 16:11:47 TATE45397
B87: 0 | D87: 1981955 | E87: 1002729676 | F87: UNR | G87: 46160 | H87: 0 | I87: ATIV | J87: Liberado para Levantamento | K87: Em levantamento | L87: MO | M87: PAT2 | N87: SUL | O87: GRAJAÚ | P87: 818.84 | Q87: 276.91 | R87: 813.31 | S87: 20.471 | T87: 3.0767778 | U87: JUDITE DOS SANTOS BARROS | V87: 3000980390 | W87: 2000059217 | X87: PRINCIPAL S/N / LAGOA TELHA | Y87: RURAL | Z87: -5.6587499 | AA87: -45.88131 | AB87: POSSUI PADRAO PROX AO POÇO ARTESIANO PROX AO RAIMUNDO BANDEIRA DENTRO DO PV LAGOA DA TELHA | CJ87: Descrição problema 21.06.2016 10:45:12 TATE85387 Poste 1015-797 mais de 170mts BT LIGAÇÃO NOVA
B88: 0 | D88: 1981693 | E88: 1002810718 | F88: UNR | G88: 46160 | H88: 0 | I88: ATIV | J88: Pré Análise | K88: 0 | L88: B | M88: PAT1 | N88: CENTRO | O88: VARGEM GRANDE | P88: 45.59 | Q88: 44.23 | R88: 66.13 | S88: 1.13975 | T88: 0.49144444 | U88: GRACILENE DOS SANTOS NASCIMENTO | V88: 3001009132 | W88: 2000060927 | X88: SAQUINHO S/N / BELA VISTA | Y88: RURAL | Z88: -3.8396771 | AA88: -43.818846 | AB88: FPC7; ENTRE O POVOADO CAJUAZEDO E CANDEI, PX: ESCLOLA E FRANCCISCO CARLOS. | CJ88: 24.06.2016 08:57:53 TATE80333 FPC 7 IRA FINANCIAR EM 24X DE 14,07, ENTRE O POVOADO CAJUAZEDO E CANDEI, Descrição problema PX: ESCLOLA E FRANCCISCO CARLOS. Da rede de bt para a casa do cliente da 85mts...trafo mais próximo da casa da cliente. ..1973126..
B89: 0 | D89: 1981319 | E89: 1002857729 | F89: UNR | G89: 46160 | H89: 0 | I89: ATIV | J89: Pré Análise | K89: 0 | L89: MO | M89: PAT3 | N89: CENTRO | O89: TUNTUM | P89: 1982.04 | Q89: 825.05 | R89: 919.39 | S89: 49.551 | T89: 9.1672222 | U89: ANTONIO RAIMUNDO DOS SANTOS SOUSA | V89: 3001031022 | W89: 2000062594 | X89: SAO RAIMUNDO S/N / SAO RAIMUNDO | Y89: RURAL | Z89: -5.2111991 | AA89: -44.754863 | AB89: FPC 7 DEPOIS DA ALDEIA, NO POVOADO A CASA DO CLIENTE FICA QUASE NO FINAL DO POVOADO , VIZINHO AO JA | CJ89: EM 24 VEZES DE 14,07 FPC 7 CLIENTE ANTONIO RAIMUNDO DOS SANTOS SOUSA VEIO NO ATENDIMENTO SOLICITAR POVOADO , VIZINHO AO JANIEL, CLIENTE CONHECIDO COMO ZILON DEPOIS DA ALDEIA, NO POVOADO A CASA DO CLIENTE FICA QUASE NO FINAL DO Distância aproximadamente 1000m poste 1332606 PARCELADO 27.06.2016 15:02:42 TCGB87399 Descrição problema REFERENCIA LIGAÇÃO NOVA ONDE O MESMO DESEJA O PADRAO FINANCIADO DE 337,67 O MESMO
B90: 0 | D90: 1982265 | E90: 1002858386 | F90: UNR | G90: 46160 | H90: 0 | I90: ATIV | J90: Pré Análise | K90: 0 | L90: MO | M90: PAT2 | N90: CENTRO | O90: VARGEM GRANDE | P90: 344.24 | Q90: 32.59 | R90: 161.23 | S90: 8.606 | T90: 0.36211111 | U90: OSWALDO NASCIMENTO SANTOS | V90: 3001031316 | W90: 2000062641 | X90: OURIVES S/N / RURAL | Y90: RURAL | Z90: -3.5225847 | AA90: -43.879385 | AB90: FPC 7 ; POVOADO LAGOA PRETA, ENTRE O POVOADO OUVIRES E CARAIBA, PX : AO SENHOR OSVALDO, PN CONHECIDO | CJ90: 1889965poste mais próximo da casa do cliente da 1000mts ENTRE O POVOADO OUVIRES E CARAIBA, PX : AO SENHOR OSVALDO, PN CONHECIDO FPF7 ; IRA FINANCIAR O PADRAO EM 24X DE 14,07, POVOADO LAGOA PRETA, Descrição problema 27.06.2016 15:32:04 TATE80333 COMO FILHO, TEL:098992381187.
B91: 0 | D91: 1981582 | E91: 1002860027 | F91: UNR | G91: 46160 | H91: 0 | I91: ATIV | J91: Pré Análise | K91: 0 | L91: MO | M91: PAT1 | N91: CENTRO | O91: TUNTUM | P91: 1982.04 | Q91: 825.05 | R91: 919.39 | S91: 49.551 | T91: 9.1672222 | U91: FRANCIMAR DE MORAIS ALMEIDA | V91: 3001031960 | W91: 2000062736 | X91: SAO RAIMUNDO 15240 / SAO RAIMUNDO | Y91: RURAL | Z91: -5.2111991 | AA91: -44.754863 | AB91: POVOADO SÃO RAIMUNDO | CJ91: Distância aproximadamente 1000m poste 1332606 POVOADO SÃO RAIMUNDO ACESSO A ESTRADA DA ALDEIA A ONDE TEM QUE CLIENTE VEIO ATE O ATENDIMENTO A MESMA SOLICITA LIGAÇÃO NOVA CLIENTE DESEJA FINANCIAMENTO DE PADRÃO DE ENTRADA DESTE CC A MESMA FICAR NO Descrição problema 27.06.2016 16:53:43 TCGB65376 ATRAVESSAR.
B92: 0 | D92: 1982264 | E92: 1002881293 | F92: UNR | G92: 46160 | H92: 0 | I92: ATIV | J92: Pré Análise | K92: 0 | L92: MO | M92: PAT2 | N92: CENTRO | O92: VARGEM GRANDE | P92: 344.24 | Q92: 32.59 | R92: 161.23 | S92: 8.606 | T92: 0.36211111 | U92: OSVALDO SILVA SANTOS | V92: 3001037551 | W92: 2000063027 | X92: OURIVES S/N / RURAL | Y92: RURAL | Z92: -3.5225847 | AA92: -43.879385 | AB92: FPC 7 ; POVOADO LAGOA PRETA, FICA ENTRE O OURIVES E CARAIBA, PX; FILHO,PN CONHECIDO COMO OSVALDO TE | CJ92: 28.06.2016 09:19:26 TATE80333 FPC 7 ; IRA FINANCIAR O PADRAO EM 24 X DE 14,07, POVOADO LAGOA PRETA, Da casa do cliente para rede de bt da 1000mts..poste mais próximo da casa do cliente 1889965... TEL:098991960720 FICA ENTRE O OURIVES E CARAIBA, PX; FILHO,PN CONHECIDO COMO OSVALDO Descrição problema
B93: 0 | D93: 1981769 | E93: 1002881515 | F93: UNR | G93: 46160 | H93: 0 | I93: ATIV | J93: Pré Análise | K93: 0 | L93: MO | M93: PAT1 | N93: CENTRO | O93: VARGEM GRANDE | P93: 344.24 | Q93: 32.59 | R93: 161.23 | S93: 8.606 | T93: 0.36211111 | U93: JASSIARA NASCIMENTO SANTOS | V93: 3001037829 | W93: 2000063058 | X93: OURIVES S/N / RURAL | Y93: RURAL | Z93: -3.5225847 | AA93: -43.879385 | AB93: FPC 7 ; POVOADO LAGOA PRETA, FICA ENTRE O OURIVES E CARAIBA, PX; FILHO,PN CONHECIDA COMO JASSIARA T | CJ93: Da casa do cliente para rede de bt da 1000mts..poste mais próximo da casa do cliente. . 28.06.2016 09:43:05 TATE80333 TEL:098991483233 Descrição problema FPC 7 ; IRA FINANCIAR O PADRAO EM 24X DE 14,07; POVOADO LAGOA PRETA, FICA ENTRE O OURIVES E CARAIBA, PX; FILHO,PN CONHECIDA COMO JASSIARA
B94: RAIMUNDO JHONES ASSUNÇÃO DA LUZ | C94: 46265 | D94: 1982476 | E94: 1034631925 | F94: UNI | G94: 46160 | H94: PASSIVO | I94: ATIV | J94: Liberado para Levantamento | K94: Correção de levantamento | L94: MO | M94: PAT1 | N94: CENTRO | O94: ALTO ALEGRE DO MARANHAO | P94: 836.99 | Q94: 273.33 | R94: 850.76 | S94: 20.92475 | T94: 3.037 | U94: VALDECY GOMES DA SILVA | V94: 3009189776 | W94: 2000463360 | X94: VARJADO S/N / VARJADO | Y94: URBANO | Z94: -4.1928965 | AA94: -44.35702 | AB94: AO LADO DO JOSE ORLANDO | CJ94: 02.10.2019 12:16:35 TATE5503451 Descrição da solução CLASSE: RESIDENCIAL CPF: 000.614.543-46 RG: 165777020013 NAS:16/05/1962 NOME DA MÃE: MARIA SUPORTE CHAT TATE20358NATIELE DE REFERÊNCIA: AO LADO DO JOSE ORLANDO MUNICIPIO : ALTO ALEGRE - MA Descrição problema MASCULINO PROFISSÃO: LAVRADOR ENDEREÇO: PV VARJADO BAIRRO: VARJADO PONTO UC: 1 ____________________ GOMES DA SILVA NATURALIDADE: COROATA - MA ESTADO CIVIL:SOLTEIRO SEXO: LIGAÇÃO NOVA COM FINANCIAMENTO DE PADRÃO NOME: VALDECY GOMES DA SILVA Assunto: FINANCIAMENTO PADRÃO 24 X MOTA E COUTINHO LTDA ME(CREDALTOALEGREDOMA) Protocólo: 776765 Tipo de Atendimento: ATENDIMENTO CREDENCIADOS Área de expansão, Cliente encontra-se a mais de 50 mts do último poste da rede de BT.
B95: 0 | D95: 1982094 | E95: 1003121254 | F95: UNI | G95: 46160 | H95: 0 | I95: ATIV | J95: Avaliação de Expurgo | K95: Improdutivo | L95: MO | M95: PAT1 | N95: CENTRO | O95: MONCAO | P95: 257.63 | Q95: 128.41 | R95: 154.43 | S95: 6.44075 | T95: 1.4267778 | U95: MARIA DAS GRACAS VIEIRA DE FRANCA | V95: 3001133542 | W95: 2000068848 | X95: JUTAI S/N / JUTAI | Y95: 0 | Z95: -3.497197 | AA95: -45.253505 | AB95: FPC7;PV JUTAI DEPOIS DO PV ILHA DOS PAUS E SÃO JOÃO NO MEIO DO PV AO LADO DE JOSE MARTINS E MARCI | CJ95: PONTO DE REFERÊNCIA: PV JUTAI DEPOIS DO PV ILHA DOS PAUS E SÃO JOÃO FINANCIAMENTO DE PADRÃO EM 24 X 14,07. acesso normalizado: kledson Descrição problema PN SOLICITA PEDIDO LIGAÇÃO DE SUAS INSTALAÇÕES A MESMA DESEJA O Sem acesso para carro NO MEIO DO PV AO LADO DE JOSE MARTINS E MARCIA E MARIA JOSE 08.07.2016 10:23:17 TATE41033
B96: 0 | D96: 1981318 | E96: 1003209407 | F96: UNR | G96: 46160 | H96: 0 | I96: CANC | J96: Liberado para Levantamento | K96: Em levantamento | L96: MO | M96: PAT1 | N96: CENTRO | O96: PEDREIRAS | P96: 168.26 | Q96: 120.66 | R96: 274.51 | S96: 4.2065 | T96: 1.3406667 | U96: ANTONIO PEREIRA SILVA | V96: 3001163670 | W96: 2000070351 | X96: SITIO NOVO S/N / CENTRO | Y96: RURAL | Z96: -4.5326257 | AA96: -44.573687 | AB96: FPC7 337,67 EM 24 X 14,07 ANTES DO POV SANTA MARIA DOBRA DOBRA A DIREITA VIZINHOS EDEZIO MAGALH | CJ96: Sr. ANTONIO PEREIRA DA SILVA SOLICITA UMA LIGACAO NOVA O FINANCIOU O 13.07.2016 09:52:13 TATE31376 Descrição problema PADRAO COMPLETO FPC7 337,67 EM 24 X 14,07 O MESMO APRESENTOU FATURA PAGA FPC7 337,67 EM 24 X 14,07 ANTES DO POV SANTA MARIA DOBRA DOBRA A EM SEU NOME COMPT 02/2016 13,18 PAGA NA CASA LOTERICA DIA 11/07/2016 AS REFERENCIA Poste 494888 Coponente 1175033 Distância 3km 09:02 DIREITA VIZINHOS EDEZIO MAGALHES E JOAQUIM CONHECIDO COMO PATRICIO
B97: 0 | D97: 1981310 | E97: 1003235787 | F97: UNR | G97: 46160 | H97: 0 | I97: ATIV | J97: Pré Análise | K97: Em levantamento | L97: MO | M97: PAT2 | N97: CENTRO | O97: POCAO DE PEDRAS | P97: 47.35 | Q97: 48.31 | R97: 32.93 | S97: 1.18375 | T97: 0.53677778 | U97: ANTONIO MENDES ALVES | V97: 3001176454 | W97: 2000071093 | X97: FEITOSA S/N / CENTRO | Y97: RURAL | Z97: -4.7605168 | AA97: -44.62953 | AB97: FPC5 337,67 24 X 14,07 POV ENTRE TERRA SANTA E SAO PEDRO VAI PELO TRANSUAL PASSA PELOS POV BOM LUGAR | CJ97: Poste n: 1108550. REFERENCIA SR ANTONIO MENDES ALVES SOLICITA LIG NOVA O MESMO FINANCIOU PADRAO COMO ANTONIO MENDES FPC5 337,67 24 X 14,07 POV ENTRE TERRA SANTA E SAO PEDRO VAI PELO TRANSUAL PASSA PELOS POV BOM LUGAR TERRA SANTA E CHEGA NO BELEM DOS LAGES PX AO BAR DO EROTILDE VIZINHOS ZE MOURAO E VANESSA CLT CONHECIDO Descrição problema 14.07.2016 12:01:35 TATE85318 COMPLETO FPC5 337,67 24 X 14,07
B98: 0 | D98: 1982129 | E98: 1003237307 | F98: UNR | G98: 46160 | H98: 0 | I98: ATIV | J98: Pré Análise | K98: Em levantamento | L98: MO | M98: PAT2 | N98: CENTRO | O98: POCAO DE PEDRAS | P98: 359.74 | Q98: 405.16 | R98: 399.54 | S98: 8.9935 | T98: 4.5017778 | U98: MARIA EMILENE RODRIGUES DA SILVA | V98: 3001178848 | W98: 2000071179 | X98: SAO JOAO S/N / CENTRO | Y98: RURAL | Z98: -4.7462737 | AA98: -44.948573 | AB98: FPC7 337,67 24 X 14,07 CASA NO POV SAO JOAO QUE FICA ENTRE OS POV BELEM DOS LAGES E MANDI DEPOIS DO | CJ98: ELA APRESENTOU FAT PAGA COMPT 05/2016 24,16 DA CC 5981727 PAGA NA CAS 14.07.2016 15:05:59 TATE85318 PADRAO COMPLETO FPC7 337,67 24 X 14,07 CONHECIDA COMO MARIA 99 9 8152 2013 FPC7 337,67 24 X 14,07 CASA NO POV SAO JOAO QUE FICA ENTRE OS POV BELEM PARA IR PRO SAO JOAO VIZINHOS CONHECIDO TOIN DO VALDEMAR E MUNDOCA Poste n: 1108550 REFERENCIA LOTERICA DIA 14/07/2016 AS 14:39 DOS LAGES E MANDI DEPOIS DO COLEGIO E DEPOIS DO POSTO DE SAUDE DEPOIS DO Descrição problema POV BELEM DOS LAGES ENTRA NA RUA EM FRENTE A CASA DO TOIM DO VALDEMAR SRA MARIA EMILENE RODRIGUES DA SILVA SOLICITA LIG NOVA A MESMA FINANCIOU
B99: 0 | D99: 1982654 | E99: 1003259797 | F99: UNR | G99: 46160 | H99: 0 | I99: ATIV | J99: Pré Análise | K99: Em levantamento | L99: MO | M99: PAT1 | N99: CENTRO | O99: POCAO DE PEDRAS | P99: 359.74 | Q99: 405.16 | R99: 399.54 | S99: 8.9935 | T99: 4.5017778 | U99: FRANCISCO ALVES DA SILVA | V99: 3001182802 | W99: 2000071423 | X99: SAO JOAO S/N / CENTRO | Y99: RURAL | Z99: -4.7462737 | AA99: -44.948573 | AB99: FICA ENTRE OS POVOADOS BELEM E MANDI, AO LADO DO SR NELSON, PROXIMO A ESCOLA SARNEY FILHO, SOLICITAN | CJ99: NELSON, PROXIMO A ESCOLA SARNEY FILHO, SOLICITANTE APELIDADO DE TIQUIM TEL: 99 996414069 VALOR TOTAL DE 337,67 DIVIDIDO EM 24X DE 14,07, O MESMO (A) CIENTE DO PONTO DE REF: FICA ENTRE OS POVOADOS BELEM E MANDI, AO LADO DO SR PN SOLICITA LIG NOVA COM FINANCIAMENTO DE PADRAO COMPLETO (FPC7) NO Descrição problema VALOR TOTAL E DA FORMA PARCELADO 15.07.2016 09:35:30 TATE97306 Post3 n: 1108550
B100: 0 | D100: 1981280 | E100: 1003303055 | F100: UNR | G100: 46160 | H100: 0 | I100: ATIV | J100: Liberado para Levantamento | K100: Em levantamento | L100: MO | M100: PAT1 | N100: CENTRO | O100: JENIPAPO DOS VIEIRAS | P100: 22.64 | Q100: 36.82 | R100: 144.11 | S100: 0.566 | T100: 0.40911111 | U100: ANTONIO COSTA DOS REIS | V100: 3001201408 | W100: 2000072278 | X100: SABONETE SN / CENTRO | Y100: RURAL | Z100: -5.4925523 | AA100: -45.272355 | AB100: FINAN EM 24 X 14,07 FICA PROX LAGOA DO SABONETE - JENIPAPO DOS VIEIRAS - FAZENDA SANTO ANTONIO - VIZ | CJ100: FAZENDA SANTO ANTONIO - VIZ FAZENDA DO VICENTE QUIRINO Descrição problema Para expansão. LIGACAO NOVA, Sr. ANTONIO COSTA DOS REIS, VEIO AO ATENDIMENTO COM CPF E RG, SOLICTA 18.07.2016 17:12:16 TATE08347 FINAN EM 24 X 14,07 FICA PROX LAGOA DO SABONETE - JENIPAPO DOS VIEIRAS - JOABE
...

Sheet DADOS
A1: PI'S | E1: NORTE | J1: NOROESTE | O1: SUL | T1: CENTRO | Y1: LESTE
A2: PI | B2: Tipo | C2: Qtd dias | D2: Data final | E2: Gerente | F2: Executivo | G2: Empresa | H2: Contrato | I2: Técnico | J2: Gerente | K2: Executivo | L2: Empresa | M2: Contrato | N2: Técnico | O2: Gerente | P2: Executivo | Q2: Empresa | R2: Contrato | S2: Técnico | T2: Gerente | U2: Executivo | V2: Empresa | W2: Contrato | X2: Técnico | Y2: Gerente | Z2: Executivo | AA2: Empresa | AB2: Contrato | AC2: Técnico | AD2: Tipo de NS|Parceiro | AE2: Resp. Obra | AH2: TIPO DE OBRA NO SISCO | AI2: TIPO DE OBRA | AJ2: SIGLA | AM2: REGIONAL | AN2: SIGLA-MUNICIPIO | AO2: MUNICIPIO | AP2: SIGLA | AR2: ID DO NUMERO | AS2: SIGLA | AU2: OBRA ESPECIAL? | AW2: REGIONAL NORTE | AX2: RESPONSÁVEL EQTL PROJETO/EXECUÇÃO | AY2: ALEATÓRIOENTRE
A3: ASC | B3: MANUTENÇÃO | C3: 175 | D3: =TODAY()+C3 -> 46441 | E3: ALINEZ MARTINS RABELO COSTA | F3: JEFFERSON CARLOS ARAUJO DOS REIS | G3: DPL - 1º | H3: 4600024693 | I3: JOILSON PINHEIRO CASTRO | J3: DANILO ARRAES DOS SANTOS JACINTO | K3: RICARDO DOS ANJOS LIMA | L3: DPL - 1º | M3: 4600024693 | N3: VERIFICAR NO SGO/SISCO/SISCO | O3: RENAN ACCIOLY PIMENTEL | P3: JOSÉ TARCÍSIO FONTELES NETO | Q3: DPL - 3º | R3: 4600024692 | S3: LUIS FELIPE MUNIZ DOS SANTOS SOUSA | T3: LUCIO DANIEL SOARES DOS SANTOS | U3: ADRIANNO BENEDICTO RABELO AQUINO | V3: CGB - 1° | W3: 4600026661 | X3: DAYLLING ALMEIDA | GESIMIEL SIVA | Y3: SIDNEY CORREA DE ALMEIDA JUNIOR | Z3: JOCIMAR GOMES MAGALHAES JUNIOR | AA3: DPL - 1º | AB3: 4600024691 | AC3: RODRIGO PEREIRA DE ALMEIDA | AD3: SOLICITAÇÃO CLIENTE|CLIENTE | AE3: EXCLUSIVA DA DISTRIBUIDORA
A4: ATV | B4: EXPANSÃO | C4: 175 | D4: =TODAY()+C4 -> 46441 | E4: ALINEZ MARTINS RABELO COSTA | F4: JOSELILSON DE SOUZA LIMA | G4: DPL - 1º | H4: 4600024693 | I4: =IFERROR(INDEX(AX:AX,MATCH(#REF!,DADOS!AW:AW,0)),"Verificar tabela da norte") -> Verificar tabela da norte | J4: DANILO ARRAES DOS SANTOS JACINTO | K4: JANDERSON PAIXÃO DOS SANTOS | L4: DPL - 1º | M4: 4600024693 | N4: VERIFICAR NO SGO/SISCO | O4: RENAN ACCIOLY PIMENTEL | P4: LETICIA CRISTINA DA SILVA BARATA | Q4: DPL - 3º | R4: 4600024692 | S4: VERIFICAR NO SGO/SISCO | T4: LUCIO DANIEL SOARES DOS SANTOS | U4: ALEXANDRE LUIS SILVA SANTOS | V4: CGB - 1° | W4: 4600026661 | X4: VERIFICAR NO SGO/SISCO | Y4: SIDNEY CORREA DE ALMEIDA JUNIOR | Z4: MARCO AURELIO NOLETO MENDES DA SILVA | AA4: DPL - 1º | AB4: 4600024691 | AC4: VERIFICAR NO SGO/SISCO | AH4: AMPLIAÇÃO DE FASE | AI4: AF-AMPLIAÇÃO DE FASE | AJ4: AF | AM4: SUL | AN4: =AP4&"-"&AO4 -> ACL-ACAILANDIA | AO4: ACAILANDIA | AP4: ACL | AR4: AL-Alimentador Tronco | AS4: AL | AU4: OE-Obras Juridicas e/ou Especiais | AW4: AGUA DOCE DO MARANHAO | AX4: =INDEX(AY4:BA4,RANDBETWEEN(1,3)) -> KESSEL LEONEL | AY4: BENILSON SOARES SILVA | AZ4: KESSEL LEONEL | BA4: PERICLES PEREIRA
A5: BCP | B5: EXPANSÃO | C5: 175 | D5: =TODAY()+C5 -> 46441 | E5: ALINEZ MARTINS RABELO COSTA | F5: JOSELILSON DE SOUZA LIMA | G5: DPL - 1º | H5: 4600024693 | I5: =IFERROR(INDEX(AX:AX,MATCH(#REF!,DADOS!AW:AW,0)),"Verificar tabela da norte") -> Verificar tabela da norte | J5: DANILO ARRAES DOS SANTOS JACINTO | K5: JANDERSON PAIXÃO DOS SANTOS | L5: DPL - 1º | M5: 4600024693 | N5: VERIFICAR NO SGO/SISCO | O5: RENAN ACCIOLY PIMENTEL | P5: LETICIA CRISTINA DA SILVA BARATA | Q5: DPL - 3º | R5: 4600024692 | S5: VERIFICAR NO SGO/SISCO | T5: LUCIO DANIEL SOARES DOS SANTOS | U5: ALEXANDRE LUIS SILVA SANTOS | V5: CGB - 1° | W5: 4600026661 | X5: VERIFICAR NO SGO/SISCO | Y5: SIDNEY CORREA DE ALMEIDA JUNIOR | Z5: MARCO AURELIO NOLETO MENDES DA SILVA | AA5: DPL - 1º | AB5: 4600024691 | AC5: ARLAN DE SOUSA AMARANTE | AD5: PLANO DETERMINATIVO|INTERNO | AE5: EXCLUSIVA DA DISTRIBUIDORA | AH5: AMPLIAÇÃO DE POTENCIA | AI5: AP-AMPLIAÇÃO DE POTENCIA | AJ5: AP | AM5: LESTE | AN5: =AP5&"-"&AO5 -> AFC-AFONSO CUNHA | AO5: AFONSO CUNHA | AP5: AFC | AR5: BA-Barramento | AS5: BA | AU5: EX-Exceções | AW5: ARAIOSES | AX5: =INDEX(AY5:BA5,RANDBETWEEN(1,3)) -> KESSEL LEONEL | AY5: BENILSON SOARES SILVA | AZ5: KESSEL LEONEL | BA5: PERICLES PEREIRA
A6: BRE | B6: EXPANSÃO | C6: 175 | D6: =TODAY()+C6 -> 46441 | E6: ALINEZ MARTINS RABELO COSTA | F6: JOSELILSON DE SOUZA LIMA | G6: DPL - 1º | H6: 4600024693 | I6: =IFERROR(INDEX(AX:AX,MATCH(#REF!,DADOS!AW:AW,0)),"Verificar tabela da norte") -> Verificar tabela da norte | J6: DANILO ARRAES DOS SANTOS JACINTO | K6: JANDERSON PAIXÃO DOS SANTOS | L6: DPL - 1º | M6: 4600024693 | N6: VERIFICAR NO SGO/SISCO | O6: RENAN ACCIOLY PIMENTEL | P6: LETICIA CRISTINA DA SILVA BARATA | Q6: DPL - 3º | R6: 4600024692 | S6: VERIFICAR NO SGO/SISCO | T6: LUCIO DANIEL SOARES DOS SANTOS | U6: ALEXANDRE LUIS SILVA SANTOS | V6: CGB - 1° | W6: 4600026661 | X6: VERIFICAR NO SGO/SISCO | Y6: SIDNEY CORREA DE ALMEIDA JUNIOR | Z6: MARCO AURELIO NOLETO MENDES DA SILVA | AA6: DPL - 1º | AB6: 4600024691 | AC6: VERIFICAR NO SGO/SISCO | AD6: PLANO DETERMINATIVO|INTERNO | AE6: EXCLUSIVA DA DISTRIBUIDORA | AH6: CONSTRUÇÃO DE AL | AI6: CA-CONSTRUÇÃO DE AL | AJ6: CA | AM6: NORTE | AN6: =AP6&"-"&AO6 -> ADM-AGUA DOCE DO MARANHAO | AO6: AGUA DOCE DO MARANHAO | AP6: ADM | AR6: CC-Conta Contrato | AS6: CC | AW6: MAGALHAES DE ALMEIDA | AX6: =INDEX(AY6:BA6,RANDBETWEEN(1,3)) -> PERICLES PEREIRA | AY6: BENILSON SOARES SILVA | AZ6: KESSEL LEONEL | BA6: PERICLES PEREIRA
A7: BRT | B7: EXPANSÃO | C7: 175 | D7: =TODAY()+C7 -> 46441 | E7: ALINEZ MARTINS RABELO COSTA | F7: JOSELILSON DE SOUZA LIMA | G7: DPL - 1º | H7: 4600024693 | I7: =IFERROR(INDEX(AX:AX,MATCH(#REF!,DADOS!AW:AW,0)),"Verificar tabela da norte") -> Verificar tabela da norte | J7: DANILO ARRAES DOS SANTOS JACINTO | K7: JANDERSON PAIXÃO DOS SANTOS | L7: DPL - 1º | M7: 4600024693 | N7: JOSE GEORGE VIEGAS SILVA | O7: RENAN ACCIOLY PIMENTEL | P7: LETICIA CRISTINA DA SILVA BARATA | Q7: DPL - 3º | R7: 4600024692 | S7: LUCAS SILVA OLIVEIRA | T7: LUCIO DANIEL SOARES DOS SANTOS | U7: ALEXANDRE LUIS SILVA SANTOS | V7: CGB - 1° | W7: 4600026661 | X7: OTTON CILIO CORREA DA SILVA | Y7: SIDNEY CORREA DE ALMEIDA JUNIOR | Z7: MARCO AURELIO NOLETO MENDES DA SILVA | AA7: DPL - 1º | AB7: 4600024691 | AC7: ARLAN DE SOUSA AMARANTE | AD7: PLANO DETERMINATIVO|INTERNO | AE7: EXCLUSIVA DA DISTRIBUIDORA | AH7: CONSTRUÇÃO DE RD | AI7: CT-CONSTRUÇÃO DE RD | AJ7: CT | AM7: NOROESTE | AN7: =AP7&"-"&AO7 -> ACT-ALCANTARA | AO7: ALCANTARA | AP7: ACT | AR7: ID-IDENTIFICADOR | AS7: ID | AW7: PAULINO NEVES | AX7: =INDEX(AY7:BA7,RANDBETWEEN(1,3)) -> PERICLES PEREIRA | AY7: BENILSON SOARES SILVA | AZ7: KESSEL LEONEL | BA7: PERICLES PEREIRA
A8: CCF | B8: EXPANSÃO | C8: 175 | D8: =TODAY()+C8 -> 46441 | E8: ALINEZ MARTINS RABELO COSTA | F8: JOSELILSON DE SOUZA LIMA | G8: DPL - 1º | H8: 4600024693 | I8: =IFERROR(INDEX(AX:AX,MATCH(#REF!,DADOS!AW:AW,0)),"Verificar tabela da norte") -> Verificar tabela da norte | J8: DANILO ARRAES DOS SANTOS JACINTO | K8: JANDERSON PAIXÃO DOS SANTOS | L8: DPL - 1º | M8: 4600024693 | N8: BENERALDO RABELO FILHO | O8: RENAN ACCIOLY PIMENTEL | P8: LETICIA CRISTINA DA SILVA BARATA | Q8: DPL - 3º | R8: 4600024692 | S8: LUCAS SILVA OLIVEIRA | T8: LUCIO DANIEL SOARES DOS SANTOS | U8: ALEXANDRE LUIS SILVA SANTOS | V8: CGB - 1° | W8: 4600026661 | X8: FABRICIO ANTONIO OLIVIEIRA MOTA | Y8: SIDNEY CORREA DE ALMEIDA JUNIOR | Z8: MARCO AURELIO NOLETO MENDES DA SILVA | AA8: DPL - 1º | AB8: 4600024691 | AC8: MARK SUEL FURTADO | AD8: SOLICITAÇÃO CLIENTE|CLIENTE | AE8: EXCLUSIVA DA DISTRIBUIDORA | AH8: DIVISÃO DE CIRCUITO | AI8: DV-DIVISÃO DE CIRCUITO | AJ8: DV | AM8: LESTE | AN8: =AP8&"-"&AO8 -> ADA-ALDEIAS ALTAS | AO8: ALDEIAS ALTAS | AP8: ADA | AR8: PF-CPF do cliente | AS8: PF | AW8: SANTANA DO MARANHAO | AX8: =INDEX(AY8:BA8,RANDBETWEEN(1,3)) -> PERICLES PEREIRA | AY8: BENILSON SOARES SILVA | AZ8: KESSEL LEONEL | BA8: PERICLES PEREIRA
A9: DIF | B9: EXPANSÃO | C9: 175 | D9: =TODAY()+C9 -> 46441 | E9: ALINEZ MARTINS RABELO COSTA | F9: JOSELILSON DE SOUZA LIMA | G9: DPL - 1º | H9: 4600024693 | I9: =IFERROR(INDEX(AX:AX,MATCH(#REF!,DADOS!AW:AW,0)),"Verificar tabela da norte") -> Verificar tabela da norte | J9: DANILO ARRAES DOS SANTOS JACINTO | K9: JANDERSON PAIXÃO DOS SANTOS | L9: DPL - 1º | M9: 4600024693 | N9: BENERALDO RABELO FILHO | O9: RENAN ACCIOLY PIMENTEL | P9: LETICIA CRISTINA DA SILVA BARATA | Q9: DPL - 3º | R9: 4600024692 | S9: LUCAS SILVA OLIVEIRA | T9: LUCIO DANIEL SOARES DOS SANTOS | U9: ALEXANDRE LUIS SILVA SANTOS | V9: CGB - 1° | W9: 4600026661 | X9: FABRICIO ANTONIO OLIVIEIRA MOTA | Y9: SIDNEY CORREA DE ALMEIDA JUNIOR | Z9: MARCO AURELIO NOLETO MENDES DA SILVA | AA9: DPL - 1º | AB9: 4600024691 | AC9: MARK SUEL FURTADO | AD9: SOLICITAÇÃO CLIENTE|CLIENTE | AE9: EXCLUSIVA DA DISTRIBUIDORA | AH9: FLEXIBILIZAÇÃO DE CIRCUITO | AI9: FC-FLEXIBILIZAÇÃO DE CIRCUITO | AJ9: FC | AM9: CENTRO | AN9: =AP9&"-"&AO9 -> ALM-ALTAMIRA DO MARANHAO | AO9: ALTAMIRA DO MARANHAO | AP9: ALM | AR9: NS-Nota CCS | AS9: NS | AW9: SAO BERNARDO | AX9: =INDEX(AY9:BA9,RANDBETWEEN(1,3)) -> PERICLES PEREIRA | AY9: BENILSON SOARES SILVA | AZ9: KESSEL LEONEL | BA9: PERICLES PEREIRA
A10: DIS | B10: EXPANSÃO | C10: 220 | D10: =TODAY()+C10 -> 46486 | E10: ALINEZ MARTINS RABELO COSTA | F10: JOSELILSON DE SOUZA LIMA | G10: DPL - 1º | H10: 4600024693 | I10: =IFERROR(INDEX(AX:AX,MATCH(#REF!,DADOS!AW:AW,0)),"Verificar tabela da norte") -> Verificar tabela da norte | J10: DANILO ARRAES DOS SANTOS JACINTO | K10: JANDERSON PAIXÃO DOS SANTOS | L10: DPL - 1º | M10: 4600024693 | N10: SANDRO HENRIQUE GOMES | O10: RENAN ACCIOLY PIMENTEL | P10: LETICIA CRISTINA DA SILVA BARATA | Q10: DPL - 3º | R10: 4600024692 | S10: VERIFICAR NO SGO/SISCO | T10: LUCIO DANIEL SOARES DOS SANTOS | U10: ALEXANDRE LUIS SILVA SANTOS | V10: CGB - 1° | W10: 4600026661 | X10: NEYVALDO LOPES MORAES | Y10: SIDNEY CORREA DE ALMEIDA JUNIOR | Z10: MARCO AURELIO NOLETO MENDES DA SILVA | AA10: DPL - 1º | AB10: 4600024691 | AC10: ARLAN DE SOUSA AMARANTE | AD10: PLANO DETERMINATIVO|INTERNO | AE10: EXCLUSIVA DA DISTRIBUIDORA | AH10: INSTALAÇÃO DE EQUIPAMENTOS | AI10: IE-INSTALAÇÃO DE EQUIPAMENTOS | AJ10: IE | AM10: CENTRO | AN10: =AP10&"-"&AO10 -> AAM-ALTO ALEGRE DO MARANHAO | AO10: ALTO ALEGRE DO MARANHAO | AP10: AAM | AR10: NR-Nota de Reclamação | AS10: NR | AW10: TUTOIA | AX10: =INDEX(AY10:BA10,RANDBETWEEN(1,3)) -> KESSEL LEONEL | AY10: BENILSON SOARES SILVA | AZ10: KESSEL LEONEL | BA10: PERICLES PEREIRA
A11: EME | B11: MANUTENÇÃO | C11: 160 | D11: =TODAY()+C11 -> 46426 | E11: ALINEZ MARTINS RABELO COSTA | F11: JEFFERSON CARLOS ARAUJO DOS REIS | G11: DPL - 1º | H11: 4600024693 | I11: JOILSON PINHEIRO CASTRO | J11: DANILO ARRAES DOS SANTOS JACINTO | K11: RICARDO DOS ANJOS LIMA | L11: DPL - 1º | M11: 4600024693 | N11: VERIFICAR NO SGO/SISCO | O11: RENAN ACCIOLY PIMENTEL | P11: JOSÉ TARCÍSIO FONTELES NETO | Q11: DPL - 3º | R11: 4600024692 | S11: VERIFICAR NO SGO/SISCO | T11: LUCIO DANIEL SOARES DOS SANTOS | U11: ADRIANNO BENEDICTO RABELO AQUINO | V11: CGB - 1° | W11: 4600026661 | X11: VERIFICAR NO SGO/SISCO | Y11: SIDNEY CORREA DE ALMEIDA JUNIOR | Z11: JOCIMAR GOMES MAGALHAES JUNIOR | AA11: DPL - 1º | AB11: 4600024691 | AC11: VERIFICAR NO SGO/SISCO | AH11: INSTALAÇÃO DE TRANSFORMADORES | AI11: IT-INSTALAÇÃO DE TRANSFORMADORES | AJ11: IT | AM11: CENTRO | AN11: =AP11&"-"&AO11 -> AAP-ALTO ALEGRE DO PINDARE | AO11: ALTO ALEGRE DO PINDARE | AP11: AAP | AR11: CO-Numero Componente | AS11: CO | AW11: BARREIRINHAS | AX11: =INDEX(AY11:BA11,RANDBETWEEN(1,2)) -> SEBASTIÃO JORGE | AY11: SEBASTIÃO JORGE | AZ11: RAISSA NAIARARA OLIVEIRA | BA11: ISMAR SOUSA
A12: ERD | B12: MANUTENÇÃO | C12: 175 | D12: =TODAY()+C12 -> 46441 | E12: ALINEZ MARTINS RABELO COSTA | F12: JEFFERSON CARLOS ARAUJO DOS REIS | G12: DPL - 1º | H12: 4600024693 | I12: JOILSON PINHEIRO CASTRO | J12: DANILO ARRAES DOS SANTOS JACINTO | K12: RICARDO DOS ANJOS LIMA | L12: DPL - 1º | M12: 4600024693 | N12: ADRIANDO MENDES COSTA | O12: RENAN ACCIOLY PIMENTEL | P12: JOSÉ TARCÍSIO FONTELES NETO | Q12: DPL - 3º | R12: 4600024692 | S12: LUCAS DAVI DOS SANTOS SILVA | T12: LUCIO DANIEL SOARES DOS SANTOS | U12: ADRIANNO BENEDICTO RABELO AQUINO | V12: CGB - 1° | W12: 4600026661 | X12: OTTON CILIO CORREA DA SILVA | Y12: SIDNEY CORREA DE ALMEIDA JUNIOR | Z12: JOCIMAR GOMES MAGALHAES JUNIOR | AA12: DPL - 1º | AB12: 4600024691 | AC12: ARLAN DE SOUSA AMARANTE | AD12: PLANO DETERMINATIVO|INTERNO | AE12: EXCLUSIVA DA DISTRIBUIDORA | AH12: MELHORIA DE REDE | AI12: ME-MELHORIA DE REDE DE DISTRIBUIÇÃO | AJ12: ME | AM12: SUL | AN12: =AP12&"-"&AO12 -> ALP-ALTO PARNAIBA | AO12: ALTO PARNAIBA | AP12: ALP | AR12: OC-Ocorrência | AS12: OC | AW12: HUMBERTO DE CAMPOS | AX12: =INDEX(AY12:BA12,RANDBETWEEN(1,2)) -> RAISSA NAIARARA OLIVEIRA | AY12: SEBASTIÃO JORGE | AZ12: RAISSA NAIARARA OLIVEIRA | BA12: ISMAR SOUSA
A13: EUR | B13: EXPANSÃO | C13: 175 | D13: =TODAY()+C13 -> 46441 | E13: ALINEZ MARTINS RABELO COSTA | F13: JOSELILSON DE SOUZA LIMA | G13: DPL - 1º | H13: 4600024693 | I13: =IFERROR(INDEX(AX:AX,MATCH(#REF!,DADOS!AW:AW,0)),"Verificar tabela da norte") -> Verificar tabela da norte | J13: DANILO ARRAES DOS SANTOS JACINTO | K13: JANDERSON PAIXÃO DOS SANTOS | L13: DPL - 1º | M13: 4600024693 | N13: VERIFICAR NO SGO/SISCO | O13: RENAN ACCIOLY PIMENTEL | P13: LETICIA CRISTINA DA SILVA BARATA | Q13: DPL - 3º | R13: 4600024692 | S13: GILVAN CARDOSO VIANA | T13: LUCIO DANIEL SOARES DOS SANTOS | U13: ALEXANDRE LUIS SILVA SANTOS | V13: CGB - 1° | W13: 4600026661 | X13: VERIFICAR NO SGO/SISCO | Y13: SIDNEY CORREA DE ALMEIDA JUNIOR | Z13: MARCO AURELIO NOLETO MENDES DA SILVA | AA13: DPL - 1º | AB13: 4600024691 | AC13: JONAS FELIPE AS MELO | AD13: SOLICITAÇÃO CLIENTE|CLIENTE | AE13: EXCLUSIVA DA DISTRIBUIDORA | AH13: MICROSSISTEMA ISOLADO DE | AI13: MI-MICROSSISTEMA ISOLADO DE GERAÇÃO DE ENERGIA | AJ13: MI | AM13: NOROESTE | AN13: =AP13&"-"&AO13 -> AMM-AMAPA DO MARANHAO | AO13: AMAPA DO MARANHAO | AP13: AMM | AR13: PT-Parecer Técnico | AS13: PT | AW13: PRIMEIRA CRUZ | AX13: =INDEX(AY13:BA13,RANDBETWEEN(1,2)) -> RAISSA NAIARARA OLIVEIRA | AY13: SEBASTIÃO JORGE | AZ13: RAISSA NAIARARA OLIVEIRA | BA13: ISMAR SOUSA
A14: FIM | B14: MANUTENÇÃO | C14: 190 | D14: =TODAY()+C14 -> 46456 | E14: ALINEZ MARTINS RABELO COSTA | F14: JEFFERSON CARLOS ARAUJO DOS REIS | G14: DPL - 1º | H14: 4600024693 | I14: JOILSON PINHEIRO CASTRO | J14: DANILO ARRAES DOS SANTOS JACINTO | K14: RICARDO DOS ANJOS LIMA | L14: DPL - 1º | M14: 4600024693 | N14: JOSE MARCIANO SILVA | O14: RENAN ACCIOLY PIMENTEL | P14: JOSÉ TARCÍSIO FONTELES NETO | Q14: DPL - 3º | R14: 4600024692 | S14: LUIS FELIPE MUNIZ DOS SANTOS | T14: LUCIO DANIEL SOARES DOS SANTOS | U14: ADRIANNO BENEDICTO RABELO AQUINO | V14: CGB - 1° | W14: 4600026661 | X14: NEYVALDO LOPES | ANDERSON APOLIANO | Y14: SIDNEY CORREA DE ALMEIDA JUNIOR | Z14: JOCIMAR GOMES MAGALHAES JUNIOR | AA14: DPL - 1º | AB14: 4600024691 | AC14: ARLAN DE SOUSA AMARANTE | AD14: PLANO DETERMINATIVO|INTERNO | AE14: EXCLUSIVA DA DISTRIBUIDORA | AH14: REALOCAÇÃO DE POSTE | AI14: MP-REALOCAÇÃO DE POSTE | AJ14: MP | AM14: SUL | AN14: =AP14&"-"&AO14 -> AMO-AMARANTE DO MARANHAO | AO14: AMARANTE DO MARANHAO | AP14: AMO | AR14: PG-Ponto Geográfico | AS14: PG | AW14: SANTO AMARO DO MARANHAO | AX14: =INDEX(AY14:BA14,RANDBETWEEN(1,2)) -> SEBASTIÃO JORGE | AY14: SEBASTIÃO JORGE | AZ14: RAISSA NAIARARA OLIVEIRA | BA14: ISMAR SOUSA
A15: INC | B15: EXPANSÃO | C15: 175 | D15: =TODAY()+C15 -> 46441 | E15: ALINEZ MARTINS RABELO COSTA | F15: JOSELILSON DE SOUZA LIMA | G15: DPL - 1º | H15: 4600024693 | I15: =IFERROR(INDEX(AX:AX,MATCH(#REF!,DADOS!AW:AW,0)),"Verificar tabela da norte") -> Verificar tabela da norte | J15: DANILO ARRAES DOS SANTOS JACINTO | K15: JANDERSON PAIXÃO DOS SANTOS | L15: DPL - 1º | M15: 4600024693 | N15: VERIFICAR NO SGO/SISCO | O15: RENAN ACCIOLY PIMENTEL | P15: LETICIA CRISTINA DA SILVA BARATA | Q15: DPL - 3º | R15: 4600024692 | S15: GILVAN CARDOSO VIANA | T15: LUCIO DANIEL SOARES DOS SANTOS | U15: ALEXANDRE LUIS SILVA SANTOS | V15: CGB - 1° | W15: 4600026661 | X15: VERIFICAR NO SGO/SISCO | Y15: SIDNEY CORREA DE ALMEIDA JUNIOR | Z15: MARCO AURELIO NOLETO MENDES DA SILVA | AA15: DPL - 1º | AB15: 4600024691 | AC15: VERIFICAR NO SGO/SISCO | AH15: REALOCAÇÃO DE TRANSFORMADORES | AI15: MT-REALOCAÇÃO DE TRANSFORMADORES RD | AJ15: MT | AM15: CENTRO | AN15: =AP15&"-"&AO15 -> ANA-ANAJATUBA | AO15: ANAJATUBA | AP15: ANA | AR15: OS-Ordem de Serviço | AS15: OS | AW15: AXIXA | AX15: =INDEX(AY15:BA15,RANDBETWEEN(1,3)) -> SERGIO SANTOS | AY15: SERGIO SANTOS | AZ15: RENAN CUNHA | BA15: GABRIEL RODRIGUES
A16: INR | B16: EXPANSÃO | C16: 220 | D16: =TODAY()+C16 -> 46486 | E16: ALINEZ MARTINS RABELO COSTA | F16: JOSELILSON DE SOUZA LIMA | G16: DPL - 1º | H16: 4600024693 | I16: =IFERROR(INDEX(AX:AX,MATCH(#REF!,DADOS!AW:AW,0)),"Verificar tabela da norte") -> Verificar tabela da norte | J16: DANILO ARRAES DOS SANTOS JACINTO | K16: JANDERSON PAIXÃO DOS SANTOS | L16: DPL - 1º | M16: 4600024693 | N16: VERIFICAR NO SGO/SISCO | O16: RENAN ACCIOLY PIMENTEL | P16: LETICIA CRISTINA DA SILVA BARATA | Q16: DPL - 3º | R16: 4600024692 | S16: VERIFICAR NO SGO/SISCO | T16: LUCIO DANIEL SOARES DOS SANTOS | U16: ALEXANDRE LUIS SILVA SANTOS | V16: CGB - 1° | W16: 4600026661 | X16: VERIFICAR NO SGO/SISCO | Y16: SIDNEY CORREA DE ALMEIDA JUNIOR | Z16: MARCO AURELIO NOLETO MENDES DA SILVA | AA16: DPL - 1º | AB16: 4600024691 | AC16: VERIFICAR NO SGO/SISCO | AH16: RECAPACITAÇÃO DE CONDUTORES | AI16: RC-RECAPACITAÇÃO DE CONDUTORES | AJ16: RC | AM16: LESTE | AN16: =AP16&"-"&AO16 -> ANS-ANAPURUS | AO16: ANAPURUS | AP16: ANS | AR16: TR-Tempo Real | AS16: TR | AW16: BACABEIRA | AX16: =INDEX(AY16:BA16,RANDBETWEEN(1,3)) -> SERGIO SANTOS | AY16: SERGIO SANTOS | AZ16: RENAN CUNHA | BA16: GABRIEL RODRIGUES
A17: LPT | B17: EXPANSÃO | C17: 190 | D17: =TODAY()+C17 -> 46456 | E17: ALINEZ MARTINS RABELO COSTA | F17: JOSELILSON DE SOUZA LIMA | G17: DPL - 1º | H17: 4600024693 | I17: RAISSA NAIARA OLIVVEIRA | J17: DANILO ARRAES DOS SANTOS JACINTO | K17: JANDERSON PAIXÃO DOS SANTOS | L17: DPL - 1º | M17: 4600024693 | N17: VERIFICAR NO SGO/SISCO | O17: RENAN ACCIOLY PIMENTEL | P17: LETICIA CRISTINA DA SILVA BARATA | Q17: DPL - 3º | R17: 4600024692 | S17: JOSÉ DE ARAUJO ANDRADE JUNIOR | T17: LUCIO DANIEL SOARES DOS SANTOS | U17: ALEXANDRE LUIS SILVA SANTOS | V17: MANSERV | W17: 4600025343 | X17: FRANCISCO FRAZÃO JUNIOR | Y17: SIDNEY CORREA DE ALMEIDA JUNIOR | Z17: MARCO AURELIO NOLETO MENDES DA SILVA | AA17: ULTRA | AB17: 4600025405 | AC17: PEDRO VICTOR DE SOUSA MOURA | AD17: SOLICITAÇÃO CLIENTE|CLIENTE | AE17: EXCLUSIVA DA DISTRIBUIDORA | AH17: RECAPACITAÇÃO DE EQUIPAMENTOS | AI17: RE-RECAPACITAÇÃO DE EQUIPAMENTOS DE RD | AJ17: RE | AM17: NOROESTE | AN17: =AP17&"-"&AO17 -> API-APICUM-ACU | AO17: APICUM-ACU | AP17: API | AW17: CACHOEIRA GRANDE | AX17: =INDEX(AY17:BA17,RANDBETWEEN(1,3)) -> GABRIEL RODRIGUES | AY17: SERGIO SANTOS | AZ17: RENAN CUNHA | BA17: GABRIEL RODRIGUES
A18: MBT | B18: MANUTENÇÃO | C18: 190 | D18: =TODAY()+C18 -> 46456 | E18: ALINEZ MARTINS RABELO COSTA | F18: JEFFERSON CARLOS ARAUJO DOS REIS | G18: DPL - 1º | H18: 4600024693 | I18: JOILSON PINHEIRO CASTRO | J18: DANILO ARRAES DOS SANTOS JACINTO | K18: RICARDO DOS ANJOS LIMA | L18: DPL - 1º | M18: 4600024693 | N18: JOSE MARCIANO SILVA | O18: RENAN ACCIOLY PIMENTEL | P18: JOSÉ TARCÍSIO FONTELES NETO | Q18: DPL - 3º | R18: 4600024692 | S18: ADRIANO ARAUJO FERNANDES | T18: LUCIO DANIEL SOARES DOS SANTOS | U18: ADRIANNO BENEDICTO RABELO AQUINO | V18: CGB - 1° | W18: 4600026661 | X18: NEYVALDO LOPES MORAES | Y18: SIDNEY CORREA DE ALMEIDA JUNIOR | Z18: JOCIMAR GOMES MAGALHAES JUNIOR | AA18: DPL - 1º | AB18: 4600024691 | AC18: ARLAN DE SOUSA AMARANTE | AD18: PLANO DETERMINATIVO|INTERNO | AE18: EXCLUSIVA DA DISTRIBUIDORA | AH18: RECAPACITAÇÃO DE C,FA, | AI18: RF-RECAPACITAÇÃO DE C,FA, C,FU E PR | AJ18: RF | AM18: CENTRO | AN18: =AP18&"-"&AO18 -> ARA-ARAGUANA | AO18: ARAGUANA | AP18: ARA | AW18: ICATU | AX18: =INDEX(AY18:BA18,RANDBETWEEN(1,3)) -> RENAN CUNHA | AY18: SERGIO SANTOS | AZ18: RENAN CUNHA | BA18: GABRIEL RODRIGUES
A19: MCJ | B19: MANUTENÇÃO | C19: 175 | D19: =TODAY()+C19 -> 46441 | E19: ALINEZ MARTINS RABELO COSTA | F19: JEFFERSON CARLOS ARAUJO DOS REIS | G19: DPL - 1º | H19: 4600024693 | I19: JOILSON PINHEIRO CASTRO | J19: DANILO ARRAES DOS SANTOS JACINTO | K19: RICARDO DOS ANJOS LIMA | L19: DPL - 1º | M19: 4600024693 | N19: VERIFICAR NO SGO/SISCO | O19: RENAN ACCIOLY PIMENTEL | P19: JOSÉ TARCÍSIO FONTELES NETO | Q19: DPL - 3º | R19: 4600024692 | S19: VERIFICAR NO SGO/SISCO | T19: LUCIO DANIEL SOARES DOS SANTOS | U19: ADRIANNO BENEDICTO RABELO AQUINO | V19: CGB - 1° | W19: 4600026661 | X19: VERIFICAR NO SGO/SISCO | Y19: SIDNEY CORREA DE ALMEIDA JUNIOR | Z19: JOCIMAR GOMES MAGALHAES JUNIOR | AA19: DPL - 1º | AB19: 4600024691 | AC19: VERIFICAR NO SGO/SISCO | AH19: RECAPACITAÇÃO DE POSTES | AI19: RP-RECAPACITAÇÃO DE POSTES | AJ19: RP | AM19: NORTE | AN19: =AP19&"-"&AO19 -> ARS-ARAIOSES | AO19: ARAIOSES | AP19: ARS | AW19: MORROS | AX19: =INDEX(AY19:BA19,RANDBETWEEN(1,3)) -> RENAN CUNHA | AY19: SERGIO SANTOS | AZ19: RENAN CUNHA | BA19: GABRIEL RODRIGUES
A20: MCR | B20: MANUTENÇÃO | C20: 175 | D20: =TODAY()+C20 -> 46441 | E20: ALINEZ MARTINS RABELO COSTA | F20: JEFFERSON CARLOS ARAUJO DOS REIS | G20: DPL - 1º | H20: 4600024693 | I20: JOILSON PINHEIRO CASTRO | J20: DANILO ARRAES DOS SANTOS JACINTO | K20: RICARDO DOS ANJOS LIMA | L20: DPL - 1º | M20: 4600024693 | N20: VERIFICAR NO SGO/SISCO | O20: RENAN ACCIOLY PIMENTEL | P20: JOSÉ TARCÍSIO FONTELES NETO | Q20: DPL - 3º | R20: 4600024692 | S20: VERIFICAR NO SGO/SISCO | T20: LUCIO DANIEL SOARES DOS SANTOS | U20: ADRIANNO BENEDICTO RABELO AQUINO | V20: CGB - 1° | W20: 4600026661 | X20: VERIFICAR NO SGO/SISCO | Y20: SIDNEY CORREA DE ALMEIDA JUNIOR | Z20: JOCIMAR GOMES MAGALHAES JUNIOR | AA20: DPL - 1º | AB20: 4600024691 | AC20: VERIFICAR NO SGO/SISCO | AH20: RECAPACITAÇÃO DE TRANSFORMADOR | AI20: RT-RECAPACITAÇÃO DE TRANSFORMADOR DE RD | AJ20: RT | AM20: SUL | AN20: =AP20&"-"&AO20 -> AME-ARAME | AO20: ARAME | AP20: AME | AW20: PACO DO LUMIAR | AX20: =INDEX(AY20:BA20,RANDBETWEEN(1,3)) -> RENAN CUNHA | AY20: SERGIO SANTOS | AZ20: RENAN CUNHA | BA20: GABRIEL RODRIGUES
A21: MEL | B21: EXPANSÃO | C21: 220 | D21: =TODAY()+C21 -> 46486 | E21: ALINEZ MARTINS RABELO COSTA | F21: JOSELILSON DE SOUZA LIMA | G21: DPL - 1º | H21: 4600024693 | I21: =IFERROR(INDEX(AX:AX,MATCH(#REF!,DADOS!AW:AW,0)),"Verificar tabela da norte") -> Verificar tabela da norte | J21: DANILO ARRAES DOS SANTOS JACINTO | K21: JANDERSON PAIXÃO DOS SANTOS | L21: DPL - 1º | M21: 4600024693 | N21: VERIFICAR NO SGO/SISCO | O21: RENAN ACCIOLY PIMENTEL | P21: LETICIA CRISTINA DA SILVA BARATA | Q21: DPL - 3º | R21: 4600024692 | S21: VERIFICAR NO SGO/SISCO | T21: LUCIO DANIEL SOARES DOS SANTOS | U21: ALEXANDRE LUIS SILVA SANTOS | V21: CGB - 1° | W21: 4600026661 | X21: NEYVALDO LOPES MORAES | Y21: SIDNEY CORREA DE ALMEIDA JUNIOR | Z21: MARCO AURELIO NOLETO MENDES DA SILVA | AA21: DPL - 1º | AB21: 4600024691 | AC21: ARLAN DE SOUSA AMARANTE | AD21: PLANO DETERMINATIVO|INTERNO | AE21: EXCLUSIVA DA DISTRIBUIDORA | AH21: SISTEMA INDIVIDUAL DE | AI21: SI-SISTEMA INDIVIDUAL DE GERAÇÃO DE ENERGIA | AJ21: SI | AM21: CENTRO | AN21: =AP21&"-"&AO21 -> ARI-ARARI | AO21: ARARI | AP21: ARI | AW21: PRESIDENTE JUSCELINO | AX21: =INDEX(AY21:BA21,RANDBETWEEN(1,3)) -> RENAN CUNHA | AY21: SERGIO SANTOS | AZ21: RENAN CUNHA | BA21: GABRIEL RODRIGUES
A22: MGD | B22: EXPANSÃO | C22: 175 | D22: =TODAY()+C22 -> 46441 | E22: ALINEZ MARTINS RABELO COSTA | F22: JOSELILSON DE SOUZA LIMA | G22: DPL - 1º | H22: 4600024693 | I22: JOSINALDO RIBEIRO | J22: DANILO ARRAES DOS SANTOS JACINTO | K22: JANDERSON PAIXÃO DOS SANTOS | L22: DPL - 1º | M22: 4600024693 | N22: BENERALDO RABELO FILHO | O22: RENAN ACCIOLY PIMENTEL | P22: LETICIA CRISTINA DA SILVA BARATA | Q22: DPL - 3º | R22: 4600024692 | S22: WLISSES DOS SANTOS MOURA | T22: LUCIO DANIEL SOARES DOS SANTOS | U22: ALEXANDRE LUIS SILVA SANTOS | V22: CGB - 1° | W22: 4600026661 | X22: LEANDRO CRISTHIAN MAFRA CRUZ | Y22: SIDNEY CORREA DE ALMEIDA JUNIOR | Z22: MARCO AURELIO NOLETO MENDES DA SILVA | AA22: DPL - 1º | AB22: 4600024691 | AC22: JONAS FELIPE AS MELO | AD22: PLANO DETERMINATIVO|INTERNO | AE22: EXCLUSIVA DA DISTRIBUIDORA | AH22: REALOCAÇÃO DE EQUIPAMENTOS | AI22: TE-REALOCAÇÃO DE EQUIPAMENTOS | AJ22: TE | AM22: NORTE | AN22: =AP22&"-"&AO22 -> AXX-AXIXA | AO22: AXIXA | AP22: AXX | AW22: RAPOSA | AX22: =INDEX(AY22:BA22,RANDBETWEEN(1,3)) -> SERGIO SANTOS | AY22: SERGIO SANTOS | AZ22: RENAN CUNHA | BA22: GABRIEL RODRIGUES
A23: MMT | B23: MANUTENÇÃO | C23: 175 | D23: =TODAY()+C23 -> 46441 | E23: ALINEZ MARTINS RABELO COSTA | F23: JEFFERSON CARLOS ARAUJO DOS REIS | G23: DPL - 1º | H23: 4600024693 | I23: JOILSON PINHEIRO CASTRO | J23: DANILO ARRAES DOS SANTOS JACINTO | K23: RICARDO DOS ANJOS LIMA | L23: DPL - 1º | M23: 4600024693 | N23: VERIFICAR NO SGO/SISCO | O23: RENAN ACCIOLY PIMENTEL | P23: JOSÉ TARCÍSIO FONTELES NETO | Q23: DPL - 3º | R23: 4600024692 | S23: ADRIANO MENDES COSTA | T23: LUCIO DANIEL SOARES DOS SANTOS | U23: ADRIANNO BENEDICTO RABELO AQUINO | V23: CGB - 1° | W23: 4600026661 | X23: NEYVALDO LOPES MORAES | Y23: SIDNEY CORREA DE ALMEIDA JUNIOR | Z23: JOCIMAR GOMES MAGALHAES JUNIOR | AA23: DPL - 1º | AB23: 4600024691 | AC23: ARLAN DE SOUSA AMARANTE | AD23: PLANO DETERMINATIVO|INTERNO | AE23: EXCLUSIVA DA DISTRIBUIDORA | AM23: CENTRO | AN23: =AP23&"-"&AO23 -> BCB-BACABAL | AO23: BACABAL | AP23: BCB | AW23: ROSARIO | AX23: =INDEX(AY23:BA23,RANDBETWEEN(1,3)) -> RENAN CUNHA | AY23: SERGIO SANTOS | AZ23: RENAN CUNHA | BA23: GABRIEL RODRIGUES
A24: MRS | B24: MANUTENÇÃO | C24: 175 | D24: =TODAY()+C24 -> 46441 | E24: ALINEZ MARTINS RABELO COSTA | F24: JEFFERSON CARLOS ARAUJO DOS REIS | G24: DPL - 1º | H24: 4600024693 | I24: JOILSON PINHEIRO CASTRO | J24: DANILO ARRAES DOS SANTOS JACINTO | K24: RICARDO DOS ANJOS LIMA | L24: DPL - 1º | M24: 4600024693 | N24: VERIFICAR NO SGO/SISCO | O24: RENAN ACCIOLY PIMENTEL | P24: JOSÉ TARCÍSIO FONTELES NETO | Q24: DPL - 3º | R24: 4600024692 | S24: VERIFICAR NO SGO/SISCO | T24: LUCIO DANIEL SOARES DOS SANTOS | U24: ADRIANNO BENEDICTO RABELO AQUINO | V24: CGB - 1° | W24: 4600026661 | X24: VERIFICAR NO SGO/SISCO | Y24: SIDNEY CORREA DE ALMEIDA JUNIOR | Z24: JOCIMAR GOMES MAGALHAES JUNIOR | AA24: DPL - 1º | AB24: 4600024691 | AC24: VERIFICAR NO SGO/SISCO | AM24: NORTE | AN24: =AP24&"-"&AO24 -> BCA-BACABEIRA | AO24: BACABEIRA | AP24: BCA | AW24: SANTA RITA | AX24: =INDEX(AY24:BA24,RANDBETWEEN(1,3)) -> RENAN CUNHA | AY24: SERGIO SANTOS | AZ24: RENAN CUNHA | BA24: GABRIEL RODRIGUES
A25: MSE | B25: MANUTENÇÃO | C25: 175 | D25: =TODAY()+C25 -> 46441 | E25: ALINEZ MARTINS RABELO COSTA | F25: JEFFERSON CARLOS ARAUJO DOS REIS | G25: DPL - 1º | H25: 4600024693 | I25: JOILSON PINHEIRO CASTRO | J25: DANILO ARRAES DOS SANTOS JACINTO | K25: RICARDO DOS ANJOS LIMA | L25: DPL - 1º | M25: 4600024693 | N25: VERIFICAR NO SGO/SISCO | O25: RENAN ACCIOLY PIMENTEL | P25: JOSÉ TARCÍSIO FONTELES NETO | Q25: DPL - 3º | R25: 4600024692 | S25: VERIFICAR NO SGO/SISCO | T25: LUCIO DANIEL SOARES DOS SANTOS | U25: ADRIANNO BENEDICTO RABELO AQUINO | V25: CGB - 1° | W25: 4600026661 | X25: VERIFICAR NO SGO/SISCO | Y25: SIDNEY CORREA DE ALMEIDA JUNIOR | Z25: JOCIMAR GOMES MAGALHAES JUNIOR | AA25: DPL - 1º | AB25: 4600024691 | AC25: VERIFICAR NO SGO/SISCO | AM25: NOROESTE | AN25: =AP25&"-"&AO25 -> BAC-BACURI | AO25: BACURI | AP25: BAC | AW25: SAO JOSE DE RIBAMAR | AX25: =INDEX(AY25:BA25,RANDBETWEEN(1,3)) -> GABRIEL RODRIGUES | AY25: SERGIO SANTOS | AZ25: RENAN CUNHA | BA25: GABRIEL RODRIGUES
A26: MTP | B26: EXPANSÃO | C26: 175 | D26: =TODAY()+C26 -> 46441 | E26: ALINEZ MARTINS RABELO COSTA | F26: JOSELILSON DE SOUZA LIMA | G26: DPL - 1º | H26: 4600024693 | I26: =IFERROR(VLOOKUP(#REF!,DADOS!AW:AX,2,0),"Verificar tabela da norte") -> Verificar tabela da norte | J26: DANILO ARRAES DOS SANTOS JACINTO | K26: JANDERSON PAIXÃO DOS SANTOS | L26: DPL - 1º | M26: 4600024693 | N26: BENERALDO RABELO FILHO | O26: RENAN ACCIOLY PIMENTEL | P26: LETICIA CRISTINA DA SILVA BARATA | Q26: DPL - 3º | R26: 4600024692 | S26: GILVAN CARDOSO VIANA | T26: LUCIO DANIEL SOARES DOS SANTOS | U26: ALEXANDRE LUIS SILVA SANTOS | V26: CGB - 1° | W26: 4600026661 | X26: LEANDRO CRISTHIAN MAFRA CRUZ | Y26: SIDNEY CORREA DE ALMEIDA JUNIOR | Z26: MARCO AURELIO NOLETO MENDES DA SILVA | AA26: DPL - 1º | AB26: 4600024691 | AC26: EVANDILSON VIANA DOS SANTOS | AD26: SOLICITAÇÃO CLIENTE|CLIENTE | AE26: EXCLUSIVA DA DISTRIBUIDORA | AM26: NOROESTE | AN26: =AP26&"-"&AO26 -> BCT-BACURITUBA | AO26: BACURITUBA | AP26: BCT | AW26: SAO LUIS | AX26: =INDEX(AY26:BA26,RANDBETWEEN(1,3)) -> RENAN CUNHA | AY26: SERGIO SANTOS | AZ26: RENAN CUNHA | BA26: GABRIEL RODRIGUES
A27: NIV | B27: MANUTENÇÃO | C27: 190 | D27: =TODAY()+C27 -> 46456 | E27: ALINEZ MARTINS RABELO COSTA | F27: JEFFERSON CARLOS ARAUJO DOS REIS | G27: DPL - 1º | H27: 4600024693 | I27: JOILSON PINHEIRO CASTRO | J27: DANILO ARRAES DOS SANTOS JACINTO | K27: RICARDO DOS ANJOS LIMA | L27: DPL - 1º | M27: 4600024693 | N27: JOSE MARCIANO SILVA | O27: RENAN ACCIOLY PIMENTEL | P27: JOSÉ TARCÍSIO FONTELES NETO | Q27: DPL - 3º | R27: 4600024692 | S27: LUIS FELIPE MUNIZ DOS SANTOS SOUSA | T27: LUCIO DANIEL SOARES DOS SANTOS | U27: ADRIANNO BENEDICTO RABELO AQUINO | V27: CGB - 1° | W27: 4600026661 | X27: ANDERSON APOLIANO | Y27: SIDNEY CORREA DE ALMEIDA JUNIOR | Z27: JOCIMAR GOMES MAGALHAES JUNIOR | AA27: DPL - 1º | AB27: 4600024691 | AC27: PAULO DE TARSO DOS SANTOS COSTA | AD27: PLANO DETERMINATIVO|INTERNO | AE27: EXCLUSIVA DA DISTRIBUIDORA | AM27: SUL | AN27: =AP27&"-"&AO27 -> BLS-BALSAS | AO27: BALSAS | AP27: BLS
A28: OCP | B28: MANUTENÇÃO | C28: 175 | D28: =TODAY()+C28 -> 46441 | E28: ALINEZ MARTINS RABELO COSTA | F28: JEFFERSON CARLOS ARAUJO DOS REIS | G28: DPL - 1º | H28: 4600024693 | I28: JOILSON PINHEIRO CASTRO | J28: DANILO ARRAES DOS SANTOS JACINTO | K28: RICARDO DOS ANJOS LIMA | L28: DPL - 1º | M28: 4600024693 | N28: JOSE MARCIANO SILVA | O28: RENAN ACCIOLY PIMENTEL | P28: JOSÉ TARCÍSIO FONTELES NETO | Q28: DPL - 3º | R28: 4600024692 | S28: LUIS FELIPE MUNIZ DOS SANTOS SOUSA | T28: LUCIO DANIEL SOARES DOS SANTOS | U28: ADRIANNO BENEDICTO RABELO AQUINO | V28: CGB - 1° | W28: 4600026661 | X28: VERIFICAR NO SGO/SISCO | Y28: SIDNEY CORREA DE ALMEIDA JUNIOR | Z28: JOCIMAR GOMES MAGALHAES JUNIOR | AA28: DPL - 1º | AB28: 4600024691 | AC28: PAULO DE TARSO DOS SANTOS COSTA | AD28: PLANO DETERMINATIVO|INTERNO | AE28: EXCLUSIVA DA DISTRIBUIDORA | AM28: LESTE | AN28: =AP28&"-"&AO28 -> BJU-BARAO DE GRAJAU | AO28: BARAO DE GRAJAU | AP28: BJU
A29: ODS | B29: EXPANSÃO | C29: 160 | D29: =TODAY()+C29 -> 46426 | E29: ALINEZ MARTINS RABELO COSTA | F29: JOSELILSON DE SOUZA LIMA | G29: DPL - 1º | H29: 4600024693 | I29: =IFERROR(VLOOKUP(#REF!,DADOS!AW:AX,2,0),"Verificar tabela da norte") -> Verificar tabela da norte | J29: DANILO ARRAES DOS SANTOS JACINTO | K29: JANDERSON PAIXÃO DOS SANTOS | L29: DPL - 1º | M29: 4600024693 | N29: VERIFICAR NO SGO/SISCO | O29: RENAN ACCIOLY PIMENTEL | P29: LETICIA CRISTINA DA SILVA BARATA | Q29: DPL - 3º | R29: 4600024692 | S29: VERIFICAR NO SGO/SISCO | T29: LUCIO DANIEL SOARES DOS SANTOS | U29: ALEXANDRE LUIS SILVA SANTOS | V29: CGB - 1° | W29: 4600026661 | X29: VERIFICAR NO SGO/SISCO | Y29: SIDNEY CORREA DE ALMEIDA JUNIOR | Z29: MARCO AURELIO NOLETO MENDES DA SILVA | AA29: DPL - 1º | AB29: 4600024691 | AC29: VERIFICAR NO SGO/SISCO | AM29: CENTRO | AN29: =AP29&"-"&AO29 -> BDC-BARRA DO CORDA | AO29: BARRA DO CORDA | AP29: BDC
A30: PMC | B30: EXPANSÃO | C30: 220 | D30: =TODAY()+C30 -> 46486 | E30: ALINEZ MARTINS RABELO COSTA | F30: JOSELILSON DE SOUZA LIMA | G30: DPL - 1º | H30: 4600024693 | I30: =IFERROR(VLOOKUP(#REF!,DADOS!AW:AX,2,0),"Verificar tabela da norte") -> Verificar tabela da norte | J30: DANILO ARRAES DOS SANTOS JACINTO | K30: JANDERSON PAIXÃO DOS SANTOS | L30: DPL - 1º | M30: 4600024693 | N30: VERIFICAR NO SGO/SISCO | O30: RENAN ACCIOLY PIMENTEL | P30: LETICIA CRISTINA DA SILVA BARATA | Q30: DPL - 3º | R30: 4600024692 | S30: VERIFICAR NO SGO/SISCO | T30: LUCIO DANIEL SOARES DOS SANTOS | U30: ALEXANDRE LUIS SILVA SANTOS | V30: CGB - 1° | W30: 4600026661 | X30: VERIFICAR NO SGO/SISCO | Y30: SIDNEY CORREA DE ALMEIDA JUNIOR | Z30: MARCO AURELIO NOLETO MENDES DA SILVA | AA30: DPL - 1º | AB30: 4600024691 | AC30: VERIFICAR NO SGO/SISCO | AM30: NORTE | AN30: =AP30&"-"&AO30 -> BRN-BARREIRINHAS | AO30: BARREIRINHAS | AP30: BRN
A31: REF | B31: EXPANSÃO | C31: 175 | D31: =TODAY()+C31 -> 46441 | E31: ALINEZ MARTINS RABELO COSTA | F31: JOSELILSON DE SOUZA LIMA | G31: DPL - 1º | H31: 4600024693 | I31: =IFERROR(VLOOKUP(#REF!,DADOS!AW:AX,2,0),"Verificar tabela da norte") -> Verificar tabela da norte | J31: DANILO ARRAES DOS SANTOS JACINTO | K31: JANDERSON PAIXÃO DOS SANTOS | L31: DPL - 1º | M31: 4600024693 | N31: VERIFICAR NO SGO/SISCO | O31: RENAN ACCIOLY PIMENTEL | P31: LETICIA CRISTINA DA SILVA BARATA | Q31: DPL - 3º | R31: 4600024692 | S31: VERIFICAR NO SGO/SISCO | T31: LUCIO DANIEL SOARES DOS SANTOS | U31: ALEXANDRE LUIS SILVA SANTOS | V31: CGB - 1° | W31: 4600026661 | X31: VERIFICAR NO SGO/SISCO | Y31: SIDNEY CORREA DE ALMEIDA JUNIOR | Z31: MARCO AURELIO NOLETO MENDES DA SILVA | AA31: DPL - 1º | AB31: 4600024691 | AC31: VERIFICAR NO SGO/SISCO | AM31: CENTRO | AN31: =AP31&"-"&AO31 -> BVM-BELA VISTA DO MARANHAO | AO31: BELA VISTA DO MARANHAO | AP31: BVM
A32: REG | B32: EXPANSÃO | C32: 190 | D32: =TODAY()+C32 -> 46456 | E32: ALINEZ MARTINS RABELO COSTA | F32: JOSELILSON DE SOUZA LIMA | G32: DPL - 1º | H32: 4600024693 | I32: =IFERROR(VLOOKUP(#REF!,DADOS!AW:AX,2,0),"Verificar tabela da norte") -> Verificar tabela da norte | J32: DANILO ARRAES DOS SANTOS JACINTO | K32: JANDERSON PAIXÃO DOS SANTOS | L32: DPL - 1º | M32: 4600024693 | N32: NATANAEL FERRAZ FILHO | O32: RENAN ACCIOLY PIMENTEL | P32: LETICIA CRISTINA DA SILVA BARATA | Q32: DPL - 3º | R32: 4600024692 | S32: LUCAS SILVA OLIVEIRA | T32: LUCIO DANIEL SOARES DOS SANTOS | U32: ALEXANDRE LUIS SILVA SANTOS | V32: CGB - 1° | W32: 4600026661 | X32: OTTON CILIO CORREA DA SILVA | Y32: SIDNEY CORREA DE ALMEIDA JUNIOR | Z32: MARCO AURELIO NOLETO MENDES DA SILVA | AA32: DPL - 1º | AB32: 4600024691 | AC32: ALISON PINHEIRO | AD32: PLANO DETERMINATIVO|INTERNO | AE32: EXCLUSIVA DA DISTRIBUIDORA | AM32: LESTE | AN32: =AP32&"-"&AO32 -> BGU-BELAGUA | AO32: BELAGUA | AP32: BGU
A33: SEG | B33: MANUTENÇÃO | C33: 190 | D33: =TODAY()+C33 -> 46456 | E33: ALINEZ MARTINS RABELO COSTA | F33: JEFFERSON CARLOS ARAUJO DOS REIS | G33: DPL - 1º | H33: 4600024693 | I33: JOILSON PINHEIRO CASTRO | J33: DANILO ARRAES DOS SANTOS JACINTO | K33: RICARDO DOS ANJOS LIMA | L33: DPL - 1º | M33: 4600024693 | N33: SANDRO HENRIQUE GOMES | O33: RENAN ACCIOLY PIMENTEL | P33: JOSÉ TARCÍSIO FONTELES NETO | Q33: DPL - 3º | R33: 4600024692 | S33: ADRIANO MENDES COSTA | T33: LUCIO DANIEL SOARES DOS SANTOS | U33: ADRIANNO BENEDICTO RABELO AQUINO | V33: CGB - 1° | W33: 4600026661 | X33: NEYVALDO LOPES MORAES | Y33: SIDNEY CORREA DE ALMEIDA JUNIOR | Z33: JOCIMAR GOMES MAGALHAES JUNIOR | AA33: DPL - 1º | AB33: 4600024691 | AC33: ARLAN DE SOUSA AMARANTE | AD33: PLANO DETERMINATIVO|INTERNO | AE33: EXCLUSIVA DA DISTRIBUIDORA | AM33: LESTE | AN33: =AP33&"-"&AO33 -> BLE-BENEDITO LEITE | AO33: BENEDITO LEITE | AP33: BLE
A34: SEQ | B34: MANUTENÇÃO | C34: 175 | D34: =TODAY()+C34 -> 46441 | E34: ALINEZ MARTINS RABELO COSTA | F34: JEFFERSON CARLOS ARAUJO DOS REIS | G34: DPL - 1º | H34: 4600024693 | I34: JOILSON PINHEIRO CASTRO | J34: DANILO ARRAES DOS SANTOS JACINTO | K34: RICARDO DOS ANJOS LIMA | L34: DPL - 1º | M34: 4600024693 | N34: VERIFICAR NO SGO/SISCO | O34: RENAN ACCIOLY PIMENTEL | P34: JOSÉ TARCÍSIO FONTELES NETO | Q34: DPL - 3º | R34: 4600024692 | S34: ADRIANO ARAUJO FERNANDES | T34: LUCIO DANIEL SOARES DOS SANTOS | U34: ADRIANNO BENEDICTO RABELO AQUINO | V34: CGB - 1° | W34: 4600026661 | X34: ANDERSON APOLIANO | Y34: SIDNEY CORREA DE ALMEIDA JUNIOR | Z34: JOCIMAR GOMES MAGALHAES JUNIOR | AA34: DPL - 1º | AB34: 4600024691 | AC34: SARAH BRITO DE MOURA / PAULO DE TARSO | AE34: EXCLUSIVA DA DISTRIBUIDORA | AM34: NOROESTE | AN34: =AP34&"-"&AO34 -> BQM-BEQUIMAO | AO34: BEQUIMAO | AP34: BQM
A35: SID | B35: EXPANSÃO | C35: 175 | D35: =TODAY()+C35 -> 46441 | E35: ALINEZ MARTINS RABELO COSTA | F35: JOSELILSON DE SOUZA LIMA | G35: DPL - 1º | H35: 4600024693 | I35: =IFERROR(VLOOKUP(#REF!,DADOS!AW:AX,2,0),"Verificar tabela da norte") -> Verificar tabela da norte | J35: DANILO ARRAES DOS SANTOS JACINTO | K35: JANDERSON PAIXÃO DOS SANTOS | L35: DPL - 1º | M35: 4600024693 | N35: CARLOS EDUARDO MONTENEGRO | O35: RENAN ACCIOLY PIMENTEL | P35: LETICIA CRISTINA DA SILVA BARATA | Q35: DPL - 3º | R35: 4600024692 | S35: ADRIANO MENDES COSTA | T35: LUCIO DANIEL SOARES DOS SANTOS | U35: ALEXANDRE LUIS SILVA SANTOS | V35: CGB - 1° | W35: 4600026661 | X35: DAYLLING ALMEIDA | GESIMIEL SIVA | Y35: SIDNEY CORREA DE ALMEIDA JUNIOR | Z35: MARCO AURELIO NOLETO MENDES DA SILVA | AA35: DPL - 1º | AB35: 4600024691 | AC35: RODRIGO PEREIRA DE ALMEIDA | AD35: SOLICITAÇÃO CLIENTE|CLIENTE | AE35: Exclusiva do Interessado | AM35: CENTRO | AN35: =AP35&"-"&AO35 -> BEM-BERNARDO DO MEARIM | AO35: BERNARDO DO MEARIM | AP35: BEM
A36: SLS | B36: EXPANSÃO | C36: 175 | D36: =TODAY()+C36 -> 46441 | E36: ALINEZ MARTINS RABELO COSTA | F36: JOSELILSON DE SOUZA LIMA | G36: DPL - 1º | H36: 4600024693 | I36: =IFERROR(VLOOKUP(#REF!,DADOS!AW:AX,2,0),"Verificar tabela da norte") -> Verificar tabela da norte | J36: DANILO ARRAES DOS SANTOS JACINTO | K36: JANDERSON PAIXÃO DOS SANTOS | L36: DPL - 1º | M36: 4600024693 | N36: VERIFICAR NO SGO/SISCO | O36: RENAN ACCIOLY PIMENTEL | P36: LETICIA CRISTINA DA SILVA BARATA | Q36: DPL - 3º | R36: 4600024692 | S36: VERIFICAR NO SGO/SISCO | T36: LUCIO DANIEL SOARES DOS SANTOS | U36: ALEXANDRE LUIS SILVA SANTOS | V36: CGB - 1° | W36: 4600026661 | X36: VERIFICAR NO SGO/SISCO | Y36: SIDNEY CORREA DE ALMEIDA JUNIOR | Z36: MARCO AURELIO NOLETO MENDES DA SILVA | AA36: DPL - 1º | AB36: 4600024691 | AC36: VERIFICAR NO SGO/SISCO | AM36: NOROESTE | AN36: =AP36&"-"&AO36 -> BVG-BOA VISTA DO GURUPI | AO36: BOA VISTA DO GURUPI | AP36: BVG
A37: SMC | B37: EXPANSÃO | C37: 175 | D37: =TODAY()+C37 -> 46441 | E37: ALINEZ MARTINS RABELO COSTA | F37: JOSELILSON DE SOUZA LIMA | G37: DPL - 1º | H37: 4600024693 | I37: =IFERROR(VLOOKUP(#REF!,DADOS!AW:AX,2,0),"Verificar tabela da norte") -> Verificar tabela da norte | J37: DANILO ARRAES DOS SANTOS JACINTO | K37: JANDERSON PAIXÃO DOS SANTOS | L37: DPL - 1º | M37: 4600024693 | N37: VERIFICAR NO SGO/SISCO | O37: RENAN ACCIOLY PIMENTEL | P37: LETICIA CRISTINA DA SILVA BARATA | Q37: DPL - 3º | R37: 4600024692 | S37: VERIFICAR NO SGO/SISCO | T37: LUCIO DANIEL SOARES DOS SANTOS | U37: ALEXANDRE LUIS SILVA SANTOS | V37: CGB - 1° | W37: 4600026661 | X37: VERIFICAR NO SGO/SISCO | Y37: SIDNEY CORREA DE ALMEIDA JUNIOR | Z37: MARCO AURELIO NOLETO MENDES DA SILVA | AA37: DPL - 1º | AB37: 4600024691 | AC37: VERIFICAR NO SGO/SISCO | AM37: CENTRO | AN37: =AP37&"-"&AO37 -> BJD-BOM JARDIM | AO37: BOM JARDIM | AP37: BJD
A38: TRI | B38: EXPANSÃO | C38: 220 | D38: =TODAY()+C38 -> 46486 | E38: ALINEZ MARTINS RABELO COSTA | F38: JOSELILSON DE SOUZA LIMA | G38: DPL - 1º | H38: 4600024693 | I38: =IFERROR(VLOOKUP(#REF!,DADOS!AW:AX,2,0),"Verificar tabela da norte") -> Verificar tabela da norte | J38: DANILO ARRAES DOS SANTOS JACINTO | K38: JANDERSON PAIXÃO DOS SANTOS | L38: DPL - 1º | M38: 4600024693 | N38: VERIFICAR NO SGO/SISCO | O38: RENAN ACCIOLY PIMENTEL | P38: LETICIA CRISTINA DA SILVA BARATA | Q38: DPL - 3º | R38: 4600024692 | S38: VERIFICAR NO SGO/SISCO | T38: LUCIO DANIEL SOARES DOS SANTOS | U38: ALEXANDRE LUIS SILVA SANTOS | V38: CGB - 1° | W38: 4600026661 | X38: NEYVALDO LOPES MORAES | Y38: SIDNEY CORREA DE ALMEIDA JUNIOR | Z38: MARCO AURELIO NOLETO MENDES DA SILVA | AA38: DPL - 1º | AB38: 4600024691 | AC38: VERIFICAR NO SGO/SISCO | AM38: SUL | AN38: =AP38&"-"&AO38 -> BJS-BOM JESUS DAS SELVAS | AO38: BOM JESUS DAS SELVAS | AP38: BJS
A39: UNI | B39: EXPANSÃO | C39: 175 | D39: =TODAY()+C39 -> 46441 | E39: ALINEZ MARTINS RABELO COSTA | F39: JOSELILSON DE SOUZA LIMA | G39: DPL - 1º | H39: 4600024693 | I39: =IFERROR(VLOOKUP(#REF!,DADOS!AW:AX,2,0),"Verificar tabela da norte") -> Verificar tabela da norte | J39: DANILO ARRAES DOS SANTOS JACINTO | K39: JANDERSON PAIXÃO DOS SANTOS | L39: DPL - 1º | M39: 4600024693 | N39: NATANAEL FERRAZ FILHO | O39: RENAN ACCIOLY PIMENTEL | P39: LETICIA CRISTINA DA SILVA BARATA | Q39: DPL - 3º | R39: 4600024692 | S39: JOSÉ DE ARAUJO ANDRADE JUNIOR | T39: LUCIO DANIEL SOARES DOS SANTOS | U39: ALEXANDRE LUIS SILVA SANTOS | V39: CGB - 1° | W39: 4600026661 | X39: FRANCISCO FRAZÃO JUNIOR | Y39: SIDNEY CORREA DE ALMEIDA JUNIOR | Z39: MARCO AURELIO NOLETO MENDES DA SILVA | AA39: DPL - 1º | AB39: 4600024691 | AC39: PEDRO VICTOR DE SOUSA MOURA | AD39: SOLICITAÇÃO CLIENTE|CLIENTE | AE39: EXCLUSIVA DA DISTRIBUIDORA | AM39: CENTRO | AN39: =AP39&"-"&AO39 -> BLU-BOM LUGAR | AO39: BOM LUGAR | AP39: BLU
A40: UNP | B40: EXPANSÃO | C40: 190 | D40: =TODAY()+C40 -> 46456 | E40: ALINEZ MARTINS RABELO COSTA | F40: JOSELILSON DE SOUZA LIMA | G40: DPL - 1º | H40: 4600024693 | I40: =IFERROR(VLOOKUP(#REF!,DADOS!AW:AX,2,0),"Verificar tabela da norte") -> Verificar tabela da norte | J40: DANILO ARRAES DOS SANTOS JACINTO | K40: JANDERSON PAIXÃO DOS SANTOS | L40: DPL - 1º | M40: 4600024693 | N40: NATANAEL FERRAZ FILHO | O40: RENAN ACCIOLY PIMENTEL | P40: LETICIA CRISTINA DA SILVA BARATA | Q40: DPL - 3º | R40: 4600024692 | S40: JOSÉ DE ARAUJO ANDRADE JUNIOR | T40: LUCIO DANIEL SOARES DOS SANTOS | U40: ALEXANDRE LUIS SILVA SANTOS | V40: CGB - 1° | W40: 4600026661 | X40: FRANCISCO FRAZÃO JUNIOR | Y40: SIDNEY CORREA DE ALMEIDA JUNIOR | Z40: MARCO AURELIO NOLETO MENDES DA SILVA | AA40: DPL - 1º | AB40: 4600024691 | AC40: PEDRO VICTOR DE SOUSA MOURA | AD40: SOLICITAÇÃO CLIENTE|CLIENTE | AE40: EXCLUSIVA DA DISTRIBUIDORA | AM40: LESTE | AN40: =AP40&"-"&AO40 -> BJO-BREJO | AO40: BREJO | AP40: BJO
A41: UNR | B41: EXPANSÃO | C41: 190 | D41: =TODAY()+C41 -> 46456 | E41: ALINEZ MARTINS RABELO COSTA | F41: JOSELILSON DE SOUZA LIMA | G41: DPL - 1º | H41: 4600024693 | I41: =IFERROR(VLOOKUP(#REF!,DADOS!AW:AX,2,0),"Verificar tabela da norte") -> Verificar tabela da norte | J41: DANILO ARRAES DOS SANTOS JACINTO | K41: JANDERSON PAIXÃO DOS SANTOS | L41: DPL - 1º | M41: 4600024693 | N41: NATANAEL FERRAZ FILHO | O41: RENAN ACCIOLY PIMENTEL | P41: LETICIA CRISTINA DA SILVA BARATA | Q41: DPL - 3º | R41: 4600024692 | S41: JOSÉ DE ARAUJO ANDRADE JUNIOR | T41: LUCIO DANIEL SOARES DOS SANTOS | U41: ALEXANDRE LUIS SILVA SANTOS | V41: CGB - 1° | W41: 4600026661 | X41: FRANCISCO FRAZÃO JUNIOR | Y41: SIDNEY CORREA DE ALMEIDA JUNIOR | Z41: MARCO AURELIO NOLETO MENDES DA SILVA | AA41: DPL - 1º | AB41: 4600024691 | AC41: PEDRO VICTOR DE SOUSA MOURA | AD41: SOLICITAÇÃO CLIENTE|CLIENTE | AE41: EXCLUSIVA DA DISTRIBUIDORA | AM41: CENTRO | AN41: =AP41&"-"&AO41 -> BJA-BREJO DE AREIA | AO41: BREJO DE AREIA | AP41: BJA
AM42: LESTE | AN42: =AP42&"-"&AO42 -> BIV-BURITI | AO42: BURITI | AP42: BIV
AM43: LESTE | AN43: =AP43&"-"&AO43 -> BBR-BURITI BRAVO | AO43: BURITI BRAVO | AP43: BBR
AM44: SUL | AN44: =AP44&"-"&AO44 -> BCP-BURITICUPU | AO44: BURITICUPU | AP44: BCP
AM45: SUL | AN45: =AP45&"-"&AO45 -> BUT-BURITIRANA | AO45: BURITIRANA | AP45: BUT
AM46: NORTE | AN46: =AP46&"-"&AO46 -> CGR-CACHOEIRA GRANDE | AO46: CACHOEIRA GRANDE | AP46: CGR
AM47: NOROESTE | AN47: =AP47&"-"&AO47 -> CJO-CAJAPIO | AO47: CAJAPIO | AP47: CJO
AM48: NOROESTE | AN48: =AP48&"-"&AO48 -> CJI-CAJARI | AO48: CAJARI | AP48: CJI
AM49: SUL | AN49: =AP49&"-"&AO49 -> CAM-CAMPESTRE DO MARANHAO | AO49: CAMPESTRE DO MARANHAO | AP49: CAM
AM50: NOROESTE | AN50: =AP50&"-"&AO50 -> CAN-CANDIDO MENDES | AO50: CANDIDO MENDES | AP50: CAN
AM51: CENTRO | AN51: =AP51&"-"&AO51 -> CHE-CANTANHEDE | AO51: CANTANHEDE | AP51: CHE
AM52: CENTRO | AN52: =AP52&"-"&AO52 -> CPN-CAPINZAL DO NORTE | AO52: CAPINZAL DO NORTE | AP52: CPN
AM53: SUL | AN53: =AP53&"-"&AO53 -> CAR-CAROLINA | AO53: CAROLINA | AP53: CAR
... AM224: CENTRO | AN224: =AP224&"-"&AO224 -> ZDC-ZE DOCA | AO224: ZE DOCA | AP224: ZDC
